Workbook
Name _1___Excel_BuiltIn__FilterDatabase_1_1: #REF!
Name _1___Excel_BuiltIn__FilterDatabase_1_1: #REF!
Name _10__Excel_BuiltIn__FilterDatabase_5_1: #REF!
Name _11_Excel_BuiltIn__FilterDatabase_1_1: #REF!
Name _12_Excel_BuiltIn__FilterDatabase_2_1: #REF!
Name _13_Excel_BuiltIn__FilterDatabase_3_1: #REF!
Name _14_Excel_BuiltIn__FilterDatabase_4_1: #REF!
Name _15_Excel_BuiltIn__FilterDatabase_5_1: #REF!
Name _1Excel_BuiltIn__FilterDatabase_1_1: #REF!
Name _2___Excel_BuiltIn__FilterDatabase_2_1: #REF!
Name _2Excel_BuiltIn__FilterDatabase_2_1: #REF!
Name _3___Excel_BuiltIn__FilterDatabase_3_1: #REF!
Name _3Excel_BuiltIn__FilterDatabase_3_1: #REF!
Name _4___Excel_BuiltIn__FilterDatabase_4_1: #REF!
Name _4Excel_BuiltIn__FilterDatabase_4_1: #REF!
Name _5___Excel_BuiltIn__FilterDatabase_5_1: #REF!
Name _5Excel_BuiltIn__FilterDatabase_5_1: #REF!
Name _6__Excel_BuiltIn__FilterDatabase_1_1: #REF!
Name _7__Excel_BuiltIn__FilterDatabase_2_1: #REF!
Name _8__Excel_BuiltIn__FilterDatabase_3_1: #REF!
Name _9__Excel_BuiltIn__FilterDatabase_4_1: #REF!
Name a: #REF!
Name a: #REF!
Name aa: #REF!
Name AAAAAA: #REF!
Name AAAAAA: #REF!
Name aasqsadh: #REF!
Name AB: #REF!
Name ABRIL: #REF!
Name AFAM: #REF!
Name AFP: #REF!
Name AFP: #REF!
Name AGOSTO: #REF!
Name ASIG_FAM: #REF!
Name BAGO: #REF!
Name BANCO: #REF!
Name BASE: #REF!
Name BASE_AFECTA: #REF!
Name BASE_RETENCION: #REF!
Name BASEJULIO: #REF!
Name BASEJUNIO: #REF!
Name BASEMAYO: #REF!
Name BASESEP: #REF!
Name BASICO: #REF!
Name BOCTUBRE: #REF!
Name BONO: #REF!
Name cadddd: #REF!
Name cadddd: #REF!
Name Caja: #REF!
Name CODIGO: #REF!
Name CONSOLIDADO: #REF!
Name CTS: #REF!
Name CUENTA: #REF!
Name DATA: #REF!
Name DATA: #REF!
Name DATASEP: #REF!
Name DEPOSITO: #REF!
Name DNI: #REF!
Name ESSALUD: #REF!
Name Excel_BuiltIn__FilterDatabase_1: #REF!

Sheet UTILIDADES 2025
AA1: =+ROUND(V1/$AA$3,2) -> 0
C2: CITIKOLD
C3: PLANILLA DE UTILIDADES 2025 | M3: ok | N3: ok | Z3: TC | AA3: 3.435
C4: 1 | D4: 2 | E4: 3 | F4: 4 | I4: 5 | J4: 6 | M4: 7 | N4: 8 | O4: 9 | P4: 10 | Q4: 11 | R4: 12 | T4: 13 | V4: 14
C5: Nº+C5:M6 | D5: DNI | E5: APELLIDOS Y NOMBRES | F5: CARGO | G5: AREA | H5: CENTRO DE COSTO | I5: FECHA DE INGRESO | J5: FECHA DE CESE | K5: FECHA DE INGRESO | L5: FECHA DE CESE | M5: Nº dias Efectivos Laborados | N5: Total de Remuneraciones | O5: ESTADO | P5: EN FUNCION A DIAS | Q5: EN FUNCION A REMUNERACIONES | R5: TOTAL DE UTILIDADES | S5: IR 5ta CATEGORIA | T5: RETENCION JUDICIAL | U5: PRESTAMO / OTROS DESCUENTOS | V5: UTILIDADES NETAS | Y5: TRAMO ALCANZADO | AA5: DOLARES
C7: 1 | D7: 07262343 | E7: CIEZA AGUILAR CESAR AUGUSTO | F7: CHOFER | G7: ADMINISTRACION | H7: ADMINISTRACION | I7: =VLOOKUP(D7,'DÍAS EFECTIVOS LABORADOS 2025'!B:F,3,0) -> 43357 | M7: =VLOOKUP(D7,'DÍAS EFECTIVOS LABORADOS 2025'!B:O,14,0) -> 231 | N7: =+ROUND(VLOOKUP(D7,'INGRESOS 2025'!$B$7:$V$159,21,0),2) -> 57700.7 | O7: ACTIVO | P7: =$N$103*M7 -> 11372.668 | Q7: =$N$104*N7 -> 5731.2636 | R7: =+ROUND(P7+Q7,2) -> 17103.93 | S7: =ROUND(HLOOKUP(D7,'5ta'!$C$7:$CF$118,112,0),2) -> 1490.95 | U7: =5856.36+5000 -> 10856.36 | V7: =+ROUND(R7-T7-S7-U7,2) -> 4756.62 | X7: =HLOOKUP(D7,'5ta'!$C$7:$CG$139,133,0) -> FALSE | Y7: =HLOOKUP(D7,'5ta'!$C$7:$CF$145,134,0) -> 08% - 14% | Z7: =VLOOKUP(D7,'[1]0220262'!$E$12:$AD$94,26,0) -> 0 | AB7: =VLOOKUP(D7,'[2]Archivo Excel Haberes Input'!$K$11:$K$80,1,0) -> 07262343
C8: 2 | D8: 07537953 | E8: SALAZAR DE LA ROCHA JUAN CARLOS GERMAN | F8: GERENTE GENERAL | G8: GERENCIA GENERAL | H8: VARIOS | I8: =VLOOKUP(D8,'DÍAS EFECTIVOS LABORADOS 2025'!B:F,3,0) -> 43003 | M8: =VLOOKUP(D8,'DÍAS EFECTIVOS LABORADOS 2025'!B:O,14,0) -> 222 | N8: =+ROUND(VLOOKUP(D8,'INGRESOS 2025'!$B$7:$V$159,21,0),2) -> 574648.72 | O8: ACTIVO | P8: =$N$103*M8 -> 10929.577 | Q8: =$N$104*N8 -> 57078.394 | R8: =+ROUND(P8+Q8,2) -> 68007.97 | S8: =ROUND(HLOOKUP(D8,'5ta'!$C$7:$CF$118,112,0),2) -> 20402.39 | V8: =+ROUND(R8-T8-S8-U8,2) -> 47605.58 | W8: =+Y8*R8-S8 -> 0.001 | X8: =HLOOKUP(D8,'5ta'!$C$7:$CG$139,133,0) -> TRUE | Y8: =HLOOKUP(D8,'5ta'!$C$7:$CF$135,129,0) -> 0.3 | Z8: =VLOOKUP(D8,'[1]0220262'!$E$12:$AD$94,26,0) -> 0 | AB8: =VLOOKUP(D8,'[2]Archivo Excel Haberes Input'!$K$11:$K$80,1,0) -> 07537953
C9: 3 | D9: 08693248 | E9: IZARRA CARRASCO IRINA KAREM | F9: ANALISTA SENIOR DE DOCUMENTACIÓN | G9: DOCUMENTACION-VISTO BUENO | H9: OPERACIONES | I9: =VLOOKUP(D9,'DÍAS EFECTIVOS LABORADOS 2025'!B:F,3,0) -> 43160 | M9: =VLOOKUP(D9,'DÍAS EFECTIVOS LABORADOS 2025'!B:O,14,0) -> 235 | N9: =+ROUND(VLOOKUP(D9,'INGRESOS 2025'!$B$7:$V$159,21,0),2) -> 78353.36 | O9: ACTIVO | P9: =$N$103*M9 -> 11569.597 | Q9: =$N$104*N9 -> 7782.6398 | R9: =+ROUND(P9+Q9,2) -> 19352.24 | S9: =ROUND(HLOOKUP(D9,'5ta'!$C$7:$CF$118,112,0),2) -> 2709.31 | V9: =+ROUND(R9-T9-S9-U9,2) -> 16642.93 | W9: =+Y9*R9-S9 -> 0.0036 | X9: =HLOOKUP(D9,'5ta'!$C$7:$CG$139,133,0) -> TRUE | Y9: =HLOOKUP(D9,'5ta'!$C$7:$CF$135,129,0) -> 0.14 | Z9: =VLOOKUP(D9,'[1]0220262'!$E$12:$AD$94,26,0) -> 0 | AB9: =VLOOKUP(D9,'[2]Archivo Excel Haberes Input'!$K$11:$K$80,1,0) -> 08693248
C10: 4 | D10: 08887801 | E10: RUIZ SALCEDO MARIA DE LOURDES | F10: ASESOR COMERCIAL IMPO | G10: COMERCIAL- VENTAS | H10: VENTAS | I10: =VLOOKUP(D10,'DÍAS EFECTIVOS LABORADOS 2025'!B:F,3,0) -> 43003 | M10: =VLOOKUP(D10,'DÍAS EFECTIVOS LABORADOS 2025'!B:O,14,0) -> 222 | N10: =+ROUND(VLOOKUP(D10,'INGRESOS 2025'!$B$7:$V$159,21,0),2) -> 181223.64 | O10: ACTIVO | P10: =$N$103*M10 -> 10929.577 | Q10: =$N$104*N10 -> 18000.483 | R10: =+ROUND(P10+Q10,2) -> 28930.06 | S10: =ROUND(HLOOKUP(D10,'5ta'!$C$7:$CF$118,112,0),2) -> 4918.11 | V10: =+ROUND(R10-T10-S10-U10,2) -> 24011.95 | W10: =+Y10*R10-S10 -> 0.0002 | X10: =HLOOKUP(D10,'5ta'!$C$7:$CG$139,133,0) -> TRUE | Y10: =HLOOKUP(D10,'5ta'!$C$7:$CF$135,129,0) -> 0.17 | Z10: =VLOOKUP(D10,'[1]0220262'!$E$12:$AD$94,26,0) -> 0 | AB10: =VLOOKUP(D10,'[2]Archivo Excel Haberes Input'!$K$11:$K$80,1,0) -> 08887801
C11: 5 | D11: 09335023 | E11: AYOS JUNGBLUTH MARIANA | F11: ASESOR COMERCIAL EXPO | G11: COMERCIAL- VENTAS | H11: VENTAS | I11: =VLOOKUP(D11,'DÍAS EFECTIVOS LABORADOS 2025'!B:F,3,0) -> 43003 | M11: =VLOOKUP(D11,'DÍAS EFECTIVOS LABORADOS 2025'!B:O,14,0) -> 227 | N11: =+ROUND(VLOOKUP(D11,'INGRESOS 2025'!$B$7:$V$159,21,0),2) -> 179497.7 | O11: ACTIVO | P11: =$N$103*M11 -> 11175.738 | Q11: =$N$104*N11 -> 17829.05 | R11: =+ROUND(P11+Q11,2) -> 29004.79 | S11: =ROUND(HLOOKUP(D11,'5ta'!$C$7:$CF$118,112,0),2) -> 4930.81 | V11: =+ROUND(R11-T11-S11-U11,2) -> 24073.98 | W11: =+Y11*R11-S11 -> 0.0043 | X11: =HLOOKUP(D11,'5ta'!$C$7:$CG$139,133,0) -> TRUE | Y11: =HLOOKUP(D11,'5ta'!$C$7:$CF$135,129,0) -> 0.17 | Z11: =VLOOKUP(D11,'[1]0220262'!$E$12:$AD$94,26,0) -> 0 | AB11: =VLOOKUP(D11,'[2]Archivo Excel Haberes Input'!$K$11:$K$80,1,0) -> 09335023
C12: 6 | D12: 09410158 | E12: BONATTI CARRASCO JORGE LUIS | F12: ANALISTA SENIOR DE DOCUMENTACIÓN | G12: DOCUMENTACION-VISTO BUENO | H12: OPERACIONES | I12: =VLOOKUP(D12,'DÍAS EFECTIVOS LABORADOS 2025'!B:F,3,0) -> 42985 | M12: =VLOOKUP(D12,'DÍAS EFECTIVOS LABORADOS 2025'!B:O,14,0) -> 227 | N12: =+ROUND(VLOOKUP(D12,'INGRESOS 2025'!$B$7:$V$159,21,0),2) -> 71990.24 | O12: ACTIVO | P12: =$N$103*M12 -> 11175.738 | Q12: =$N$104*N12 -> 7150.6073 | R12: =+ROUND(P12+Q12,2) -> 18326.35 | S12: =ROUND(HLOOKUP(D12,'5ta'!$C$7:$CF$118,112,0),2) -> 2565.69 | V12: =+ROUND(R12-T12-S12-U12,2) -> 15760.66 | W12: =+Y12*R12-S12 -> -0.001 | X12: =HLOOKUP(D12,'5ta'!$C$7:$CG$139,133,0) -> TRUE | Y12: =HLOOKUP(D12,'5ta'!$C$7:$CF$135,129,0) -> 0.14 | Z12: =VLOOKUP(D12,'[1]0220262'!$E$12:$AD$94,26,0) -> 0 | AB12: =VLOOKUP(D12,'[2]Archivo Excel Haberes Input'!$K$11:$K$80,1,0) -> 09410158
C13: 7 | D13: 09542822 | E13: CAVERO RODRIGUEZ JANNYE VERONICA | F13: CUSTOMER SERVICE SENIOR EXPO | G13: COMERCIAL- VENTAS | H13: VENTAS | I13: =VLOOKUP(D13,'DÍAS EFECTIVOS LABORADOS 2025'!B:F,3,0) -> 42985 | M13: =VLOOKUP(D13,'DÍAS EFECTIVOS LABORADOS 2025'!B:O,14,0) -> 235 | N13: =+ROUND(VLOOKUP(D13,'INGRESOS 2025'!$B$7:$V$159,21,0),2) -> 132874.03 | O13: ACTIVO | P13: =$N$103*M13 -> 11569.597 | Q13: =$N$104*N13 -> 13198.039 | R13: =+ROUND(P13+Q13,2) -> 24767.64 | S13: =ROUND(HLOOKUP(D13,'5ta'!$C$7:$CF$118,112,0),2) -> 3467.47 | V13: =+ROUND(R13-T13-S13-U13,2) -> 21300.17 | W13: =+Y13*R13-S13 -> -0.0004 | X13: =HLOOKUP(D13,'5ta'!$C$7:$CG$139,133,0) -> TRUE | Y13: =HLOOKUP(D13,'5ta'!$C$7:$CF$135,129,0) -> 0.14 | Z13: =VLOOKUP(D13,'[1]0220262'!$E$12:$AD$94,26,0) -> 0 | AB13: =VLOOKUP(D13,'[2]Archivo Excel Haberes Input'!$K$11:$K$80,1,0) -> 09542822
C14: 8 | D14: 09867320 | E14: ROTALDE DEL RIO XIMENA MARIA | F14: JEFE DE CONTROL DE EQUIPOS | G14: CONTROL DE EQUIPOS | H14: OPERACIONES | I14: =VLOOKUP(D14,'DÍAS EFECTIVOS LABORADOS 2025'!B:F,3,0) -> 42985 | M14: =VLOOKUP(D14,'DÍAS EFECTIVOS LABORADOS 2025'!B:O,14,0) -> 229 | N14: =+ROUND(VLOOKUP(D14,'INGRESOS 2025'!$B$7:$V$159,21,0),2) -> 224410.03 | O14: ACTIVO | P14: =$N$103*M14 -> 11274.203 | Q14: =$N$104*N14 -> 22290.077 | R14: =+ROUND(P14+Q14,2) -> 33564.28 | S14: =ROUND(HLOOKUP(D14,'5ta'!$C$7:$CF$118,112,0),2) -> 6192.2 | V14: =+ROUND(R14-T14-S14-U14,2) -> 27372.08 | X14: =HLOOKUP(D14,'5ta'!$C$7:$CG$139,133,0) -> FALSE | Y14: =HLOOKUP(D14,'5ta'!$C$7:$CF$145,134,0) -> 17% - 20% | Z14: =VLOOKUP(D14,'[1]0220262'!$E$12:$AD$94,26,0) -> 0 | AB14: =VLOOKUP(D14,'[2]Archivo Excel Haberes Input'!$K$11:$K$80,1,0) -> 09867320
C15: 9 | D15: 10080476 | E15: CASTILLEJOS HINOSTROZA NAYLLI MARLENE | I15: =VLOOKUP(D15,'DÍAS EFECTIVOS LABORADOS 2025'!B:F,3,0) -> 44911 | J15: =VLOOKUP(D15,'DÍAS EFECTIVOS LABORADOS 2025'!B:F,5,0) -> 45961 | M15: =VLOOKUP(D15,'DÍAS EFECTIVOS LABORADOS 2025'!B:O,14,0) -> 179 | N15: =+ROUND(VLOOKUP(D15,'INGRESOS 2025'!$B$7:$V$159,21,0),2) -> 82758.7 | O15: CESADO | P15: =$N$103*M15 -> 8812.5866 | Q15: =$N$104*N15 -> 8220.211 | R15: =+ROUND(P15+Q15,2) -> 17032.8 | V15: =+ROUND(R15-T15-S15-U15,2) -> 17032.8 | Z15: =VLOOKUP(D15,'[1]0220262'!$E$12:$AD$94,26,0) -> #N/A
C16: 10 | D16: 10346719 | E16: ROMERO ORDOÑEZ EDUARDO ARTURO | F16: ANALISTA DE DOCUMENTACIÓN | G16: DOCUMENTACION-VISTO BUENO | H16: OPERACIONES | I16: =VLOOKUP(D16,'DÍAS EFECTIVOS LABORADOS 2025'!B:F,3,0) -> 43070 | M16: =VLOOKUP(D16,'DÍAS EFECTIVOS LABORADOS 2025'!B:O,14,0) -> 240 | N16: =+ROUND(VLOOKUP(D16,'INGRESOS 2025'!$B$7:$V$159,21,0),2) -> 62197.96 | O16: ACTIVO | P16: =$N$103*M16 -> 11815.759 | Q16: =$N$104*N16 -> 6177.965 | R16: =+ROUND(P16+Q16,2) -> 17993.72 | S16: =ROUND(HLOOKUP(D16,'5ta'!$C$7:$CF$118,112,0),2) -> 2161.89 | V16: =+ROUND(R16-T16-S16-U16,2) -> 15831.83 | X16: =HLOOKUP(D16,'5ta'!$C$7:$CG$139,133,0) -> FALSE | Y16: =HLOOKUP(D16,'5ta'!$C$7:$CF$145,134,0) -> 08% - 14% | Z16: =VLOOKUP(D16,'[1]0220262'!$E$12:$AD$94,26,0) -> 0 | AB16: =VLOOKUP(D16,'[2]Archivo Excel Haberes Input'!$K$11:$K$80,1,0) -> 10346719
C17: 11 | D17: 10725704 | E17: RONCEROS GONZALES LUISA MARILIN | F17: GERENTE DE ADMNISTRACIÓN | G17: ADMINISTRACION | H17: ADMINISTRACION | I17: =VLOOKUP(D17,'DÍAS EFECTIVOS LABORADOS 2025'!B:F,3,0) -> 43382 | M17: =VLOOKUP(D17,'DÍAS EFECTIVOS LABORADOS 2025'!B:O,14,0) -> 239 | N17: =+ROUND(VLOOKUP(D17,'INGRESOS 2025'!$B$7:$V$159,21,0),2) -> 116634.4 | O17: ACTIVO | P17: =$N$103*M17 -> 11766.526 | Q17: =$N$104*N17 -> 11584.998 | R17: =+ROUND(P17+Q17,2) -> 23351.52 | S17: =ROUND(HLOOKUP(D17,'5ta'!$C$7:$CF$118,112,0),2) -> 3269.21 | V17: =+ROUND(R17-T17-S17-U17,2) -> 20082.31 | W17: =+Y17*R17-S17 -> 0.0028 | X17: =HLOOKUP(D17,'5ta'!$C$7:$CG$139,133,0) -> TRUE | Y17: =HLOOKUP(D17,'5ta'!$C$7:$CF$135,129,0) -> 0.14 | Z17: =VLOOKUP(D17,'[1]0220262'!$E$12:$AD$94,26,0) -> 0 | AB17: =VLOOKUP(D17,'[2]Archivo Excel Haberes Input'!$K$11:$K$80,1,0) -> 10725704
C18: 12 | D18: 25710966 | E18: GIURIA CONSTANTINO HUMBERTO ANDRES | F18: JEFE DE DOCUMENTACIÓN Y VISTO BUENO | G18: DOCUMENTACION-VISTO BUENO | H18: OPERACIONES | I18: =VLOOKUP(D18,'DÍAS EFECTIVOS LABORADOS 2025'!B:F,3,0) -> 42985 | M18: =VLOOKUP(D18,'DÍAS EFECTIVOS LABORADOS 2025'!B:O,14,0) -> 238 | N18: =+ROUND(VLOOKUP(D18,'INGRESOS 2025'!$B$7:$V$159,21,0),2) -> 113138.07 | O18: ACTIVO | P18: =$N$103*M18 -> 11717.294 | Q18: =$N$104*N18 -> 11237.716 | R18: =+ROUND(P18+Q18,2) -> 22955.01 | S18: =ROUND(HLOOKUP(D18,'5ta'!$C$7:$CF$118,112,0),2) -> 3213.7 | V18: =+ROUND(R18-T18-S18-U18,2) -> 19741.31 | W18: =+Y18*R18-S18 -> 0.0014 | X18: =HLOOKUP(D18,'5ta'!$C$7:$CG$139,133,0) -> TRUE | Y18: =HLOOKUP(D18,'5ta'!$C$7:$CF$135,129,0) -> 0.14 | Z18: =VLOOKUP(D18,'[1]0220262'!$E$12:$AD$94,26,0) -> 0 | AB18: =VLOOKUP(D18,'[2]Archivo Excel Haberes Input'!$K$11:$K$80,1,0) -> 25710966
C19: 13 | D19: 25769631 | E19: RUIZ TORRES CESAR AUGUSTO | F19: CONDUCTOR/MENSAJERO | G19: ADMINISTRACION | H19: ADMINISTRACION | I19: =VLOOKUP(D19,'DÍAS EFECTIVOS LABORADOS 2025'!B:F,3,0) -> 44677 | M19: =VLOOKUP(D19,'DÍAS EFECTIVOS LABORADOS 2025'!B:O,14,0) -> 219 | N19: =+ROUND(VLOOKUP(D19,'INGRESOS 2025'!$B$7:$V$159,21,0),2) -> 30225.82 | O19: ACTIVO | P19: =$N$103*M19 -> 10781.88 | Q19: =$N$104*N19 -> 3002.2537 | R19: =+ROUND(P19+Q19,2) -> 13784.13 | S19: =ROUND(HLOOKUP(D19,'5ta'!$C$7:$CF$118,112,0),2) -> 203.01 | V19: =+ROUND(R19-T19-S19-U19,2) -> 13581.12 | X19: =HLOOKUP(D19,'5ta'!$C$7:$CG$139,133,0) -> FALSE | Y19: =HLOOKUP(D19,'5ta'!$C$7:$CF$145,134,0) -> 00% - 08% | Z19: =VLOOKUP(D19,'[1]0220262'!$E$12:$AD$94,26,0) -> 0 | AB19: =VLOOKUP(D19,'[2]Archivo Excel Haberes Input'!$K$11:$K$80,1,0) -> 25769631
C20: 14 | D20: 25828090 | E20: CHERO ORTIZ MARTIN ALEJANDRO | F20: ANALISTA DE CONTROL DE COSTO | G20: COST CONTROLER | H20: OPERACIONES | I20: =VLOOKUP(D20,'DÍAS EFECTIVOS LABORADOS 2025'!B:F,3,0) -> 44111 | M20: =VLOOKUP(D20,'DÍAS EFECTIVOS LABORADOS 2025'!B:O,14,0) -> 226 | N20: =+ROUND(VLOOKUP(D20,'INGRESOS 2025'!$B$7:$V$159,21,0),2) -> 54262.99 | O20: ACTIVO | P20: =$N$103*M20 -> 11126.506 | Q20: =$N$104*N20 -> 5389.8046 | R20: =+ROUND(P20+Q20,2) -> 16516.31 | S20: =ROUND(HLOOKUP(D20,'5ta'!$C$7:$CF$118,112,0),2) -> 1505.33 | V20: =+ROUND(R20-T20-S20-U20,2) -> 15010.98 | X20: =HLOOKUP(D20,'5ta'!$C$7:$CG$139,133,0) -> FALSE | Y20: =HLOOKUP(D20,'5ta'!$C$7:$CF$145,134,0) -> 08% - 14% | Z20: =VLOOKUP(D20,'[1]0220262'!$E$12:$AD$94,26,0) -> 0 | AB20: =VLOOKUP(D20,'[2]Archivo Excel Haberes Input'!$K$11:$K$80,1,0) -> 25828090
C21: 15 | D21: 40508445 | E21: MEJIA CAVERO PAOLA CECILIA | F21: ANALISTA SENIOR DE CONTROL DE EQUIPOS | G21: CONTROL DE EQUIPOS | H21: OPERACIONES | I21: =VLOOKUP(D21,'DÍAS EFECTIVOS LABORADOS 2025'!B:F,3,0) -> 42985 | M21: =VLOOKUP(D21,'DÍAS EFECTIVOS LABORADOS 2025'!B:O,14,0) -> 214 | N21: =+ROUND(VLOOKUP(D21,'INGRESOS 2025'!$B$7:$V$159,21,0),2) -> 76929.63 | O21: ACTIVO | P21: =$N$103*M21 -> 10535.718 | Q21: =$N$104*N21 -> 7641.2243 | R21: =+ROUND(P21+Q21,2) -> 18176.94 | S21: =ROUND(HLOOKUP(D21,'5ta'!$C$7:$CF$118,112,0),2) -> 2544.77 | V21: =+ROUND(R21-T21-S21-U21,2) -> 15632.17 | W21: =+Y21*R21-S21 -> 0.0016 | X21: =HLOOKUP(D21,'5ta'!$C$7:$CG$139,133,0) -> TRUE | Y21: =HLOOKUP(D21,'5ta'!$C$7:$CF$135,129,0) -> 0.14 | Z21: =VLOOKUP(D21,'[1]0220262'!$E$12:$AD$94,26,0) -> 0 | AB21: =VLOOKUP(D21,'[2]Archivo Excel Haberes Input'!$K$11:$K$80,1,0) -> 40508445
C22: 16 | D22: 40537272 | E22: GARRIDO LEON CARLA VERONICA | F22: ASESOR COMERCIAL EXPORTACIÓN | G22: COMERCIAL- VENTAS | H22: VENTAS | I22: =VLOOKUP(D22,'DÍAS EFECTIVOS LABORADOS 2025'!B:F,3,0) -> 42985 | M22: =VLOOKUP(D22,'DÍAS EFECTIVOS LABORADOS 2025'!B:O,14,0) -> 232 | N22: =+ROUND(VLOOKUP(D22,'INGRESOS 2025'!$B$7:$V$159,21,0),2) -> 154154.13 | O22: ACTIVO | P22: =$N$103*M22 -> 11421.9 | Q22: =$N$104*N22 -> 15311.737 | R22: =+ROUND(P22+Q22,2) -> 26733.64 | S22: =ROUND(HLOOKUP(D22,'5ta'!$C$7:$CF$118,112,0),2) -> 4378.81 | V22: =+ROUND(R22-T22-S22-U22,2) -> 22354.83 | X22: =HLOOKUP(D22,'5ta'!$C$7:$CG$139,133,0) -> FALSE | Y22: =HLOOKUP(D22,'5ta'!$C$7:$CF$145,134,0) -> 14% - 17% | Z22: =VLOOKUP(D22,'[1]0220262'!$E$12:$AD$94,26,0) -> 0 | AB22: =VLOOKUP(D22,'[2]Archivo Excel Haberes Input'!$K$11:$K$80,1,0) -> 40537272
C23: 17 | D23: 41047057 | E23: GALLEGOS BLAS LUIS MIGUEL | F23: CONTADOR | G23: CONTABILIDAD | H23: ADMINISTRACION | I23: =VLOOKUP(D23,'DÍAS EFECTIVOS LABORADOS 2025'!B:F,3,0) -> 45481 | M23: =VLOOKUP(D23,'DÍAS EFECTIVOS LABORADOS 2025'!B:O,14,0) -> 237 | N23: =+ROUND(VLOOKUP(D23,'INGRESOS 2025'!$B$7:$V$159,21,0),2) -> 87323.01 | O23: ACTIVO | P23: =$N$103*M23 -> 11668.062 | Q23: =$N$104*N23 -> 8673.5723 | R23: =+ROUND(P23+Q23,2) -> 20341.63 | S23: =ROUND(HLOOKUP(D23,'5ta'!$C$7:$CF$118,112,0),2) -> 2847.83 | V23: =+ROUND(R23-T23-S23-U23,2) -> 17493.8 | W23: =+Y23*R23-S23 -> -0.0018 | X23: =HLOOKUP(D23,'5ta'!$C$7:$CG$139,133,0) -> TRUE | Y23: =HLOOKUP(D23,'5ta'!$C$7:$CF$135,129,0) -> 0.14 | Z23: =VLOOKUP(D23,'[1]0220262'!$E$12:$AD$94,26,0) -> 0 | AB23: =VLOOKUP(D23,'[2]Archivo Excel Haberes Input'!$K$11:$K$80,1,0) -> 41047057
C24: 18 | D24: 41832234 | E24: HUERTA PALOMINO NELLY VANESSA | I24: =VLOOKUP(D24,'DÍAS EFECTIVOS LABORADOS 2025'!B:F,3,0) -> 44986 | J24: =VLOOKUP(D24,'DÍAS EFECTIVOS LABORADOS 2025'!B:F,5,0) -> 45748 | M24: =VLOOKUP(D24,'DÍAS EFECTIVOS LABORADOS 2025'!B:O,14,0) -> 49 | N24: =+ROUND(VLOOKUP(D24,'INGRESOS 2025'!$B$7:$V$159,21,0),2) -> 29573.67 | O24: CESADO | P24: =$N$103*M24 -> 2412.384 | Q24: =$N$104*N24 -> 2937.4773 | R24: =+ROUND(P24+Q24,2) -> 5349.86 | V24: =+ROUND(R24-T24-S24-U24,2) -> 5349.86 | Z24: =VLOOKUP(D24,'[1]0220262'!$E$12:$AD$94,26,0) -> #N/A
C25: 19 | D25: 42035890 | E25: CASTAÑEDA CARRION VIVIEN KARLA | F25: COORDINADOR TRIBUTARIO | G25: CONTABILIDAD | H25: ADMINISTRACION | I25: =VLOOKUP(D25,'DÍAS EFECTIVOS LABORADOS 2025'!B:F,3,0) -> 45181 | M25: =VLOOKUP(D25,'DÍAS EFECTIVOS LABORADOS 2025'!B:O,14,0) -> 227 | N25: =+ROUND(VLOOKUP(D25,'INGRESOS 2025'!$B$7:$V$159,21,0),2) -> 95349.71 | O25: ACTIVO | P25: =$N$103*M25 -> 11175.738 | Q25: =$N$104*N25 -> 9470.8439 | R25: =+ROUND(P25+Q25,2) -> 20646.58 | S25: =ROUND(HLOOKUP(D25,'5ta'!$C$7:$CF$118,112,0),2) -> 2890.52 | V25: =+ROUND(R25-T25-S25-U25,2) -> 17756.06 | W25: =+Y25*R25-S25 -> 0.0012 | X25: =HLOOKUP(D25,'5ta'!$C$7:$CG$139,133,0) -> TRUE | Y25: =HLOOKUP(D25,'5ta'!$C$7:$CF$135,129,0) -> 0.14 | Z25: =VLOOKUP(D25,'[1]0220262'!$E$12:$AD$94,26,0) -> 0 | AB25: =VLOOKUP(D25,'[2]Archivo Excel Haberes Input'!$K$11:$K$80,1,0) -> 42035890
C26: 20 | D26: 42168737 | E26: MARTINEZ MURAYARI INES ROXANA | F26: CUSTOMER SERVICE EXPORTACIÓN | G26: COMERCIAL- VENTAS | H26: VENTAS | I26: =VLOOKUP(D26,'DÍAS EFECTIVOS LABORADOS 2025'!B:F,3,0) -> 43252 | M26: =VLOOKUP(D26,'DÍAS EFECTIVOS LABORADOS 2025'!B:O,14,0) -> 238 | N26: =+ROUND(VLOOKUP(D26,'INGRESOS 2025'!$B$7:$V$159,21,0),2) -> 65356.07 | O26: ACTIVO | P26: =$N$103*M26 -> 11717.294 | Q26: =$N$104*N26 -> 6491.652 | R26: =+ROUND(P26+Q26,2) -> 18208.95 | S26: =ROUND(HLOOKUP(D26,'5ta'!$C$7:$CF$118,112,0),2) -> 2549.25 | V26: =+ROUND(R26-T26-S26-U26,2) -> 15659.7 | W26: =+Y26*R26-S26 -> 0.003 | X26: =HLOOKUP(D26,'5ta'!$C$7:$CG$139,133,0) -> TRUE | Y26: =HLOOKUP(D26,'5ta'!$C$7:$CF$135,129,0) -> 0.14 | Z26: =VLOOKUP(D26,'[1]0220262'!$E$12:$AD$94,26,0) -> 0 | AB26: =VLOOKUP(D26,'[2]Archivo Excel Haberes Input'!$K$11:$K$80,1,0) -> 42168737
C27: 21 | D27: 42326063 | E27: MARTI ROJAS DE ZÁRATE ANGELA TERESA | I27: =VLOOKUP(D27,'DÍAS EFECTIVOS LABORADOS 2025'!B:F,3,0) -> 43900 | J27: =VLOOKUP(D27,'DÍAS EFECTIVOS LABORADOS 2025'!B:F,5,0) -> 45747 | M27: =VLOOKUP(D27,'DÍAS EFECTIVOS LABORADOS 2025'!B:O,14,0) -> 63 | N27: =+ROUND(VLOOKUP(D27,'INGRESOS 2025'!$B$7:$V$159,21,0),2) -> 75354.76 | O27: CESADO | P27: =$N$103*M27 -> 3101.6366 | Q27: =$N$104*N27 -> 7484.7965 | R27: =+ROUND(P27+Q27,2) -> 10586.43 | V27: =+ROUND(R27-T27-S27-U27,2) -> 10586.43 | Z27: =VLOOKUP(D27,'[1]0220262'!$E$12:$AD$94,26,0) -> #N/A
C28: 22 | D28: 42560153 | E28: VALDEZ CRUZ JOSEPH JOSUE | F28: PROCURADOR MARITIMO PAITA | G28: OPERACIONES PORTUARIAS | H28: OPERACIONES | I28: =VLOOKUP(D28,'DÍAS EFECTIVOS LABORADOS 2025'!B:F,3,0) -> 43222 | M28: =VLOOKUP(D28,'DÍAS EFECTIVOS LABORADOS 2025'!B:O,14,0) -> 229 | N28: =+ROUND(VLOOKUP(D28,'INGRESOS 2025'!$B$7:$V$159,21,0),2) -> 46483.98 | O28: ACTIVO | P28: =$N$103*M28 -> 11274.203 | Q28: =$N$104*N28 -> 4617.1354 | R28: =+ROUND(P28+Q28,2) -> 15891.34 | S28: =ROUND(HLOOKUP(D28,'5ta'!$C$7:$CF$118,112,0),2) -> 1271.31 | V28: =+ROUND(R28-T28-S28-U28,2) -> 14620.03 | W28: =+Y28*R28-S28 -> -0.0028 | X28: =HLOOKUP(D28,'5ta'!$C$7:$CG$139,133,0) -> TRUE | Y28: =HLOOKUP(D28,'5ta'!$C$7:$CF$135,129,0) -> 0.08 | Z28: =VLOOKUP(D28,'[1]0220262'!$E$12:$AD$94,26,0) -> 0 | AB28: =VLOOKUP(D28,'[2]Archivo Excel Haberes Input'!$K$11:$K$80,1,0) -> 42560153
C29: 23 | D29: 42646402 | E29: BALDOCEDA COLQUI YESENIA FLORA | F29: AUXILIAR DE LIMPIEZA | G29: ADMINISTRACION | H29: ADMINISTRACION | I29: =VLOOKUP(D29,'DÍAS EFECTIVOS LABORADOS 2025'!B:F,3,0) -> 44935 | M29: =VLOOKUP(D29,'DÍAS EFECTIVOS LABORADOS 2025'!B:O,14,0) -> 235 | N29: =+ROUND(VLOOKUP(D29,'INGRESOS 2025'!$B$7:$V$159,21,0),2) -> 28101.11 | O29: ACTIVO | P29: =$N$103*M29 -> 11569.597 | Q29: =$N$104*N29 -> 2791.2117 | R29: =+ROUND(P29+Q29,2) -> 14360.81 | S29: =ROUND(HLOOKUP(D29,'5ta'!$C$7:$CF$118,112,0),2) -> 246.5 | V29: =+ROUND(R29-T29-S29-U29,2) -> 14114.31 | X29: =HLOOKUP(D29,'5ta'!$C$7:$CG$139,133,0) -> FALSE | Y29: =HLOOKUP(D29,'5ta'!$C$7:$CF$145,134,0) -> 00% - 08% | Z29: =VLOOKUP(D29,'[1]0220262'!$E$12:$AD$94,26,0) -> 0 | AB29: =VLOOKUP(D29,'[2]Archivo Excel Haberes Input'!$K$11:$K$80,1,0) -> 42646402
C30: 24 | D30: 43393889 | E30: ZAPATA QUEVEDO KARINA JANET | I30: =VLOOKUP(D30,'DÍAS EFECTIVOS LABORADOS 2025'!B:F,3,0) -> 45631 | J30: =VLOOKUP(D30,'DÍAS EFECTIVOS LABORADOS 2025'!B:F,5,0) -> 45882 | M30: =VLOOKUP(D30,'DÍAS EFECTIVOS LABORADOS 2025'!B:O,14,0) -> 152 | N30: =+ROUND(VLOOKUP(D30,'INGRESOS 2025'!$B$7:$V$159,21,0),2) -> 38843.4 | O30: CESADO | P30: =$N$103*M30 -> 7483.3138 | Q30: =$N$104*N30 -> 3858.216 | R30: =+ROUND(P30+Q30,2) -> 11341.53 | V30: =+ROUND(R30-T30-S30-U30,2) -> 11341.53 | Z30: =VLOOKUP(D30,'[1]0220262'!$E$12:$AD$94,26,0) -> #N/A
C31: 25 | D31: 43426313 | E31: LOPEZ MENDOZA GIULIANA JANNET | F31: ANALISTA SENIOR DE DOCUMENTACIÓ Y VISTO BUENO | G31: DOCUMENTACION-VISTO BUENO | H31: OPERACIONES | I31: =VLOOKUP(D31,'DÍAS EFECTIVOS LABORADOS 2025'!B:F,3,0) -> 43206 | M31: =VLOOKUP(D31,'DÍAS EFECTIVOS LABORADOS 2025'!B:O,14,0) -> 219 | N31: =+ROUND(VLOOKUP(D31,'INGRESOS 2025'!$B$7:$V$159,21,0),2) -> 71138.4 | O31: ACTIVO | P31: =$N$103*M31 -> 10781.88 | Q31: =$N$104*N31 -> 7065.9962 | R31: =+ROUND(P31+Q31,2) -> 17847.88 | S31: =ROUND(HLOOKUP(D31,'5ta'!$C$7:$CF$118,112,0),2) -> 2498.7 | V31: =+ROUND(R31-T31-S31-U31,2) -> 15349.18 | W31: =+Y31*R31-S31 -> 0.0032 | X31: =HLOOKUP(D31,'5ta'!$C$7:$CG$139,133,0) -> TRUE | Y31: =HLOOKUP(D31,'5ta'!$C$7:$CF$135,129,0) -> 0.14 | Z31: =VLOOKUP(D31,'[1]0220262'!$E$12:$AD$94,26,0) -> 0 | AB31: =VLOOKUP(D31,'[2]Archivo Excel Haberes Input'!$K$11:$K$80,1,0) -> 43426313
C32: 26 | D32: 43643490 | E32: ESPINOZA RUA KARINNA ESPERANZA | I32: =VLOOKUP(D32,'DÍAS EFECTIVOS LABORADOS 2025'!B:F,3,0) -> 44348 | J32: =VLOOKUP(D32,'DÍAS EFECTIVOS LABORADOS 2025'!B:F,5,0) -> 45844 | M32: =VLOOKUP(D32,'DÍAS EFECTIVOS LABORADOS 2025'!B:O,14,0) -> 115 | N32: =+ROUND(VLOOKUP(D32,'INGRESOS 2025'!$B$7:$V$159,21,0),2) -> 62939.35 | O32: CESADO | P32: =$N$103*M32 -> 5661.7177 | Q32: =$N$104*N32 -> 6251.6054 | R32: =+ROUND(P32+Q32,2) -> 11913.32 | U32: 21.74 | V32: =+ROUND(R32-T32-S32-U32,2) -> 11891.58 | Z32: =VLOOKUP(D32,'[1]0220262'!$E$12:$AD$94,26,0) -> #N/A
C33: 27 | D33: 45282900 | E33: BELUPU GUTIERREZ CARLO DANIEL | F33: ANALISTA DE COMPRAS | G33: COMPRAS | H33: OPERACIONES | I33: =VLOOKUP(D33,'DÍAS EFECTIVOS LABORADOS 2025'!B:F,3,0) -> 45541 | M33: =VLOOKUP(D33,'DÍAS EFECTIVOS LABORADOS 2025'!B:O,14,0) -> 240 | N33: =+ROUND(VLOOKUP(D33,'INGRESOS 2025'!$B$7:$V$159,21,0),2) -> 41728.5 | O33: ACTIVO | P33: =$N$103*M33 -> 11815.759 | Q33: =$N$104*N33 -> 4144.7857 | R33: =+ROUND(P33+Q33,2) -> 15960.54 | S33: =ROUND(HLOOKUP(D33,'5ta'!$C$7:$CF$118,112,0),2) -> 1276.84 | V33: =+ROUND(R33-T33-S33-U33,2) -> 14683.7 | W33: =+Y33*R33-S33 -> 0.0032 | X33: =HLOOKUP(D33,'5ta'!$C$7:$CG$139,133,0) -> TRUE | Y33: =HLOOKUP(D33,'5ta'!$C$7:$CF$135,129,0) -> 0.08 | Z33: =VLOOKUP(D33,'[1]0220262'!$E$12:$AD$94,26,0) -> 0 | AB33: =VLOOKUP(D33,'[2]Archivo Excel Haberes Input'!$K$11:$K$80,1,0) -> 45282900
C34: 28 | D34: 45813056 | E34: ALFARO VILLACORTA VICTOR HUGO GARY | F34: JEFE DE OPERACIONES | G34: OPERACIONES PORTUARIAS | H34: OPERACIONES | I34: =VLOOKUP(D34,'DÍAS EFECTIVOS LABORADOS 2025'!B:F,3,0) -> 42948 | M34: =VLOOKUP(D34,'DÍAS EFECTIVOS LABORADOS 2025'!B:O,14,0) -> 221 | N34: =+ROUND(VLOOKUP(D34,'INGRESOS 2025'!$B$7:$V$159,21,0),2) -> 156914.37 | O34: ACTIVO | P34: =$N$103*M34 -> 10880.344 | Q34: =$N$104*N34 -> 15585.905 | R34: =+ROUND(P34+Q34,2) -> 26466.25 | S34: =ROUND(HLOOKUP(D34,'5ta'!$C$7:$CF$118,112,0),2) -> 4250.84 | V34: =+ROUND(R34-T34-S34-U34,2) -> 22215.41 | X34: =HLOOKUP(D34,'5ta'!$C$7:$CG$139,133,0) -> FALSE | Y34: =HLOOKUP(D34,'5ta'!$C$7:$CF$145,134,0) -> 14% - 17% | Z34: =VLOOKUP(D34,'[1]0220262'!$E$12:$AD$94,26,0) -> 0 | AB34: =VLOOKUP(D34,'[2]Archivo Excel Haberes Input'!$K$11:$K$80,1,0) -> 45813056
C35: 29 | D35: 45858948 | E35: CHAVEZ QUILCATE JULIA DEL PILAR | F35: ASISTENTE DE OPERACIONES PORTUARIAS | G35: OPERACIONES PORTUARIAS | H35: OPERACIONES | I35: =VLOOKUP(D35,'DÍAS EFECTIVOS LABORADOS 2025'!B:F,3,0) -> 44600 | M35: =VLOOKUP(D35,'DÍAS EFECTIVOS LABORADOS 2025'!B:O,14,0) -> 223 | N35: =+ROUND(VLOOKUP(D35,'INGRESOS 2025'!$B$7:$V$159,21,0),2) -> 41789.27 | O35: ACTIVO | P35: =$N$103*M35 -> 10978.809 | Q35: =$N$104*N35 -> 4150.8218 | R35: =+ROUND(P35+Q35,2) -> 15129.63 | S35: =ROUND(HLOOKUP(D35,'5ta'!$C$7:$CF$118,112,0),2) -> 1149.86 | V35: =+ROUND(R35-T35-S35-U35,2) -> 13979.77 | X35: =HLOOKUP(D35,'5ta'!$C$7:$CG$139,133,0) -> FALSE | Y35: =HLOOKUP(D35,'5ta'!$C$7:$CF$145,134,0) -> 00% - 08% | Z35: =VLOOKUP(D35,'[1]0220262'!$E$12:$AD$94,26,0) -> 0 | AB35: =VLOOKUP(D35,'[2]Archivo Excel Haberes Input'!$K$11:$K$80,1,0) -> 45858948
C36: 30 | D36: 46833118 | E36: MOSCAYZA NAZARIO STEPHANIE JULIANA | F36: ASISTENTE DE CONTABILIDAD | G36: CONTABILIDAD | H36: ADMINISTRACION | I36: =VLOOKUP(D36,'DÍAS EFECTIVOS LABORADOS 2025'!B:F,3,0) -> 45292 | M36: =VLOOKUP(D36,'DÍAS EFECTIVOS LABORADOS 2025'!B:O,14,0) -> 233 | N36: =+ROUND(VLOOKUP(D36,'INGRESOS 2025'!$B$7:$V$159,21,0),2) -> 38324.14 | O36: ACTIVO | P36: =$N$103*M36 -> 11471.132 | Q36: =$N$104*N36 -> 3806.6393 | R36: =+ROUND(P36+Q36,2) -> 15277.77 | S36: =ROUND(HLOOKUP(D36,'5ta'!$C$7:$CF$118,112,0),2) -> 1222.22 | V36: =+ROUND(R36-T36-S36-U36,2) -> 14055.55 | W36: =+Y36*R36-S36 -> 0.0016 | X36: =HLOOKUP(D36,'5ta'!$C$7:$CG$139,133,0) -> TRUE | Y36: =HLOOKUP(D36,'5ta'!$C$7:$CF$135,129,0) -> 0.08 | Z36: =VLOOKUP(D36,'[1]0220262'!$E$12:$AD$94,26,0) -> 0 | AB36: =VLOOKUP(D36,'[2]Archivo Excel Haberes Input'!$K$11:$K$80,1,0) -> 46833118
C37: 31 | D37: 47470495 | E37: VILLANTOY GUTIERREZ ANDRES DANIEL | F37: COORDINADOR DE OPERACIONES | G37: OPERACIONES PORTUARIAS | H37: OPERACIONES | I37: =VLOOKUP(D37,'DÍAS EFECTIVOS LABORADOS 2025'!B:F,3,0) -> 43206 | M37: =VLOOKUP(D37,'DÍAS EFECTIVOS LABORADOS 2025'!B:O,14,0) -> 224 | N37: =+ROUND(VLOOKUP(D37,'INGRESOS 2025'!$B$7:$V$159,21,0),2) -> 63233.48 | O37: ACTIVO | P37: =$N$103*M37 -> 11028.041 | Q37: =$N$104*N37 -> 6280.8206 | R37: =+ROUND(P37+Q37,2) -> 17308.86 | S37: =ROUND(HLOOKUP(D37,'5ta'!$C$7:$CF$118,112,0),2) -> 2423.24 | V37: =+ROUND(R37-T37-S37-U37,2) -> 14885.62 | W37: =+Y37*R37-S37 -> 0.0004 | X37: =HLOOKUP(D37,'5ta'!$C$7:$CG$139,133,0) -> TRUE | Y37: =HLOOKUP(D37,'5ta'!$C$7:$CF$135,129,0) -> 0.14 | Z37: =VLOOKUP(D37,'[1]0220262'!$E$12:$AD$94,26,0) -> 0 | AB37: =VLOOKUP(D37,'[2]Archivo Excel Haberes Input'!$K$11:$K$80,1,0) -> 47470495
C38: 32 | D38: 47472407 | E38: BARRANZUELA SANTOS MELISSA ANTONED | F38: ANALISTA DE COBRANZAS Y FACTURACION | G38: COBRANZAS | H38: ADMINISTRACION | I38: =VLOOKUP(D38,'DÍAS EFECTIVOS LABORADOS 2025'!B:F,3,0) -> 43374 | M38: =VLOOKUP(D38,'DÍAS EFECTIVOS LABORADOS 2025'!B:O,14,0) -> 224 | N38: =+ROUND(VLOOKUP(D38,'INGRESOS 2025'!$B$7:$V$159,21,0),2) -> 47055.4 | O38: ACTIVO | P38: =$N$103*M38 -> 11028.041 | Q38: =$N$104*N38 -> 4673.8931 | R38: =+ROUND(P38+Q38,2) -> 15701.93 | S38: =ROUND(HLOOKUP(D38,'5ta'!$C$7:$CF$118,112,0),2) -> 1256.15 | V38: =+ROUND(R38-T38-S38-U38,2) -> 14445.78 | W38: =+Y38*R38-S38 -> 0.0044 | X38: =HLOOKUP(D38,'5ta'!$C$7:$CG$139,133,0) -> TRUE | Y38: =HLOOKUP(D38,'5ta'!$C$7:$CF$135,129,0) -> 0.08 | Z38: =VLOOKUP(D38,'[1]0220262'!$E$12:$AD$94,26,0) -> 0 | AB38: =VLOOKUP(D38,'[2]Archivo Excel Haberes Input'!$K$11:$K$80,1,0) -> 47472407
C39: 33 | D39: 47668422 | E39: ROMAN PINTADO JULLISA IVETTE | F39: ASISTENTE SENIOR DE DOCUMENTACIÓN | G39: DOCUMENTACION-VISTO BUENO | H39: OPERACIONES | I39: =VLOOKUP(D39,'DÍAS EFECTIVOS LABORADOS 2025'!B:F,3,0) -> 43160 | M39: =VLOOKUP(D39,'DÍAS EFECTIVOS LABORADOS 2025'!B:O,14,0) -> 235 | N39: =+ROUND(VLOOKUP(D39,'INGRESOS 2025'!$B$7:$V$159,21,0),2) -> 48632.41 | O39: ACTIVO | P39: =$N$103*M39 -> 11569.597 | Q39: =$N$104*N39 -> 4830.5335 | R39: =+ROUND(P39+Q39,2) -> 16400.13 | S39: =ROUND(HLOOKUP(D39,'5ta'!$C$7:$CF$118,112,0),2) -> 1312.01 | V39: =+ROUND(R39-T39-S39-U39,2) -> 15088.12 | W39: =+Y39*R39-S39 -> 0.0004 | X39: =HLOOKUP(D39,'5ta'!$C$7:$CG$139,133,0) -> TRUE | Y39: =HLOOKUP(D39,'5ta'!$C$7:$CF$135,129,0) -> 0.08 | Z39: =VLOOKUP(D39,'[1]0220262'!$E$12:$AD$94,26,0) -> 0 | AB39: =VLOOKUP(D39,'[2]Archivo Excel Haberes Input'!$K$11:$K$80,1,0) -> 47668422
C40: 34 | D40: 47706283 | E40: ALIAGA DEL ROSARIO JOSEPH CHRISTHOPHER | F40: ASISTENTE DE VISTO BUENO | G40: DOCUMENTACION-VISTO BUENO | H40: OPERACIONES | I40: =VLOOKUP(D40,'DÍAS EFECTIVOS LABORADOS 2025'!B:F,3,0) -> 44539 | M40: =VLOOKUP(D40,'DÍAS EFECTIVOS LABORADOS 2025'!B:O,14,0) -> 234 | N40: =+ROUND(VLOOKUP(D40,'INGRESOS 2025'!$B$7:$V$159,21,0),2) -> 33537.66 | O40: ACTIVO | P40: =$N$103*M40 -> 11520.365 | Q40: =$N$104*N40 -> 3331.2104 | R40: =+ROUND(P40+Q40,2) -> 14851.58 | S40: =ROUND(HLOOKUP(D40,'5ta'!$C$7:$CF$118,112,0),2) -> 713.36 | V40: =+ROUND(R40-T40-S40-U40,2) -> 14138.22 | X40: =HLOOKUP(D40,'5ta'!$C$7:$CG$139,133,0) -> FALSE | Y40: =HLOOKUP(D40,'5ta'!$C$7:$CF$145,134,0) -> 00% - 08% | Z40: =VLOOKUP(D40,'[1]0220262'!$E$12:$AD$94,26,0) -> 0 | AB40: =VLOOKUP(D40,'[2]Archivo Excel Haberes Input'!$K$11:$K$80,1,0) -> 47706283
C41: 35 | D41: 47806538 | E41: RAMIREZ ALBINAGORTA ENRIQUE ALEJANDRO | F41: ANALISTA CUSTOMER SERVICES EXPORTACION | G41: COMERCIAL- VENTAS | H41: VENTAS | I41: =VLOOKUP(D41,'DÍAS EFECTIVOS LABORADOS 2025'!B:F,3,0) -> 43402 | M41: =VLOOKUP(D41,'DÍAS EFECTIVOS LABORADOS 2025'!B:O,14,0) -> 246 | N41: =+ROUND(VLOOKUP(D41,'INGRESOS 2025'!$B$7:$V$159,21,0),2) -> 43663.7 | O41: ACTIVO | P41: =$N$103*M41 -> 12111.153 | Q41: =$N$104*N41 -> 4337.0042 | R41: =+ROUND(P41+Q41,2) -> 16448.16 | S41: =ROUND(HLOOKUP(D41,'5ta'!$C$7:$CF$118,112,0),2) -> 1388.32 | V41: =+ROUND(R41-T41-S41-U41,2) -> 15059.84 | X41: =HLOOKUP(D41,'5ta'!$C$7:$CG$139,133,0) -> FALSE | Y41: =HLOOKUP(D41,'5ta'!$C$7:$CF$145,134,0) -> 08% - 14% | Z41: =VLOOKUP(D41,'[1]0220262'!$E$12:$AD$94,26,0) -> 0 | AB41: =VLOOKUP(D41,'[2]Archivo Excel Haberes Input'!$K$11:$K$80,1,0) -> 47806538
C42: 36 | D42: 47867088 | E42: ROSALES ATOCHE ROXANA IVETTE | F42: ASISTENTE DE FLETADO | G42: COMERCIAL- VENTAS | H42: VENTAS | I42: =VLOOKUP(D42,'DÍAS EFECTIVOS LABORADOS 2025'!B:F,3,0) -> 44911 | M42: =VLOOKUP(D42,'DÍAS EFECTIVOS LABORADOS 2025'!B:O,14,0) -> 232 | N42: =+ROUND(VLOOKUP(D42,'INGRESOS 2025'!$B$7:$V$159,21,0),2) -> 34615.03 | O42: ACTIVO | P42: =$N$103*M42 -> 11421.9 | Q42: =$N$104*N42 -> 3438.2228 | R42: =+ROUND(P42+Q42,2) -> 14860.12 | S42: =ROUND(HLOOKUP(D42,'5ta'!$C$7:$CF$118,112,0),2) -> 742.51 | V42: =+ROUND(R42-T42-S42-U42,2) -> 14117.61 | X42: =HLOOKUP(D42,'5ta'!$C$7:$CG$139,133,0) -> FALSE | Y42: =HLOOKUP(D42,'5ta'!$C$7:$CF$145,134,0) -> 00% - 08% | Z42: =VLOOKUP(D42,'[1]0220262'!$E$12:$AD$94,26,0) -> 0 | AB42: =VLOOKUP(D42,'[2]Archivo Excel Haberes Input'!$K$11:$K$80,1,0) -> 47867088
C43: 37 | D43: 48035238 | E43: YUCRA MANCILLA AHRON | F43: ANALISTA DE COBRANZAS Y FACTURACION | G43: COBRANZAS | H43: ADMINISTRACION | I43: =VLOOKUP(D43,'DÍAS EFECTIVOS LABORADOS 2025'!B:F,3,0) -> 45627 | M43: =VLOOKUP(D43,'DÍAS EFECTIVOS LABORADOS 2025'!B:O,14,0) -> 238 | N43: =+ROUND(VLOOKUP(D43,'INGRESOS 2025'!$B$7:$V$159,21,0),2) -> 46934.94 | O43: CESADO EN 2026 | P43: =$N$103*M43 -> 11717.294 | Q43: =$N$104*N43 -> 4661.9281 | R43: =+ROUND(P43+Q43,2) -> 16379.22 | V43: =+ROUND(R43-T43-S43-U43,2) -> 16379.22 | Z43: =VLOOKUP(D43,'[1]0220262'!$E$12:$AD$94,26,0) -> 46078
C44: 38 | D44: 48109666 | E44: CCAPA SIGUEÑAS SILENE DORA | F44: ANALISTA TRIBUTARIO | G44: TRIBUTARIA | H44: ADMINISTRACION | I44: =VLOOKUP(D44,'DÍAS EFECTIVOS LABORADOS 2025'!B:F,3,0) -> 45628 | J44: =VLOOKUP(D44,'DÍAS EFECTIVOS LABORADOS 2025'!B:F,5,0) -> 45716 | K44: 45887 | M44: =VLOOKUP(D44,'DÍAS EFECTIVOS LABORADOS 2025'!B:O,14,0) -> 133 | N44: =+ROUND(VLOOKUP(D44,'INGRESOS 2025'!$B$7:$V$159,21,0),2) -> 34773.23 | O44: ACTIVO | P44: =$N$103*M44 -> 6547.8995 | Q44: =$N$104*N44 -> 3453.9364 | R44: =+ROUND(P44+Q44,2) -> 10001.84 | S44: =ROUND(HLOOKUP(D44,'5ta'!$C$7:$CF$118,112,0),2) -> 1341.52 | V44: =+ROUND(R44-T44-S44-U44,2) -> 8660.32 | X44: =HLOOKUP(D44,'5ta'!$C$7:$CG$139,133,0) -> FALSE | Y44: =HLOOKUP(D44,'5ta'!$C$7:$CF$145,134,0) -> 08% - 14% | Z44: =VLOOKUP(D44,'[1]0220262'!$E$12:$AD$94,26,0) -> 0 | AB44: =VLOOKUP(D44,'[2]Archivo Excel Haberes Input'!$K$11:$K$80,1,0) -> 48109666
C45: 39 | D45: 48588627 | E45: CARRERA RAMIREZ KATTYA HELEN | F45: ASISTENTE DE CONTROL DE EQUIPOS | G45: CONTROL DE EQUIPOS | H45: OPERACIONES | I45: =VLOOKUP(D45,'DÍAS EFECTIVOS LABORADOS 2025'!B:F,3,0) -> 43243 | M45: =VLOOKUP(D45,'DÍAS EFECTIVOS LABORADOS 2025'!B:O,14,0) -> 264 | N45: =+ROUND(VLOOKUP(D45,'INGRESOS 2025'!$B$7:$V$159,21,0),2) -> 30017.31 | O45: ACTIVO | P45: =$N$103*M45 -> 12997.334 | Q45: =$N$104*N45 -> 2981.543 | R45: =+ROUND(P45+Q45,2) -> 15978.88 | S45: =ROUND(HLOOKUP(D45,'5ta'!$C$7:$CF$118,112,0),2) -> 1148.34 | V45: =+ROUND(R45-T45-S45-U45,2) -> 14830.54 | X45: =HLOOKUP(D45,'5ta'!$C$7:$CG$139,133,0) -> FALSE | Y45: =HLOOKUP(D45,'5ta'!$C$7:$CF$145,134,0) -> 00% - 08% | Z45: =VLOOKUP(D45,'[1]0220262'!$E$12:$AD$94,26,0) -> 0 | AB45: =VLOOKUP(D45,'[2]Archivo Excel Haberes Input'!$K$11:$K$80,1,0) -> 48588627
C46: 40 | D46: 70857319 | E46: SAKAY MORISAKI LUIS CARLOS | F46: ASISTENTE ADMINISTRATIVO | G46: ADMINISTRACION | H46: ADMINISTRACION | I46: =VLOOKUP(D46,'DÍAS EFECTIVOS LABORADOS 2025'!B:F,3,0) -> 44799 | M46: =VLOOKUP(D46,'DÍAS EFECTIVOS LABORADOS 2025'!B:O,14,0) -> 225 | N46: =+ROUND(VLOOKUP(D46,'INGRESOS 2025'!$B$7:$V$159,21,0),2) -> 31999.39 | O46: ACTIVO | P46: =$N$103*M46 -> 11077.274 | Q46: =$N$104*N46 -> 3178.4179 | R46: =+ROUND(P46+Q46,2) -> 14255.69 | S46: =ROUND(HLOOKUP(D46,'5ta'!$C$7:$CF$118,112,0),2) -> 546.68 | V46: =+ROUND(R46-T46-S46-U46,2) -> 13709.01 | X46: =HLOOKUP(D46,'5ta'!$C$7:$CG$139,133,0) -> FALSE | Y46: =HLOOKUP(D46,'5ta'!$C$7:$CF$145,134,0) -> 00% - 08% | Z46: =VLOOKUP(D46,'[1]0220262'!$E$12:$AD$94,26,0) -> 0 | AB46: =VLOOKUP(D46,'[2]Archivo Excel Haberes Input'!$K$11:$K$80,1,0) -> 70857319
C47: 41 | D47: 71467210 | E47: ANTAYHUA GRABIEL ISAAC ISMAEL | F47: ANALISTA CONTABILIDAD | G47: CONTABILIDAD | H47: ADMINISTRACION | I47: =VLOOKUP(D47,'DÍAS EFECTIVOS LABORADOS 2025'!B:F,3,0) -> 43525 | M47: =VLOOKUP(D47,'DÍAS EFECTIVOS LABORADOS 2025'!B:O,14,0) -> 230 | N47: =+ROUND(VLOOKUP(D47,'INGRESOS 2025'!$B$7:$V$159,21,0),2) -> 51211.13 | O47: ACTIVO | P47: =$N$103*M47 -> 11323.435 | Q47: =$N$104*N47 -> 5086.6712 | R47: =+ROUND(P47+Q47,2) -> 16410.11 | S47: =ROUND(HLOOKUP(D47,'5ta'!$C$7:$CF$118,112,0),2) -> 1312.81 | V47: =+ROUND(R47-T47-S47-U47,2) -> 15097.3 | W47: =+Y47*R47-S47 -> -0.0012 | X47: =HLOOKUP(D47,'5ta'!$C$7:$CG$139,133,0) -> TRUE | Y47: =HLOOKUP(D47,'5ta'!$C$7:$CF$135,129,0) -> 0.08 | Z47: =VLOOKUP(D47,'[1]0220262'!$E$12:$AD$94,26,0) -> 0 | AB47: =VLOOKUP(D47,'[2]Archivo Excel Haberes Input'!$K$11:$K$80,1,0) -> 71467210
C48: 42 | D48: 71569497 | E48: CAMPOS PALOMINO DIANA MARGARITA | F48: ASISTENTE DE VISTO BUENO Y FACTURACIÓN | G48: DOCUMENTACION-VISTO BUENO | H48: OPERACIONES | I48: =VLOOKUP(D48,'DÍAS EFECTIVOS LABORADOS 2025'!B:F,3,0) -> 43973 | M48: =VLOOKUP(D48,'DÍAS EFECTIVOS LABORADOS 2025'!B:O,14,0) -> 252 | N48: =+ROUND(VLOOKUP(D48,'INGRESOS 2025'!$B$7:$V$159,21,0),2) -> 26072.44 | O48: ACTIVO | P48: =$N$103*M48 -> 12406.547 | Q48: =$N$104*N48 -> 2589.7091 | R48: =+ROUND(P48+Q48,2) -> 14996.26 | S48: =ROUND(HLOOKUP(D48,'5ta'!$C$7:$CF$118,112,0),2) -> 737.65 | V48: =+ROUND(R48-T48-S48-U48,2) -> 14258.61 | X48: =HLOOKUP(D48,'5ta'!$C$7:$CG$139,133,0) -> FALSE | Y48: =HLOOKUP(D48,'5ta'!$C$7:$CF$145,134,0) -> 00% - 08% | Z48: =VLOOKUP(D48,'[1]0220262'!$E$12:$AD$94,26,0) -> 0 | AB48: =VLOOKUP(D48,'[2]Archivo Excel Haberes Input'!$K$11:$K$80,1,0) -> 71569497
C49: 43 | D49: 71726981 | E49: CRUZ QUISPE GEYDI ANTONELA | F49: AUXILIAR DE CONTROL DE EQUIPOS | G49: CONTROL DE EQUIPO | H49: OPERACIONES | I49: =VLOOKUP(D49,'DÍAS EFECTIVOS LABORADOS 2025'!B:F,3,0) -> 45600 | M49: =VLOOKUP(D49,'DÍAS EFECTIVOS LABORADOS 2025'!B:O,14,0) -> 248 | N49: =+ROUND(VLOOKUP(D49,'INGRESOS 2025'!$B$7:$V$159,21,0),2) -> 29023.25 | O49: ACTIVO | P49: =$N$103*M49 -> 12209.617 | Q49: =$N$104*N49 -> 2882.8055 | R49: =+ROUND(P49+Q49,2) -> 15092.42 | S49: =ROUND(HLOOKUP(D49,'5ta'!$C$7:$CF$118,112,0),2) -> 403.19 | V49: =+ROUND(R49-T49-S49-U49,2) -> 14689.23 | X49: =HLOOKUP(D49,'5ta'!$C$7:$CG$139,133,0) -> FALSE | Y49: =HLOOKUP(D49,'5ta'!$C$7:$CF$145,134,0) -> 00% - 08% | Z49: =VLOOKUP(D49,'[1]0220262'!$E$12:$AD$94,26,0) -> 0 | AB49: =VLOOKUP(D49,'[2]Archivo Excel Haberes Input'!$K$11:$K$80,1,0) -> 71726981
C50: 44 | D50: 72001771 | E50: GUEVARA SALINAS BRYAN GUSTAVO | F50: CUSTOMER SERVICES IMPORTACIÓN | G50: COMERCIAL- VENTAS | H50: VENTAS | I50: =VLOOKUP(D50,'DÍAS EFECTIVOS LABORADOS 2025'!B:F,3,0) -> 44483 | M50: =VLOOKUP(D50,'DÍAS EFECTIVOS LABORADOS 2025'!B:O,14,0) -> 232 | N50: =+ROUND(VLOOKUP(D50,'INGRESOS 2025'!$B$7:$V$159,21,0),2) -> 40650.5 | O50: ACTIVO | P50: =$N$103*M50 -> 11421.9 | Q50: =$N$104*N50 -> 4037.7107 | R50: =+ROUND(P50+Q50,2) -> 15459.61 | S50: =ROUND(HLOOKUP(D50,'5ta'!$C$7:$CF$118,112,0),2) -> 1236.77 | V50: =+ROUND(R50-T50-S50-U50,2) -> 14222.84 | W50: =+Y50*R50-S50 -> -0.0012 | X50: =HLOOKUP(D50,'5ta'!$C$7:$CG$139,133,0) -> TRUE | Y50: =HLOOKUP(D50,'5ta'!$C$7:$CF$135,129,0) -> 0.08 | Z50: =VLOOKUP(D50,'[1]0220262'!$E$12:$AD$94,26,0) -> 0 | AB50: =VLOOKUP(D50,'[2]Archivo Excel Haberes Input'!$K$11:$K$80,1,0) -> 72001771
C51: 45 | D51: 72016504 | E51: GUTIERREZ DE LA CRUZ MIGUEL ANGEL | F51: ASISTENTE DE DOCUMENTACIÓN | G51: DOCUMENTACION-VISTO BUENO | H51: OPERACIONES | I51: =VLOOKUP(D51,'DÍAS EFECTIVOS LABORADOS 2025'!B:F,3,0) -> 44432 | M51: =VLOOKUP(D51,'DÍAS EFECTIVOS LABORADOS 2025'!B:O,14,0) -> 228 | N51: =+ROUND(VLOOKUP(D51,'INGRESOS 2025'!$B$7:$V$159,21,0),2) -> 34784.83 | O51: ACTIVO | P51: =$N$103*M51 -> 11224.971 | Q51: =$N$104*N51 -> 3455.0886 | R51: =+ROUND(P51+Q51,2) -> 14680.06 | S51: =ROUND(HLOOKUP(D51,'5ta'!$C$7:$CF$118,112,0),2) -> 697.34 | V51: =+ROUND(R51-T51-S51-U51,2) -> 13982.72 | X51: =HLOOKUP(D51,'5ta'!$C$7:$CG$139,133,0) -> FALSE | Y51: =HLOOKUP(D51,'5ta'!$C$7:$CF$145,134,0) -> 00% - 08% | Z51: =VLOOKUP(D51,'[1]0220262'!$E$12:$AD$94,26,0) -> 0 | AB51: =VLOOKUP(D51,'[2]Archivo Excel Haberes Input'!$K$11:$K$80,1,0) -> 72016504
C52: 46 | D52: 72152204 | E52: HUAMAN COLLANTES WALTER JUNIOR | F52: ANALISTA DE DOCUMENTACIÓN | G52: DOCUMENTACION-VISTO BUENO | H52: OPERACIONES | I52: =VLOOKUP(D52,'DÍAS EFECTIVOS LABORADOS 2025'!B:F,3,0) -> 43724 | M52: =VLOOKUP(D52,'DÍAS EFECTIVOS LABORADOS 2025'!B:O,14,0) -> 239 | N52: =+ROUND(VLOOKUP(D52,'INGRESOS 2025'!$B$7:$V$159,21,0),2) -> 52538.27 | O52: ACTIVO | P52: =$N$103*M52 -> 11766.526 | Q52: =$N$104*N52 -> 5218.4926 | R52: =+ROUND(P52+Q52,2) -> 16985.02 | S52: =ROUND(HLOOKUP(D52,'5ta'!$C$7:$CF$118,112,0),2) -> 1358.8 | V52: =+ROUND(R52-T52-S52-U52,2) -> 15626.22 | W52: =+Y52*R52-S52 -> 0.0016 | X52: =HLOOKUP(D52,'5ta'!$C$7:$CG$139,133,0) -> TRUE | Y52: =HLOOKUP(D52,'5ta'!$C$7:$CF$135,129,0) -> 0.08 | Z52: =VLOOKUP(D52,'[1]0220262'!$E$12:$AD$94,26,0) -> 0 | AB52: =VLOOKUP(D52,'[2]Archivo Excel Haberes Input'!$K$11:$K$80,1,0) -> 72152204
C53: 47 | D53: 72152557 | E53: ENCALADA PRADA GLORIA STEFANY | F53: ASISTENTE DE DOCUMENTACIÓN | G53: DOCUMENTACION-VISTO BUENO | H53: OPERACIONES | I53: =VLOOKUP(D53,'DÍAS EFECTIVOS LABORADOS 2025'!B:F,3,0) -> 45313 | M53: =VLOOKUP(D53,'DÍAS EFECTIVOS LABORADOS 2025'!B:O,14,0) -> 243 | N53: =+ROUND(VLOOKUP(D53,'INGRESOS 2025'!$B$7:$V$159,21,0),2) -> 36400.78 | O53: ACTIVO | P53: =$N$103*M53 -> 11963.456 | Q53: =$N$104*N53 -> 3615.5968 | R53: =+ROUND(P53+Q53,2) -> 15579.05 | S53: =ROUND(HLOOKUP(D53,'5ta'!$C$7:$CF$118,112,0),2) -> 1168.06 | V53: =+ROUND(R53-T53-S53-U53,2) -> 14410.99 | X53: =HLOOKUP(D53,'5ta'!$C$7:$CG$139,133,0) -> FALSE | Y53: =HLOOKUP(D53,'5ta'!$C$7:$CF$145,134,0) -> 00% - 08% | Z53: =VLOOKUP(D53,'[1]0220262'!$E$12:$AD$94,26,0) -> 0 | AB53: =VLOOKUP(D53,'[2]Archivo Excel Haberes Input'!$K$11:$K$80,1,0) -> 72152557
C54: 48 | D54: 72410117 | E54: LOPEZ GAVELAN JESUS ALFREDO | I54: =VLOOKUP(D54,'DÍAS EFECTIVOS LABORADOS 2025'!B:F,3,0) -> 45414 | J54: =VLOOKUP(D54,'DÍAS EFECTIVOS LABORADOS 2025'!B:F,5,0) -> 45900 | M54: =VLOOKUP(D54,'DÍAS EFECTIVOS LABORADOS 2025'!B:O,14,0) -> 155 | N54: =+ROUND(VLOOKUP(D54,'INGRESOS 2025'!$B$7:$V$159,21,0),2) -> 22781.76 | O54: CESADO | P54: =$N$103*M54 -> 7631.0108 | Q54: =$N$104*N54 -> 2262.8542 | R54: =+ROUND(P54+Q54,2) -> 9893.86 | V54: =+ROUND(R54-T54-S54-U54,2) -> 9893.86 | Z54: =VLOOKUP(D54,'[1]0220262'!$E$12:$AD$94,26,0) -> #N/A
C55: 49 | D55: 72686896 | E55: REBATTA ROJAS GONZALO | F55: CUSTOMER SERVICES EXPORTACIÓN | G55: COMERCIAL- VENTAS | H55: VENTAS | I55: =VLOOKUP(D55,'DÍAS EFECTIVOS LABORADOS 2025'!B:F,3,0) -> 44453 | M55: =VLOOKUP(D55,'DÍAS EFECTIVOS LABORADOS 2025'!B:O,14,0) -> 234 | N55: =+ROUND(VLOOKUP(D55,'INGRESOS 2025'!$B$7:$V$159,21,0),2) -> 40522.26 | O55: ACTIVO | P55: =$N$103*M55 -> 11520.365 | Q55: =$N$104*N55 -> 4024.9729 | R55: =+ROUND(P55+Q55,2) -> 15545.34 | S55: =ROUND(HLOOKUP(D55,'5ta'!$C$7:$CF$118,112,0),2) -> 1243.63 | V55: =+ROUND(R55-T55-S55-U55,2) -> 14301.71 | W55: =+Y55*R55-S55 -> -0.0028 | X55: =HLOOKUP(D55,'5ta'!$C$7:$CG$139,133,0) -> TRUE | Y55: =HLOOKUP(D55,'5ta'!$C$7:$CF$135,129,0) -> 0.08 | Z55: =VLOOKUP(D55,'[1]0220262'!$E$12:$AD$94,26,0) -> 0 | AB55: =VLOOKUP(D55,'[2]Archivo Excel Haberes Input'!$K$11:$K$80,1,0) -> 72686896
C56: 50 | D56: 72857524 | E56: SANCHEZ VALDEZ MACARENA | F56: ASISTENTE DE DOCUMENTACIÓN | G56: DOCUMENTACIÓN Y VISTO BUENOS | H56: OPERACIONES | I56: =VLOOKUP(D56,'DÍAS EFECTIVOS LABORADOS 2025'!B:F,3,0) -> 45574 | M56: =VLOOKUP(D56,'DÍAS EFECTIVOS LABORADOS 2025'!B:O,14,0) -> 244 | N56: =+ROUND(VLOOKUP(D56,'INGRESOS 2025'!$B$7:$V$159,21,0),2) -> 42868.15 | O56: ACTIVO | P56: =$N$103*M56 -> 12012.688 | Q56: =$N$104*N56 -> 4257.9842 | R56: =+ROUND(P56+Q56,2) -> 16270.67 | S56: =ROUND(HLOOKUP(D56,'5ta'!$C$7:$CF$118,112,0),2) -> 1301.65 | V56: =+ROUND(R56-T56-S56-U56,2) -> 14969.02 | W56: =+Y56*R56-S56 -> 0.0036 | X56: =HLOOKUP(D56,'5ta'!$C$7:$CG$139,133,0) -> TRUE | Y56: =HLOOKUP(D56,'5ta'!$C$7:$CF$135,129,0) -> 0.08 | Z56: =VLOOKUP(D56,'[1]0220262'!$E$12:$AD$94,26,0) -> 0 | AB56: =VLOOKUP(D56,'[2]Archivo Excel Haberes Input'!$K$11:$K$80,1,0) -> 72857524
C57: 51 | D57: 72900856 | E57: TORRES ALEGRIA JUAN LUIS | I57: =VLOOKUP(D57,'DÍAS EFECTIVOS LABORADOS 2025'!B:F,3,0) -> 43845 | J57: =VLOOKUP(D57,'DÍAS EFECTIVOS LABORADOS 2025'!B:F,5,0) -> 45835 | M57: =VLOOKUP(D57,'DÍAS EFECTIVOS LABORADOS 2025'!B:O,14,0) -> 118 | N57: =+ROUND(VLOOKUP(D57,'INGRESOS 2025'!$B$7:$V$159,21,0),2) -> 29616.95 | O57: CESADO | P57: =$N$103*M57 -> 5809.4146 | Q57: =$N$104*N57 -> 2941.7762 | R57: =+ROUND(P57+Q57,2) -> 8751.19 | V57: =+ROUND(R57-T57-S57-U57,2) -> 8751.19 | Z57: =VLOOKUP(D57,'[1]0220262'!$E$12:$AD$94,26,0) -> #N/A
C58: 52 | D58: 73115211 | E58: TORRES TORRES ANA PAULA | F58: ASISTENTE DE VISTO BUENO | G58: DOCUMENTACION-VISTO BUENO | H58: OPERACIONES | I58: =VLOOKUP(D58,'DÍAS EFECTIVOS LABORADOS 2025'!B:F,3,0) -> 45481 | M58: =VLOOKUP(D58,'DÍAS EFECTIVOS LABORADOS 2025'!B:O,14,0) -> 244 | N58: =+ROUND(VLOOKUP(D58,'INGRESOS 2025'!$B$7:$V$159,21,0),2) -> 35332.91 | O58: ACTIVO | P58: =$N$103*M58 -> 12012.688 | Q58: =$N$104*N58 -> 3509.528 | R58: =+ROUND(P58+Q58,2) -> 15522.22 | S58: =ROUND(HLOOKUP(D58,'5ta'!$C$7:$CF$118,112,0),2) -> 775.5 | V58: =+ROUND(R58-T58-S58-U58,2) -> 14746.72 | X58: =HLOOKUP(D58,'5ta'!$C$7:$CG$139,133,0) -> FALSE | Y58: =HLOOKUP(D58,'5ta'!$C$7:$CF$145,134,0) -> 00% - 08% | Z58: =VLOOKUP(D58,'[1]0220262'!$E$12:$AD$94,26,0) -> 0 | AB58: =VLOOKUP(D58,'[2]Archivo Excel Haberes Input'!$K$11:$K$80,1,0) -> 73115211
C59: 53 | D59: 73958636 | E59: ALEJOS EGUSQUIZA AYXA JELUZETH | F59: CUSTOMER SERVICE EXPORTACIÓN | G59: ADMINISTRACION | H59: ADMINISTRACION | I59: =VLOOKUP(D59,'DÍAS EFECTIVOS LABORADOS 2025'!B:F,3,0) -> 43530 | M59: =VLOOKUP(D59,'DÍAS EFECTIVOS LABORADOS 2025'!B:O,14,0) -> 256 | N59: =+ROUND(VLOOKUP(D59,'INGRESOS 2025'!$B$7:$V$159,21,0),2) -> 47751.12 | O59: ACTIVO | P59: =$N$103*M59 -> 12603.476 | Q59: =$N$104*N59 -> 4742.9972 | R59: =+ROUND(P59+Q59,2) -> 17346.47 | S59: =ROUND(HLOOKUP(D59,'5ta'!$C$7:$CF$118,112,0),2) -> 1387.72 | V59: =+ROUND(R59-T59-S59-U59,2) -> 15958.75 | W59: =+Y59*R59-S59 -> -0.0024 | X59: =HLOOKUP(D59,'5ta'!$C$7:$CG$139,133,0) -> TRUE | Y59: =HLOOKUP(D59,'5ta'!$C$7:$CF$135,129,0) -> 0.08 | Z59: =VLOOKUP(D59,'[1]0220262'!$E$12:$AD$94,26,0) -> 0 | AB59: =VLOOKUP(D59,'[2]Archivo Excel Haberes Input'!$K$11:$K$80,1,0) -> 73958636
C60: 54 | D60: 74069271 | E60: HUAMANI ALTAMIRANO GABRIELA SABRINA | F60: ASISTENTE DE CUSTOMER SERVICES EXPORTACIÓN | G60: CONTROL DE EQUIPOS | H60: OPERACIONES | I60: =VLOOKUP(D60,'DÍAS EFECTIVOS LABORADOS 2025'!B:F,3,0) -> 44483 | M60: =VLOOKUP(D60,'DÍAS EFECTIVOS LABORADOS 2025'!B:O,14,0) -> 230 | N60: =+ROUND(VLOOKUP(D60,'INGRESOS 2025'!$B$7:$V$159,21,0),2) -> 34255.37 | O60: ACTIVO | P60: =$N$103*M60 -> 11323.435 | Q60: =$N$104*N60 -> 3402.4987 | R60: =+ROUND(P60+Q60,2) -> 14725.93 | S60: =ROUND(HLOOKUP(D60,'5ta'!$C$7:$CF$118,112,0),2) -> 912.87 | V60: =+ROUND(R60-T60-S60-U60,2) -> 13813.06 | X60: =HLOOKUP(D60,'5ta'!$C$7:$CG$139,133,0) -> FALSE | Y60: =HLOOKUP(D60,'5ta'!$C$7:$CF$145,134,0) -> 00% - 08% | Z60: =VLOOKUP(D60,'[1]0220262'!$E$12:$AD$94,26,0) -> 0 | AB60: =VLOOKUP(D60,'[2]Archivo Excel Haberes Input'!$K$11:$K$80,1,0) -> 74069271
C61: 55 | D61: 74080395 | E61: AVALOS MORANTE KATHERINE ALEXANDRA | F61: JEFE DE LOGISTICA INTEGRAL | G61: COMERCIAL- VENTAS | H61: VENTAS | I61: =VLOOKUP(D61,'DÍAS EFECTIVOS LABORADOS 2025'!B:F,3,0) -> 43497 | M61: =VLOOKUP(D61,'DÍAS EFECTIVOS LABORADOS 2025'!B:O,14,0) -> 245 | N61: =+ROUND(VLOOKUP(D61,'INGRESOS 2025'!$B$7:$V$159,21,0),2) -> 108446.98 | O61: ACTIVO | P61: =$N$103*M61 -> 12061.92 | Q61: =$N$104*N61 -> 10771.762 | R61: =+ROUND(P61+Q61,2) -> 22833.68 | S61: =ROUND(HLOOKUP(D61,'5ta'!$C$7:$CF$118,112,0),2) -> 3667.23 | V61: =+ROUND(R61-T61-S61-U61,2) -> 19166.45 | X61: =HLOOKUP(D61,'5ta'!$C$7:$CG$139,133,0) -> FALSE | Y61: =HLOOKUP(D61,'5ta'!$C$7:$CF$145,134,0) -> 14% - 17% | Z61: =VLOOKUP(D61,'[1]0220262'!$E$12:$AD$94,26,0) -> 0 | AB61: =VLOOKUP(D61,'[2]Archivo Excel Haberes Input'!$K$11:$K$80,1,0) -> 74080395
C62: 56 | D62: 74499365 | E62: GRANDA SANTIAGO YONATHAN SMIETH | I62: =VLOOKUP(D62,'DÍAS EFECTIVOS LABORADOS 2025'!B:F,3,0) -> 45181 | J62: =VLOOKUP(D62,'DÍAS EFECTIVOS LABORADOS 2025'!B:F,5,0) -> 46003 | M62: =VLOOKUP(D62,'DÍAS EFECTIVOS LABORADOS 2025'!B:O,14,0) -> 224 | N62: =+ROUND(VLOOKUP(D62,'INGRESOS 2025'!$B$7:$V$159,21,0),2) -> 65084.17 | O62: CESADO | P62: =$N$103*M62 -> 11028.041 | Q62: =$N$104*N62 -> 6464.6449 | R62: =+ROUND(P62+Q62,2) -> 17492.69 | U62: 48 | V62: =+ROUND(R62-T62-S62-U62,2) -> 17444.69 | Z62: =VLOOKUP(D62,'[1]0220262'!$E$12:$AD$94,26,0) -> #N/A
C63: 57 | D63: 75597433 | E63: AZAÑERO SALAZAR LUIS ARTURO | I63: =VLOOKUP(D63,'DÍAS EFECTIVOS LABORADOS 2025'!B:F,3,0) -> 45663 | J63: =VLOOKUP(D63,'DÍAS EFECTIVOS LABORADOS 2025'!B:F,5,0) -> 45807 | M63: =VLOOKUP(D63,'DÍAS EFECTIVOS LABORADOS 2025'!B:O,14,0) -> 102 | N63: =+ROUND(VLOOKUP(D63,'INGRESOS 2025'!$B$7:$V$159,21,0),2) -> 11805.56 | O63: CESADO | P63: =$N$103*M63 -> 5021.6974 | Q63: =$N$104*N63 -> 1172.6162 | R63: =+ROUND(P63+Q63,2) -> 6194.31 | V63: =+ROUND(R63-T63-S63-U63,2) -> 6194.31 | Z63: =VLOOKUP(D63,'[1]0220262'!$E$12:$AD$94,26,0) -> #N/A
C64: 58 | D64: 75743277 | E64: MALPARTIDA CASTILLO CLAUDIA | F64: ANALISTA DE PROCESOS Y DATOS | G64: PROYECTOS Y MEJORA CONTINUA | H64: OPERACIONES | I64: =VLOOKUP(D64,'DÍAS EFECTIVOS LABORADOS 2025'!B:F,3,0) -> 45628 | M64: =VLOOKUP(D64,'DÍAS EFECTIVOS LABORADOS 2025'!B:O,14,0) -> 224 | N64: =+ROUND(VLOOKUP(D64,'INGRESOS 2025'!$B$7:$V$159,21,0),2) -> 49662.62 | O64: ACTIVO | P64: =$N$103*M64 -> 11028.041 | Q64: =$N$104*N64 -> 4932.8616 | R64: =+ROUND(P64+Q64,2) -> 15960.9 | S64: =ROUND(HLOOKUP(D64,'5ta'!$C$7:$CF$118,112,0),2) -> 1276.87 | V64: =+ROUND(R64-T64-S64-U64,2) -> 14684.03 | W64: =+Y64*R64-S64 -> 0.002 | X64: =HLOOKUP(D64,'5ta'!$C$7:$CG$139,133,0) -> TRUE | Y64: =HLOOKUP(D64,'5ta'!$C$7:$CF$135,129,0) -> 0.08 | Z64: =VLOOKUP(D64,'[1]0220262'!$E$12:$AD$94,26,0) -> 0 | AB64: =VLOOKUP(D64,'[2]Archivo Excel Haberes Input'!$K$11:$K$80,1,0) -> 75743277
C65: 59 | D65: 76055775 | E65: ALAMA BERECHE ROYAL ANTHONY | F65: ANALISTA DE COBRANZAS Y FACTURACION | G65: CONTABILIDAD | H65: OPERACIONES | I65: =VLOOKUP(D65,'DÍAS EFECTIVOS LABORADOS 2025'!B:F,3,0) -> 45658 | M65: =VLOOKUP(D65,'DÍAS EFECTIVOS LABORADOS 2025'!B:O,14,0) -> 242 | N65: =+ROUND(VLOOKUP(D65,'INGRESOS 2025'!$B$7:$V$159,21,0),2) -> 34753.64 | O65: ACTIVO | P65: =$N$103*M65 -> 11914.223 | Q65: =$N$104*N65 -> 3451.9906 | R65: =+ROUND(P65+Q65,2) -> 15366.21 | S65: =ROUND(HLOOKUP(D65,'5ta'!$C$7:$CF$118,112,0),2) -> 1229.3 | V65: =+ROUND(R65-T65-S65-U65,2) -> 14136.91 | W65: =+Y65*R65-S65 -> -0.0032 | X65: =HLOOKUP(D65,'5ta'!$C$7:$CG$139,133,0) -> TRUE | Y65: =HLOOKUP(D65,'5ta'!$C$7:$CF$135,129,0) -> 0.08 | Z65: =VLOOKUP(D65,'[1]0220262'!$E$12:$AD$94,26,0) -> 0 | AB65: =VLOOKUP(D65,'[2]Archivo Excel Haberes Input'!$K$11:$K$80,1,0) -> 76055775
C66: 60 | D66: 76084478 | E66: SANCHEZ AUCCAPURE JILLS KRAINEEM | F66: ASISTENTE DE DOCUMENTACIÓN Y VISTO BUENO | G66: DOCUMENTACION-VISTO BUENO | H66: OPERACIONES | I66: =VLOOKUP(D66,'DÍAS EFECTIVOS LABORADOS 2025'!B:F,3,0) -> 45125 | M66: =VLOOKUP(D66,'DÍAS EFECTIVOS LABORADOS 2025'!B:O,14,0) -> 249 | N66: =+ROUND(VLOOKUP(D66,'INGRESOS 2025'!$B$7:$V$159,21,0),2) -> 30161.14 | O66: ACTIVO | P66: =$N$103*M66 -> 12258.85 | Q66: =$N$104*N66 -> 2995.8292 | R66: =+ROUND(P66+Q66,2) -> 15254.68 | S66: =ROUND(HLOOKUP(D66,'5ta'!$C$7:$CF$118,112,0),2) -> 459.33 | V66: =+ROUND(R66-T66-S66-U66,2) -> 14795.35 | X66: =HLOOKUP(D66,'5ta'!$C$7:$CG$139,133,0) -> FALSE | Y66: =HLOOKUP(D66,'5ta'!$C$7:$CF$145,134,0) -> 00% - 08% | Z66: =VLOOKUP(D66,'[1]0220262'!$E$12:$AD$94,26,0) -> 0 | AB66: =VLOOKUP(D66,'[2]Archivo Excel Haberes Input'!$K$11:$K$80,1,0) -> 76084478
C67: 61 | D67: 76163280 | E67: BENITES OTERO YRINNA GISELLA | F67: LIDER DE PROYECTOS | G67: SISTEMAS | H67: ADMINISTRACION | I67: =VLOOKUP(D67,'DÍAS EFECTIVOS LABORADOS 2025'!B:F,3,0) -> 45181 | M67: =VLOOKUP(D67,'DÍAS EFECTIVOS LABORADOS 2025'!B:O,14,0) -> 230 | N67: =+ROUND(VLOOKUP(D67,'INGRESOS 2025'!$B$7:$V$159,21,0),2) -> 56036.16 | O67: ACTIVO | P67: =$N$103*M67 -> 11323.435 | Q67: =$N$104*N67 -> 5565.9291 | R67: =+ROUND(P67+Q67,2) -> 16889.36 | S67: =ROUND(HLOOKUP(D67,'5ta'!$C$7:$CF$118,112,0),2) -> 2364.51 | V67: =+ROUND(R67-T67-S67-U67,2) -> 14524.85 | W67: =+Y67*R67-S67 -> 0.0004 | X67: =HLOOKUP(D67,'5ta'!$C$7:$CG$139,133,0) -> TRUE | Y67: =HLOOKUP(D67,'5ta'!$C$7:$CF$135,129,0) -> 0.14 | Z67: =VLOOKUP(D67,'[1]0220262'!$E$12:$AD$94,26,0) -> 0 | AB67: =VLOOKUP(D67,'[2]Archivo Excel Haberes Input'!$K$11:$K$80,1,0) -> 76163280
C68: 62 | D68: 76723256 | E68: REYNA CORTEZ PATRICK ADAMS | F68: SALES SUPPORT | G68: COMERCIAL- VENTAS | H68: VENTAS | I68: =VLOOKUP(D68,'DÍAS EFECTIVOS LABORADOS 2025'!B:F,3,0) -> 44636 | M68: =VLOOKUP(D68,'DÍAS EFECTIVOS LABORADOS 2025'!B:O,14,0) -> 231 | N68: =+ROUND(VLOOKUP(D68,'INGRESOS 2025'!$B$7:$V$159,21,0),2) -> 37520.43 | O68: ACTIVO | P68: =$N$103*M68 -> 11372.668 | Q68: =$N$104*N68 -> 3726.8088 | R68: =+ROUND(P68+Q68,2) -> 15099.48 | S68: =ROUND(HLOOKUP(D68,'5ta'!$C$7:$CF$118,112,0),2) -> 1058.4 | V68: =+ROUND(R68-T68-S68-U68,2) -> 14041.08 | X68: =HLOOKUP(D68,'5ta'!$C$7:$CG$139,133,0) -> FALSE | Y68: =HLOOKUP(D68,'5ta'!$C$7:$CF$145,134,0) -> 00% - 08% | Z68: =VLOOKUP(D68,'[1]0220262'!$E$12:$AD$94,26,0) -> 0 | AB68: =VLOOKUP(D68,'[2]Archivo Excel Haberes Input'!$K$11:$K$80,1,0) -> 76723256
C69: 63 | D69: 77473806 | E69: SANDOVAL GONZALES YASIRA JASMIN | F69: ASISTENTE DE DOCUMENTACIÓN | G69: DOCUMENTACION-VISTO BUENO | H69: OPERACIONES | I69: =VLOOKUP(D69,'DÍAS EFECTIVOS LABORADOS 2025'!B:F,3,0) -> 45261 | M69: =VLOOKUP(D69,'DÍAS EFECTIVOS LABORADOS 2025'!B:O,14,0) -> 275 | N69: =+ROUND(VLOOKUP(D69,'INGRESOS 2025'!$B$7:$V$159,21,0),2) -> 27084.83 | O69: ACTIVO | P69: =$N$103*M69 -> 13538.89 | Q69: =$N$104*N69 -> 2690.2672 | R69: =+ROUND(P69+Q69,2) -> 16229.16 | S69: =ROUND(HLOOKUP(D69,'5ta'!$C$7:$CF$118,112,0),2) -> 892.94 | V69: =+ROUND(R69-T69-S69-U69,2) -> 15336.22 | X69: =HLOOKUP(D69,'5ta'!$C$7:$CG$139,133,0) -> FALSE | Y69: =HLOOKUP(D69,'5ta'!$C$7:$CF$145,134,0) -> 00% - 08% | Z69: =VLOOKUP(D69,'[1]0220262'!$E$12:$AD$94,26,0) -> 0 | AB69: =VLOOKUP(D69,'[2]Archivo Excel Haberes Input'!$K$11:$K$80,1,0) -> 77473806
C70: 64 | D70: 002120932 | E70: GAME LOAIZA MANUELXAVIER | F70: PRESIDENTE EJECUTIVO | G70: GERENCIA GENERAL | H70: VARIOS | I70: =VLOOKUP(D70,'DÍAS EFECTIVOS LABORADOS 2025'!B:F,3,0) -> 43678 | M70: =VLOOKUP(D70,'DÍAS EFECTIVOS LABORADOS 2025'!B:O,14,0) -> 249 | N70: =+ROUND(VLOOKUP(D70,'INGRESOS 2025'!$B$7:$V$159,21,0),2) -> 2243115.6 | O70: ACTIVO | P70: =$N$103*M70 -> 12258.85 | Q70: =$N$104*N70 -> 222802.96 | R70: =+ROUND(P70+Q70,2) -> 235061.81 | S70: =ROUND(HLOOKUP(D70,'5ta'!$C$7:$CF$118,112,0),2) -> 70518.54 | V70: =+ROUND(R70-T70-S70-U70,2) -> 164543.27 | W70: =+Y70*R70-S70 -> 0.003 | X70: =HLOOKUP(D70,'5ta'!$C$7:$CG$139,133,0) -> TRUE | Y70: =HLOOKUP(D70,'5ta'!$C$7:$CF$135,129,0) -> 0.3 | Z70: =VLOOKUP(D70,'[1]0220262'!$E$12:$AD$94,26,0) -> 0 | AA70: =+ROUND(V70/$AA$3,2) -> 47901.97 | AC70: =+AA70+AA71 -> 56963.59
C71: 65 | D71: 002420607 | E71: ESCALANTE ZUÑIGA DAVID | F71: GERENTE DE PROYECTO Y MEJORA CONTÍNUA | G71: PROYECTO Y MEJORA CONTINUA | H71: ADMINISTRACION | I71: =VLOOKUP(D71,'DÍAS EFECTIVOS LABORADOS 2025'!B:F,3,0) -> 45261 | M71: =VLOOKUP(D71,'DÍAS EFECTIVOS LABORADOS 2025'!B:O,14,0) -> 249 | N71: =+ROUND(VLOOKUP(D71,'INGRESOS 2025'!$B$7:$V$159,21,0),2) -> 324259 | O71: ACTIVO | P71: =$N$103*M71 -> 12258.85 | Q71: =$N$104*N71 -> 32207.821 | R71: =+ROUND(P71+Q71,2) -> 44466.67 | S71: =+ROUND(R71*Y71,2) -> 13340 | V71: =+ROUND(R71-T71-S71-U71,2) -> 31126.67 | W71: NO DOMICILIADO | X71: =HLOOKUP(D71,'5ta'!$C$7:$CG$139,133,0) -> TRUE | Y71: 0.3 | Z71: =VLOOKUP(D71,'[1]0220262'!$E$12:$AD$94,26,0) -> 0 | AA71: =+ROUND(V71/$AA$3,2) -> 9061.62
C72: 66 | D72: 005608621 | E72: GAME TRIVIÑO MARIA JOSE | F72: GERENTE DE TALENTO HUMANO | G72: TALENTO HUMANO | H72: ADMINISTRACION | I72: =VLOOKUP(D72,'DÍAS EFECTIVOS LABORADOS 2025'!B:F,3,0) -> 45170 | M72: =VLOOKUP(D72,'DÍAS EFECTIVOS LABORADOS 2025'!B:O,14,0) -> 249 | N72: =+ROUND(VLOOKUP(D72,'INGRESOS 2025'!$B$7:$V$159,21,0),2) -> 300685.42 | O72: ACTIVO | P72: =$N$103*M72 -> 12258.85 | Q72: =$N$104*N72 -> 29866.317 | R72: =+ROUND(P72+Q72,2) -> 42125.17 | S72: =ROUND(HLOOKUP(D72,'5ta'!$C$7:$CF$118,112,0),2) -> 12321.92 | V72: =+ROUND(R72-T72-S72-U72,2) -> 29803.25 | X72: =HLOOKUP(D72,'5ta'!$C$7:$CG$139,133,0) -> FALSE | Y72: =HLOOKUP(D72,'5ta'!$C$7:$CF$145,134,0) -> 20% - 30% | Z72: =VLOOKUP(D72,'[1]0220262'!$E$12:$AD$94,26,0) -> 0 | AA72: =+ROUND(V72/$AA$3,2) -> 8676.35
C73: 67 | D73: 005698394 | E73: GAME TRIVIÑO JUAN ANDRES | F73: GERENTE DE COMPRAS Y BODEGA | G73: ADMINISTRACION | H73: ADMINISTRACION | I73: =VLOOKUP(D73,'DÍAS EFECTIVOS LABORADOS 2025'!B:F,3,0) -> 45170 | M73: =VLOOKUP(D73,'DÍAS EFECTIVOS LABORADOS 2025'!B:O,14,0) -> 249 | N73: =+ROUND(VLOOKUP(D73,'INGRESOS 2025'!$B$7:$V$159,21,0),2) -> 300685.42 | O73: ACTIVO | P73: =$N$103*M73 -> 12258.85 | Q73: =$N$104*N73 -> 29866.317 | R73: =+ROUND(P73+Q73,2) -> 42125.17 | S73: =ROUND(HLOOKUP(D73,'5ta'!$C$7:$CF$118,112,0),2) -> 12321.92 | V73: =+ROUND(R73-T73-S73-U73,2) -> 29803.25 | X73: =HLOOKUP(D73,'5ta'!$C$7:$CG$139,133,0) -> FALSE | Y73: =HLOOKUP(D73,'5ta'!$C$7:$CF$145,134,0) -> 20% - 30% | Z73: =VLOOKUP(D73,'[1]0220262'!$E$12:$AD$94,26,0) -> 0 | AA73: =+ROUND(V73/$AA$3,2) -> 8676.35
C74: 68 | D74: 006123587 | E74: GAME TRIVIÑO MANUEL XAVIER | F74: GERENTE DE ADMINISTRACIÓN | G74: ADMINISTRACION | H74: ADMINISTRACION | I74: =VLOOKUP(D74,'DÍAS EFECTIVOS LABORADOS 2025'!B:F,3,0) -> 45170 | M74: =VLOOKUP(D74,'DÍAS EFECTIVOS LABORADOS 2025'!B:O,14,0) -> 249 | N74: =+ROUND(VLOOKUP(D74,'INGRESOS 2025'!$B$7:$V$159,21,0),2) -> 361118.26 | O74: ACTIVO | P74: =$N$103*M74 -> 12258.85 | Q74: =$N$104*N74 -> 35868.957 | R74: =+ROUND(P74+Q74,2) -> 48127.81 | S74: =ROUND(HLOOKUP(D74,'5ta'!$C$7:$CF$118,112,0),2) -> 14438.34 | V74: =+ROUND(R74-T74-S74-U74,2) -> 33689.47 | W74: =+Y74*R74-S74 -> 0.003 | X74: =HLOOKUP(D74,'5ta'!$C$7:$CG$139,133,0) -> TRUE | Y74: =HLOOKUP(D74,'5ta'!$C$7:$CF$135,129,0) -> 0.3 | Z74: =VLOOKUP(D74,'[1]0220262'!$E$12:$AD$94,26,0) -> 0 | AA74: =+ROUND(V74/$AA$3,2) -> 9807.71
C75: 69 | D75: 74723670 | E75: QUINTO CAMAHUALI LISETH CHARO | F75: AUXILIAR DE LIMPIEZA | G75: ADMINISTRACION | H75: ADMINISTRACION | I75: =VLOOKUP(D75,'DÍAS EFECTIVOS LABORADOS 2025'!B:F,3,0) -> 45689 | M75: =VLOOKUP(D75,'DÍAS EFECTIVOS LABORADOS 2025'!B:O,14,0) -> 221 | N75: =+ROUND(VLOOKUP(D75,'INGRESOS 2025'!$B$7:$V$159,21,0),2) -> 21366.69 | O75: ACTIVO | P75: =$N$103*M75 -> 10880.344 | Q75: =$N$104*N75 -> 2122.2989 | R75: =+ROUND(P75+Q75,2) -> 13002.64 | S75: =ROUND(HLOOKUP(D75,'5ta'!$C$7:$CF$118,112,0),2) -> 132.41 | V75: =+ROUND(R75-T75-S75-U75,2) -> 12870.23 | X75: =HLOOKUP(D75,'5ta'!$C$7:$CG$139,133,0) -> FALSE | Y75: =HLOOKUP(D75,'5ta'!$C$7:$CF$145,134,0) -> 00% - 08% | Z75: =VLOOKUP(D75,'[1]0220262'!$E$12:$AD$94,26,0) -> 0 | AB75: =VLOOKUP(D75,'[2]Archivo Excel Haberes Input'!$K$11:$K$80,1,0) -> 74723670
C76: 70 | D76: 70831120 | E76: TORRES OCHOA KAMILA OLENKA | I76: =VLOOKUP(D76,'DÍAS EFECTIVOS LABORADOS 2025'!B:F,3,0) -> 45719 | J76: =VLOOKUP(D76,'DÍAS EFECTIVOS LABORADOS 2025'!B:F,5,0) -> 45900 | M76: =VLOOKUP(D76,'DÍAS EFECTIVOS LABORADOS 2025'!B:O,14,0) -> 120 | N76: =+ROUND(VLOOKUP(D76,'INGRESOS 2025'!$B$7:$V$159,21,0),2) -> 33270.45 | O76: CESADO | P76: =$N$103*M76 -> 5907.8793 | Q76: =$N$104*N76 -> 3304.6691 | R76: =+ROUND(P76+Q76,2) -> 9212.55 | V76: =+ROUND(R76-T76-S76-U76,2) -> 9212.55 | Z76: =VLOOKUP(D76,'[1]0220262'!$E$12:$AD$94,26,0) -> #N/A
C77: 71 | D77: 008938904 | E77: CABEZAS RUBIO JORGE ARTURO | F77: COORDINADOR LOGISTICO REGIONAL | G77: ADMINISTRACION | H77: ADMINISTRACION | I77: =VLOOKUP(D77,'DÍAS EFECTIVOS LABORADOS 2025'!B:F,3,0) -> 45717 | M77: =VLOOKUP(D77,'DÍAS EFECTIVOS LABORADOS 2025'!B:O,14,0) -> 207 | N77: =+ROUND(VLOOKUP(D77,'INGRESOS 2025'!$B$7:$V$159,21,0),2) -> 49902.04 | O77: ACTIVO | P77: =$N$103*M77 -> 10191.092 | Q77: =$N$104*N77 -> 4956.6426 | R77: =+ROUND(P77+Q77,2) -> 15147.73 | S77: =ROUND(HLOOKUP(D77,'5ta'!$C$7:$CF$118,112,0),2) -> 1592.87 | V77: =+ROUND(R77-T77-S77-U77,2) -> 13554.86 | X77: =HLOOKUP(D77,'5ta'!$C$7:$CG$139,133,0) -> FALSE | Y77: =HLOOKUP(D77,'5ta'!$C$7:$CF$145,134,0) -> 08% - 14% | Z77: =VLOOKUP(D77,'[1]0220262'!$E$12:$AD$94,26,0) -> 0 | AA77: =+ROUND(V77/$AA$3,2) -> 3946.1 | AB77: =VLOOKUP(D77,'[2]Archivo Excel Haberes Input'!$K$11:$K$80,1,0) -> #N/A
C78: 72 | D78: 40365445 | E78: DE OLARTE FERNANDEZ MILAGROS | I78: =VLOOKUP(D78,'DÍAS EFECTIVOS LABORADOS 2025'!B:F,3,0) -> 45783 | J78: =VLOOKUP(D78,'DÍAS EFECTIVOS LABORADOS 2025'!B:F,5,0) -> 45961 | M78: =VLOOKUP(D78,'DÍAS EFECTIVOS LABORADOS 2025'!B:O,14,0) -> 121 | N78: =+ROUND(VLOOKUP(D78,'INGRESOS 2025'!$B$7:$V$159,21,0),2) -> 25331.47 | O78: CESADO | P78: =$N$103*M78 -> 5957.1116 | Q78: =$N$104*N78 -> 2516.1104 | R78: =+ROUND(P78+Q78,2) -> 8473.22 | V78: =+ROUND(R78-T78-S78-U78,2) -> 8473.22 | Z78: =VLOOKUP(D78,'[1]0220262'!$E$12:$AD$94,26,0) -> #N/A
C79: 73 | D79: 78377581 | E79: ROMAN RENTERIA ZAIDA YASMIN | F79: SALES SUPPORT | G79: OPERACIONES | H79: ADMINISTRACION | I79: =VLOOKUP(D79,'DÍAS EFECTIVOS LABORADOS 2025'!B:F,3,0) -> 45784 | M79: =VLOOKUP(D79,'DÍAS EFECTIVOS LABORADOS 2025'!B:O,14,0) -> 160 | N79: =+ROUND(VLOOKUP(D79,'INGRESOS 2025'!$B$7:$V$159,21,0),2) -> 22145.08 | O79: ACTIVO | P79: =$N$103*M79 -> 7877.1724 | Q79: =$N$104*N79 -> 2199.6144 | R79: =+ROUND(P79+Q79,2) -> 10076.79 | S79: =ROUND(HLOOKUP(D79,'5ta'!$C$7:$CF$118,112,0),2) -> 806.14 | V79: =+ROUND(R79-T79-S79-U79,2) -> 9270.65 | W79: =+Y79*R79-S79 -> 0.0032 | X79: =HLOOKUP(D79,'5ta'!$C$7:$CG$139,133,0) -> TRUE | Y79: =HLOOKUP(D79,'5ta'!$C$7:$CF$135,129,0) -> 0.08 | Z79: =VLOOKUP(D79,'[1]0220262'!$E$12:$AD$94,26,0) -> 0 | AB79: =VLOOKUP(D79,'[2]Archivo Excel Haberes Input'!$K$11:$K$80,1,0) -> 78377581
C80: 74 | D80: 42151178 | E80: BORDA LEON ROSARIO LIZBETH | F80: SUB-GERENTE DE TALENTO HUMANO | G80: TALENTO HUMANO | H80: ADMINISTRACION | I80: =VLOOKUP(D80,'DÍAS EFECTIVOS LABORADOS 2025'!B:F,3,0) -> 45839 | M80: =VLOOKUP(D80,'DÍAS EFECTIVOS LABORADOS 2025'!B:O,14,0) -> 124 | N80: =+ROUND(VLOOKUP(D80,'INGRESOS 2025'!$B$7:$V$159,21,0),2) -> 79502.5 | O80: ACTIVO | P80: =$N$103*M80 -> 6104.8086 | Q80: =$N$104*N80 -> 7896.7809 | R80: =+ROUND(P80+Q80,2) -> 14001.59 | S80: =ROUND(HLOOKUP(D80,'5ta'!$C$7:$CF$118,112,0),2) -> 2380.27 | V80: =+ROUND(R80-T80-S80-U80,2) -> 11621.32 | W80: =+Y80*R80-S80 -> 0.0003 | X80: =HLOOKUP(D80,'5ta'!$C$7:$CG$139,133,0) -> TRUE | Y80: =HLOOKUP(D80,'5ta'!$C$7:$CF$135,129,0) -> 0.17 | Z80: =VLOOKUP(D80,'[1]0220262'!$E$12:$AD$94,26,0) -> 0 | AB80: =VLOOKUP(D80,'[2]Archivo Excel Haberes Input'!$K$11:$K$80,1,0) -> 42151178
C81: 75 | D81: 44521978 | E81: SORIA OCHOA MAGALY GIOVANNA | I81: =VLOOKUP(D81,'DÍAS EFECTIVOS LABORADOS 2025'!B:F,3,0) -> 45868 | J81: =VLOOKUP(D81,'DÍAS EFECTIVOS LABORADOS 2025'!B:F,5,0) -> 45902 | M81: =VLOOKUP(D81,'DÍAS EFECTIVOS LABORADOS 2025'!B:O,14,0) -> 24 | N81: =+ROUND(VLOOKUP(D81,'INGRESOS 2025'!$B$7:$V$159,21,0),2) -> 7326.52 | O81: CESADO | P81: =$N$103*M81 -> 1181.5759 | Q81: =$N$104*N81 -> 727.72458 | R81: =+ROUND(P81+Q81,2) -> 1909.3 | V81: =+ROUND(R81-T81-S81-U81,2) -> 1909.3 | Z81: =VLOOKUP(D81,'[1]0220262'!$E$12:$AD$94,26,0) -> #N/A
C82: 76 | D82: 73218422 | E82: VERA HUAMANCHUMO ANA PAULA JANET | F82: ASISTENTE DE CUSTOMER SERVICE IMPORTACION | G82: COMERCIAL | H82: VENTAS | I82: =VLOOKUP(D82,'DÍAS EFECTIVOS LABORADOS 2025'!B:F,3,0) -> 45852 | M82: =VLOOKUP(D82,'DÍAS EFECTIVOS LABORADOS 2025'!B:O,14,0) -> 111 | N82: =+ROUND(VLOOKUP(D82,'INGRESOS 2025'!$B$7:$V$159,21,0),2) -> 15947.92 | O82: ACTIVO | P82: =$N$103*M82 -> 5464.7883 | Q82: =$N$104*N82 -> 1584.0663 | R82: =+ROUND(P82+Q82,2) -> 7048.85 | S82: =ROUND(HLOOKUP(D82,'5ta'!$C$7:$CF$118,112,0),2) -> 310.38 | V82: =+ROUND(R82-T82-S82-U82,2) -> 6738.47 | X82: =HLOOKUP(D82,'5ta'!$C$7:$CG$139,133,0) -> FALSE | Y82: =HLOOKUP(D82,'5ta'!$C$7:$CF$145,134,0) -> 00% - 08% | Z82: =VLOOKUP(D82,'[1]0220262'!$E$12:$AD$94,26,0) -> 0 | AB82: =VLOOKUP(D82,'[2]Archivo Excel Haberes Input'!$K$11:$K$80,1,0) -> 73218422
C83: 77 | D83: 45533404 | E83: CASTILLO SANDOVAL MARIA ISABEL | F83: ASISTENTE DE DOCUMENTACIÓN | G83: DOCUMENTACION Y VISTO BUENO | H83: ADMINISTRACION | I83: =VLOOKUP(D83,'DÍAS EFECTIVOS LABORADOS 2025'!B:F,3,0) -> 45887 | M83: =VLOOKUP(D83,'DÍAS EFECTIVOS LABORADOS 2025'!B:O,14,0) -> 94 | N83: =+ROUND(VLOOKUP(D83,'INGRESOS 2025'!$B$7:$V$159,21,0),2) -> 10350 | O83: ACTIVO | P83: =$N$103*M83 -> 4627.8388 | Q83: =$N$104*N83 -> 1028.0391 | R83: =+ROUND(P83+Q83,2) -> 5655.88 | S83: =ROUND(HLOOKUP(D83,'5ta'!$C$7:$CF$118,112,0),2) -> 0 | V83: =+ROUND(R83-T83-S83-U83,2) -> 5655.88 | W83: =+Y83*R83-S83 -> 0 | X83: =HLOOKUP(D83,'5ta'!$C$7:$CG$139,133,0) -> TRUE | Y83: =HLOOKUP(D83,'5ta'!$C$7:$CF$135,129,0) -> 0 | Z83: =VLOOKUP(D83,'[1]0220262'!$E$12:$AD$94,26,0) -> 0 | AB83: =VLOOKUP(D83,'[2]Archivo Excel Haberes Input'!$K$11:$K$80,1,0) -> 45533404
C84: 78 | D84: 48332716 | E84: GUILLEN QUEZADA EMELY HARUMI | F84: ANALISTA DE ADMINISTRACION DE PERSONAL | G84: TALENTO HUMANO | H84: ADMINISTRACION | I84: =VLOOKUP(D84,'DÍAS EFECTIVOS LABORADOS 2025'!B:F,3,0) -> 45870 | M84: =VLOOKUP(D84,'DÍAS EFECTIVOS LABORADOS 2025'!B:O,14,0) -> 102 | N84: =+ROUND(VLOOKUP(D84,'INGRESOS 2025'!$B$7:$V$159,21,0),2) -> 19318.25 | O84: CESADO EN 2026 | P84: =$N$103*M84 -> 5021.6974 | Q84: =$N$104*N84 -> 1918.8326 | R84: =+ROUND(P84+Q84,2) -> 6940.53 | V84: =+ROUND(R84-T84-S84-U84,2) -> 6940.53 | Z84: =VLOOKUP(D84,'[1]0220262'!$E$12:$AD$94,26,0) -> 46068
C85: 79 | D85: 76644670 | E85: MARTINEZ HUAMAN GABRIELA NICOLE | F85: ASISTENTE DE ADMINISTRACION Y CONTROL | G85: ADMINISTRACION | H85: ADMINISTRACION | I85: =VLOOKUP(D85,'DÍAS EFECTIVOS LABORADOS 2025'!B:F,3,0) -> 45894 | M85: =VLOOKUP(D85,'DÍAS EFECTIVOS LABORADOS 2025'!B:O,14,0) -> 88 | N85: =+ROUND(VLOOKUP(D85,'INGRESOS 2025'!$B$7:$V$159,21,0),2) -> 10650.45 | O85: ACTIVO | P85: =$N$103*M85 -> 4332.4448 | Q85: =$N$104*N85 -> 1057.8821 | R85: =+ROUND(P85+Q85,2) -> 5390.33 | S85: =ROUND(HLOOKUP(D85,'5ta'!$C$7:$CF$118,112,0),2) -> 0 | V85: =+ROUND(R85-T85-S85-U85,2) -> 5390.33 | W85: =+Y85*R85-S85 -> 0 | X85: =HLOOKUP(D85,'5ta'!$C$7:$CG$139,133,0) -> TRUE | Y85: =HLOOKUP(D85,'5ta'!$C$7:$CF$135,129,0) -> 0 | Z85: =VLOOKUP(D85,'[1]0220262'!$E$12:$AD$94,26,0) -> 0 | AB85: =VLOOKUP(D85,'[2]Archivo Excel Haberes Input'!$K$11:$K$80,1,0) -> 76644670
C86: 80 | D86: 74611823 | E86: CARDENAS CARDENAS LESLIE ELIZABETH | F86: ANALISTA DE INTELIGENCIA COMERCIAL | G86: VENTAS | H86: VENTAS | I86: =VLOOKUP(D86,'DÍAS EFECTIVOS LABORADOS 2025'!B:F,3,0) -> 45908 | M86: =VLOOKUP(D86,'DÍAS EFECTIVOS LABORADOS 2025'!B:O,14,0) -> 79 | N86: =+ROUND(VLOOKUP(D86,'INGRESOS 2025'!$B$7:$V$159,21,0),2) -> 13195.46 | O86: ACTIVO | P86: =$N$103*M86 -> 3889.3539 | Q86: =$N$104*N86 -> 1310.6714 | R86: =+ROUND(P86+Q86,2) -> 5200.03 | S86: =ROUND(HLOOKUP(D86,'5ta'!$C$7:$CF$118,112,0),2) -> 416 | V86: =+ROUND(R86-T86-S86-U86,2) -> 4784.03 | W86: =+Y86*R86-S86 -> 0.0024 | X86: =HLOOKUP(D86,'5ta'!$C$7:$CG$139,133,0) -> TRUE | Y86: =HLOOKUP(D86,'5ta'!$C$7:$CF$135,129,0) -> 0.08 | Z86: =VLOOKUP(D86,'[1]0220262'!$E$12:$AD$94,26,0) -> 0 | AB86: =VLOOKUP(D86,'[2]Archivo Excel Haberes Input'!$K$11:$K$80,1,0) -> 74611823
C87: 81 | D87: 10659025 | E87: LEON FUENTES ROCIO MATILDE | F87: AUXILIAR DE LIMPIEZA | G87: ADMINISTRACION | H87: ADMINISTRACION | I87: =VLOOKUP(D87,'DÍAS EFECTIVOS LABORADOS 2025'!B:F,3,0) -> 45943 | M87: =VLOOKUP(D87,'DÍAS EFECTIVOS LABORADOS 2025'!B:O,14,0) -> 55 | N87: =+ROUND(VLOOKUP(D87,'INGRESOS 2025'!$B$7:$V$159,21,0),2) -> 5543.67 | O87: ACTIVO | P87: =$N$103*M87 -> 2707.778 | Q87: =$N$104*N87 -> 550.63863 | R87: =+ROUND(P87+Q87,2) -> 3258.42 | S87: =ROUND(HLOOKUP(D87,'5ta'!$C$7:$CF$118,112,0),2) -> 0 | V87: =+ROUND(R87-T87-S87-U87,2) -> 3258.42 | W87: =+Y87*R87-S87 -> 0 | X87: =HLOOKUP(D87,'5ta'!$C$7:$CG$139,133,0) -> TRUE | Y87: =HLOOKUP(D87,'5ta'!$C$7:$CF$135,129,0) -> 0 | Z87: =VLOOKUP(D87,'[1]0220262'!$E$12:$AD$94,26,0) -> 0 | AB87: =VLOOKUP(D87,'[2]Archivo Excel Haberes Input'!$K$11:$K$80,1,0) -> 10659025
C88: 82 | D88: 46137609 | E88: FERNANDEZ MALASQUEZ KATHERINE ROSMERY | F88: CUSTOMER SERVICE EXPORTACIÓN | G88: COMERCIAL | H88: VENTAS | I88: =VLOOKUP(D88,'DÍAS EFECTIVOS LABORADOS 2025'!B:F,3,0) -> 45943 | M88: =VLOOKUP(D88,'DÍAS EFECTIVOS LABORADOS 2025'!B:O,14,0) -> 55 | N88: =+ROUND(VLOOKUP(D88,'INGRESOS 2025'!$B$7:$V$159,21,0),2) -> 11313.81 | O88: ACTIVO | P88: =$N$103*M88 -> 2707.778 | Q88: =$N$104*N88 -> 1123.7719 | R88: =+ROUND(P88+Q88,2) -> 3831.55 | S88: =ROUND(HLOOKUP(D88,'5ta'!$C$7:$CF$118,112,0),2) -> 306.52 | V88: =+ROUND(R88-T88-S88-U88,2) -> 3525.03 | W88: =+Y88*R88-S88 -> 0.004 | X88: =HLOOKUP(D88,'5ta'!$C$7:$CG$139,133,0) -> TRUE | Y88: =HLOOKUP(D88,'5ta'!$C$7:$CF$135,129,0) -> 0.08 | Z88: =VLOOKUP(D88,'[1]0220262'!$E$12:$AD$94,26,0) -> 0 | AB88: =VLOOKUP(D88,'[2]Archivo Excel Haberes Input'!$K$11:$K$80,1,0) -> 46137609
C89: 83 | D89: 72531605 | E89: ROBINSON TORIBIO SARA JANET | F89: JEFE DE COMPRAS | G89: COMPRAS | H89: ADMINISTRACION | I89: =VLOOKUP(D89,'DÍAS EFECTIVOS LABORADOS 2025'!B:F,3,0) -> 45931 | M89: =VLOOKUP(D89,'DÍAS EFECTIVOS LABORADOS 2025'!B:O,14,0) -> 62 | N89: =+ROUND(VLOOKUP(D89,'INGRESOS 2025'!$B$7:$V$159,21,0),2) -> 16034.5 | O89: ACTIVO | P89: =$N$103*M89 -> 3052.4043 | Q89: =$N$104*N89 -> 1592.6661 | R89: =+ROUND(P89+Q89,2) -> 4645.07 | S89: =ROUND(HLOOKUP(D89,'5ta'!$C$7:$CF$118,112,0),2) -> 371.61 | V89: =+ROUND(R89-T89-S89-U89,2) -> 4273.46 | W89: =+Y89*R89-S89 -> -0.0044 | X89: =HLOOKUP(D89,'5ta'!$C$7:$CG$139,133,0) -> TRUE | Y89: =HLOOKUP(D89,'5ta'!$C$7:$CF$135,129,0) -> 0.08 | Z89: =VLOOKUP(D89,'[1]0220262'!$E$12:$AD$94,26,0) -> 0 | AB89: =VLOOKUP(D89,'[2]Archivo Excel Haberes Input'!$K$11:$K$80,1,0) -> 72531605
C90: 84 | D90: 75267086 | E90: ZETA CORONADO SHAHIRA CECILIA | F90: AUXILIAR ADMINISTRATIVO - RECEPCION | G90: ADMINISTRACION | H90: ADMINISTRACION | I90: =VLOOKUP(D90,'DÍAS EFECTIVOS LABORADOS 2025'!B:F,3,0) -> 45931 | M90: =VLOOKUP(D90,'DÍAS EFECTIVOS LABORADOS 2025'!B:O,14,0) -> 62 | N90: =+ROUND(VLOOKUP(D90,'INGRESOS 2025'!$B$7:$V$159,21,0),2) -> 6303.37 | O90: ACTIVO | P90: =$N$103*M90 -> 3052.4043 | Q90: =$N$104*N90 -> 626.09769 | R90: =+ROUND(P90+Q90,2) -> 3678.5 | S90: =ROUND(HLOOKUP(D90,'5ta'!$C$7:$CF$118,112,0),2) -> 0 | V90: =+ROUND(R90-T90-S90-U90,2) -> 3678.5 | W90: =+Y90*R90-S90 -> 0 | X90: =HLOOKUP(D90,'5ta'!$C$7:$CG$139,133,0) -> TRUE | Y90: =HLOOKUP(D90,'5ta'!$C$7:$CF$135,129,0) -> 0 | Z90: =VLOOKUP(D90,'[1]0220262'!$E$12:$AD$94,26,0) -> 0 | AB90: =VLOOKUP(D90,'[2]Archivo Excel Haberes Input'!$K$11:$K$80,1,0) -> 75267086
C91: 85 | D91: 46854908 | E91: MURGA ESPINOZA YAJAIRA LISBEL | F91: COORDINADORA DE NOMINAS Y ADMINISTRACION DE PERSONAL | G91: TALENTO HUMANO | H91: ADMINISTRACION | I91: =VLOOKUP(D91,'DÍAS EFECTIVOS LABORADOS 2025'!B:F,3,0) -> 45964 | M91: =VLOOKUP(D91,'DÍAS EFECTIVOS LABORADOS 2025'!B:O,14,0) -> 40 | N91: =+ROUND(VLOOKUP(D91,'INGRESOS 2025'!$B$7:$V$159,21,0),2) -> 10500 | O91: ACTIVO | P91: =$N$103*M91 -> 1969.2931 | Q91: =$N$104*N91 -> 1042.9383 | R91: =+ROUND(P91+Q91,2) -> 3012.23 | S91: =ROUND(HLOOKUP(D91,'5ta'!$C$7:$CF$118,112,0),2) -> 421.71 | V91: =+ROUND(R91-T91-S91-U91,2) -> 2590.52 | W91: =+Y91*R91-S91 -> 0.0022 | X91: =HLOOKUP(D91,'5ta'!$C$7:$CG$139,133,0) -> TRUE | Y91: =HLOOKUP(D91,'5ta'!$C$7:$CF$135,129,0) -> 0.14 | Z91: =VLOOKUP(D91,'[1]0220262'!$E$12:$AD$94,26,0) -> 0 | AB91: =VLOOKUP(D91,'[2]Archivo Excel Haberes Input'!$K$11:$K$80,1,0) -> 46854908
C92: 86 | D92: 47500764 | E92: VILLANUEVA TORRES GERALDINE CYNTHIA | F92: ASISTENTE DE VISTO BUENO | G92: ADMINISTRACION | H92: ADMINISTRACION | I92: =VLOOKUP(D92,'DÍAS EFECTIVOS LABORADOS 2025'!B:F,3,0) -> 45964 | M92: =VLOOKUP(D92,'DÍAS EFECTIVOS LABORADOS 2025'!B:O,14,0) -> 40 | N92: =+ROUND(VLOOKUP(D92,'INGRESOS 2025'!$B$7:$V$159,21,0),2) -> 4812.27 | O92: ACTIVO | P92: =$N$103*M92 -> 1969.2931 | Q92: =$N$104*N92 -> 477.99053 | R92: =+ROUND(P92+Q92,2) -> 2447.28 | S92: =ROUND(HLOOKUP(D92,'5ta'!$C$7:$CF$118,112,0),2) -> 0 | V92: =+ROUND(R92-T92-S92-U92,2) -> 2447.28 | W92: =+Y92*R92-S92 -> 0 | X92: =HLOOKUP(D92,'5ta'!$C$7:$CG$139,133,0) -> TRUE | Y92: =HLOOKUP(D92,'5ta'!$C$7:$CF$135,129,0) -> 0 | Z92: =VLOOKUP(D92,'[1]0220262'!$E$12:$AD$94,26,0) -> 0 | AB92: =VLOOKUP(D92,'[2]Archivo Excel Haberes Input'!$K$11:$K$80,1,0) -> 47500764
C93: 87 | D93: 72902664 | E93: DEXTRE ZUBIETA ELA SIBELY | F93: COORDINADORA DE SELECCIÓN Y DESARROLLO | G93: TALENTO HUMANO | H93: ADMINISTRACION | I93: =VLOOKUP(D93,'DÍAS EFECTIVOS LABORADOS 2025'!B:F,3,0) -> 45962 | M93: =VLOOKUP(D93,'DÍAS EFECTIVOS LABORADOS 2025'!B:O,14,0) -> 40 | N93: =+ROUND(VLOOKUP(D93,'INGRESOS 2025'!$B$7:$V$159,21,0),2) -> 11948.33 | O93: ACTIVO | P93: =$N$103*M93 -> 1969.2931 | Q93: =$N$104*N93 -> 1186.7972 | R93: =+ROUND(P93+Q93,2) -> 3156.09 | S93: =ROUND(HLOOKUP(D93,'5ta'!$C$7:$CF$118,112,0),2) -> 441.85 | V93: =+ROUND(R93-T93-S93-U93,2) -> 2714.24 | W93: =+Y93*R93-S93 -> 0.0026 | X93: =HLOOKUP(D93,'5ta'!$C$7:$CG$139,133,0) -> TRUE | Y93: =HLOOKUP(D93,'5ta'!$C$7:$CF$135,129,0) -> 0.14 | Z93: =VLOOKUP(D93,'[1]0220262'!$E$12:$AD$94,26,0) -> 0 | AB93: =VLOOKUP(D93,'[2]Archivo Excel Haberes Input'!$K$11:$K$80,1,0) -> 72902664
C94: 88 | D94: 40865746 | E94: OLAYA RAMOS GLADYS MARLENY | F94: JEFE DE COBRANZAS Y FACTURACIÓN | G94: ADMINISTRACION | H94: ADMINISTRACION | I94: =VLOOKUP(D94,'DÍAS EFECTIVOS LABORADOS 2025'!B:F,3,0) -> 45992 | M94: =VLOOKUP(D94,'DÍAS EFECTIVOS LABORADOS 2025'!B:O,14,0) -> 20 | N94: =+ROUND(VLOOKUP(D94,'INGRESOS 2025'!$B$7:$V$159,21,0),2) -> 7592.33 | O94: ACTIVO | P94: =$N$103*M94 -> 984.64655 | Q94: =$N$104*N94 -> 754.12681 | R94: =+ROUND(P94+Q94,2) -> 1738.77 | S94: =ROUND(HLOOKUP(D94,'5ta'!$C$7:$CF$118,112,0),2) -> 243.43 | V94: =+ROUND(R94-T94-S94-U94,2) -> 1495.34 | W94: =+Y94*R94-S94 -> -0.0022 | X94: =HLOOKUP(D94,'5ta'!$C$7:$CG$139,133,0) -> TRUE | Y94: =HLOOKUP(D94,'5ta'!$C$7:$CF$135,129,0) -> 0.14 | Z94: =VLOOKUP(D94,'[1]0220262'!$E$12:$AD$94,26,0) -> 0 | AB94: =VLOOKUP(D94,'[2]Archivo Excel Haberes Input'!$K$11:$K$80,1,0) -> 40865746
C95: 89 | D95: 72859721 | E95: ESPINOZA REYES LIZ KERALDIL | F95: AUXILIAR DE PREVENCION - SIG | G95: ADMINISTRACION | H95: ADMINISTRACION | I95: =VLOOKUP(D95,'DÍAS EFECTIVOS LABORADOS 2025'!B:F,3,0) -> 45992 | M95: =VLOOKUP(D95,'DÍAS EFECTIVOS LABORADOS 2025'!B:O,14,0) -> 24 | N95: =+ROUND(VLOOKUP(D95,'INGRESOS 2025'!$B$7:$V$159,21,0),2) -> 1620 | O95: ACTIVO | P95: =$N$103*M95 -> 1181.5759 | Q95: =$N$104*N95 -> 160.91048 | R95: =+ROUND(P95+Q95,2) -> 1342.49 | S95: =ROUND(HLOOKUP(D95,'5ta'!$C$7:$CF$118,112,0),2) -> 0 | V95: =+ROUND(R95-T95-S95-U95,2) -> 1342.49 | W95: =+Y95*R95-S95 -> 0 | X95: =HLOOKUP(D95,'5ta'!$C$7:$CG$139,133,0) -> TRUE | Y95: =HLOOKUP(D95,'5ta'!$C$7:$CF$135,129,0) -> 0 | Z95: =VLOOKUP(D95,'[1]0220262'!$E$12:$AD$94,26,0) -> 0 | AB95: =VLOOKUP(D95,'[2]Archivo Excel Haberes Input'!$K$11:$K$80,1,0) -> 72859721
C96: 90 | D96: 74376927 | E96: AMODEO GORDILLO ANGIE ESTEFANI | F96: ASISTENTE DE VISTO BUENO | G96: ADMINISTRACION | H96: ADMINISTRACION | I96: =VLOOKUP(D96,'DÍAS EFECTIVOS LABORADOS 2025'!B:F,3,0) -> 46002 | M96: =VLOOKUP(D96,'DÍAS EFECTIVOS LABORADOS 2025'!B:O,14,0) -> 14 | N96: =+ROUND(VLOOKUP(D96,'INGRESOS 2025'!$B$7:$V$159,21,0),2) -> 1000 | O96: ACTIVO | P96: =$N$103*M96 -> 689.25258 | Q96: =$N$104*N96 -> 99.327454 | R96: =+ROUND(P96+Q96,2) -> 788.58 | S96: =ROUND(HLOOKUP(D96,'5ta'!$C$7:$CF$118,112,0),2) -> 0 | V96: =+ROUND(R96-T96-S96-U96,2) -> 788.58 | W96: =+Y96*R96-S96 -> 0 | X96: =HLOOKUP(D96,'5ta'!$C$7:$CG$139,133,0) -> TRUE | Y96: =HLOOKUP(D96,'5ta'!$C$7:$CF$135,129,0) -> 0 | Z96: =VLOOKUP(D96,'[1]0220262'!$E$12:$AD$94,26,0) -> 0 | AB96: =VLOOKUP(D96,'[2]Archivo Excel Haberes Input'!$K$11:$K$80,1,0) -> 74376927
M97: =SUM(M7:M96) -> 16834 | N97: =SUM(N7:N96) -> 8343886.5 | P97: =SUM(P7:P96) -> 828777 | Q97: =SUM(Q7:Q96) -> 828777 | R97: =SUM(R7:R96) -> 1657554 | S97: =SUM(S7:S96) -> 248878.13 | T97: =SUM(T7:T96) -> 0 | U97: =SUM(U7:U96) -> 10926.1 | V97: =SUM(V7:V96) -> 1397749.8
I99: Renta anual de la empresa antes de impuestos : | N99: 33151080
I100: Porcentaje a distribuir : | N100: 0.05
I101: Monto a distribuir : | N101: =+N99*N100 -> 1657554 | P101: 1657554
I103: Factor Dias trabajados : | N103: =+N101/2/M97 -> 49.232327
...

Sheet BOLETA
L1: 4
B5: PARTICIPACION EN LAS UTILIDADES POR EL EJERCICIO GRAVABLE 2025
B6: ( D.Leg. Nº 892 y el D.S. Nº 009-98-TR )
B11: CITIKOLD DEL PERU S.A.C., con RUC Nº 20601767423 domiciliado fiscal en AV. JAVIER PRADO OESTE NRO. 757 INT. 1303 URB. SAN FELIPE (EDIFICIO SKYTOWER), DISTRITO DE MAGDALENA DEL MAR, PROVINCIA Y DEPARTAMENTO DE LIMA, debidamente representada por el Sr. SALAZAR DE LA ROCHA JUAN CARLOS GERMAN con DNI 07537953 , en su calidad de empleador y en cumplimiento de lo dispuesto por el D.Leg. Nº 892 y el D.S. Nº 009-98-TR., deja constancia de la determinación, distribución y pago de la participación en las utilidades al :
B17: Sr.(a) | C17: =VLOOKUP($L$1,'UTILIDADES 2025'!C6:V97,3,0) -> RUIZ SALCEDO MARIA DE LOURDES | G17: identificado(a) con DNI / C.E. | J17: =VLOOKUP($L$1,'UTILIDADES 2025'!C6:V97,2,0) -> 08887801 | K17: ,
B18: correspondiente al ejercicio gravable 2025, calculado en base al siguiente detalle:
B21: 1. UTILIDAD POR DISTRIBUIR
B23: - Renta anual de la empresa antes de impuestos : | J23: =+'UTILIDADES 2025'!N99 -> 33151080
B25: - Porcentaje a distribuir : | J25: 0.05
B27: - Monto a distribuir : | J27: =+J23*J25 -> 1657554
B29: 2. CALCULO DE LA PARTICIPACION
B31: 2.1. SEGÚN LOS DÍAS LABORADOS
B33: - Número total de días laborados durante el ejercicio 2025 por todos los trabajadores
B34: de la empresa con derecho a percibir utilidades : | J34: =+'UTILIDADES 2025'!M97 -> 16834
B36: - Número de días laborados durante el ejercicio 2025 por el trabajador : | J36: =VLOOKUP($L$1,'UTILIDADES 2025'!C7:V96,11,0) -> 222
B38: - Participación del trabajador según los días laborados : | J38: =VLOOKUP($L$1,'UTILIDADES 2025'!C7:V96,14,0) -> 10929.577
B40: 2.2. SEGÚN LAS REMUNERACION PERCIBIDAS
B42: - Remuneración computable total pagada durante el ejercicio 2025 a todos los
B43: trabajadores de la empresa : | J43: =+'UTILIDADES 2025'!N97 -> 8343886.5
B45: - Remuneración computable percibida durante el ejercicio 2025 por el trabajador : | J45: =VLOOKUP($L$1,'UTILIDADES 2025'!C7:V96,12,0) -> 181223.64
B47: - Participación del trabajador según las remuneraciones percibidas : | J47: =VLOOKUP($L$1,'UTILIDADES 2025'!C7:V96,15,0) -> 18000.483
B49: 3. MONTO DE LA PARTICIPACIÓN A PERCIBIR POR EL TRABAJADOR
B51: - Participación según los días laborados : | J51: =+J38 -> 10929.577
B53: - Participación según las remuneraciones percibidas : | J53: =+J47 -> 18000.483
B55: - Total de la participación del trabajador en las utilidades : | J55: =ROUND(SUM(J51:J53),2) -> 28930.06
B57: - Descuento de Renta de Quinta Categoria : | J57: =VLOOKUP($L$1,'UTILIDADES 2025'!C7:V96,17,0) -> 4918.11
B59: - Otros descuentos | J59: =VLOOKUP($L$1,'UTILIDADES 2025'!C7:V96,19,0) -> 0
B61: TOTAL DE LA PARTICIPACION NETA DEL TRABAJADOR EN LAS UTILIDADES | J61: =+J55-J57-J59 -> 24011.95 | M61: =VLOOKUP($L$1,'UTILIDADES 2025'!C7:ZV96,20,0) -> 24011.95 | N61: =+J61-M61 -> 0
B64: Lima, 25 de Marzo del 2026
A74: =+C17 -> RUIZ SALCEDO MARIA DE LOURDES | H74: CITIKOLD DEL PERU S.A.C
B75: DNI / C.E. : | C75: =+J17 -> 08887801 | H75: RUC : 20601767423

Sheet 5ta
B1: PROYECTADO DE RENTA QUINTA CATEGORÍA
B3: PERIODO 2026 | CC3: =MONTH(CC6) -> 1
B4: Nro.
B5: OBS | V5: RIA | AB5: RIA | AR5: RIA | AS5: RIA | AT5: RIA
B6: FECHA DE INICIO | C6: 42948 | D6: 43003 | E6: 43374 | F6: 42985 | G6: 43243 | H6: 42985 | I6: 43357 | J6: 42985 | K6: 42985 | L6: 43160 | M6: 43206 | N6: 43252 | O6: 42985 | P6: 43402 | Q6: 43160 | R6: 43070 | S6: 43382 | T6: 42985 | U6: 43003 | V6: 43003 | W6: 43222 | X6: 43206 | Y6: 43497 | Z6: 43530 | AA6: 43525 | AB6: 43678 | AC6: 43724 | AD6: 43973 | AE6: 44111 | AF6: 44432 | AG6: 44453 | AH6: 44483 | AI6: 44483 | AJ6: 44539 | AK6: 44600 | AL6: 44636 | AM6: 44677 | AN6: 44799 | AO6: 44911 | AP6: 44935 | AQ6: 45125 | AR6: 45170 | AS6: 45170 | AT6: 45170 | AU6: 45181 | AV6: 45181 | AW6: 45261 | AX6: 45261 | AY6: 45292 | AZ6: 45313 | BA6: 45481 | BB6: 45481 | BC6: 45541 | BD6: 45574 | BE6: 45600 | BF6: 45627 | BG6: 45628 | BH6: 45658 | BI6: 45689 | BJ6: 45717 | BK6: 45784 | BL6: 45839 | BM6: 45852 | BN6: 45870 | BO6: 45887 | BP6: 45908 | BQ6: 45894 | BR6: 45887 | BS6: 45931 | BT6: 45931 | BU6: 45943 | BV6: 45943 | BW6: 45964 | BX6: 45964 | BY6: 45962 | BZ6: 45992 | CA6: 45992 | CB6: 46002 | CC6: 46024 | CD6: 46027 | CE6: 46023 | CF6: 46041
B7: DNI/C.E | C7: 45813056 | D7: 09335023 | E7: 47472407 | F7: 09410158 | G7: 48588627 | H7: 09542822 | I7: 07262343 | J7: 40537272 | K7: 25710966 | L7: 08693248 | M7: 43426313 | N7: 42168737 | O7: 40508445 | P7: 47806538 | Q7: 47668422 | R7: 10346719 | S7: 10725704 | T7: 09867320 | U7: 08887801 | V7: 07537953 | W7: 42560153 | X7: 47470495 | Y7: 74080395 | Z7: 73958636 | AA7: 71467210 | AB7: 002120932 | AC7: 72152204 | AD7: 71569497 | AE7: 25828090 | AF7: 72016504 | AG7: 72686896 | AH7: 74069271 | AI7: 72001771 | AJ7: 47706283 | AK7: 45858948 | AL7: 76723256 | AM7: 25769631 | AN7: 70857319 | AO7: 47867088 | AP7: 42646402 | AQ7: 76084478 | AR7: 005608621 | AS7: 006123587 | AT7: 005698394 | AU7: 76163280 | AV7: 42035890 | AW7: 002420607 | AX7: 77473806 | AY7: 46833118 | AZ7: 72152557 | BA7: 41047057 | BB7: 73115211 | BC7: 45282900 | BD7: 72857524 | BE7: 71726981 | BF7: 48035238 | BG7: 75743277 | BH7: 76055775 | BI7: 74723670 | BJ7: 008938904 | BK7: 78377581 | BL7: 42151178 | BM7: 73218422 | BN7: 48332716 | BO7: 48109666 | BP7: 74611823 | BQ7: 76644670 | BR7: 45533404 | BS7: 72531605 | BT7: 75267086 | BU7: 46137609 | BV7: 10659025 | BW7: 47500764 | BX7: 46854908 | BY7: 72902664 | BZ7: 72859721 | CA7: 40865746 | CB7: 74376927 | CC7: 48280194 | CD7: 73881843 | CE7: 70447361 | CF7: 70000534
B8: EPS | C8: SI | D8: SI | E8: SI | F8: SI | G8: SI | H8: SI | I8: SI | J8: SI | K8: SI | L8: NO | M8: NO | N8: SI | O8: NO | P8: SI | Q8: SI | R8: NO | S8: SI | T8: SI | U8: SI | V8: SI | W8: SI | X8: NO | Y8: SI | Z8: SI | AA8: SI | AB8: SI | AC8: SI | AD8: SI | AE8: NO | AF8: SI | AG8: SI | AH8: SI | AI8: SI | AJ8: SI | AK8: NO | AL8: SI | AM8: NO | AN8: SI | AO8: NO | AP8: NO | AQ8: NO | AR8: NO | AS8: NO | AT8: NO | AU8: SI | AV8: SI | AW8: NO | AX8: SI | AY8: SI | AZ8: SI | BA8: SI | BB8: SI | BC8: SI | BD8: SI | BE8: SI | BF8: SI | BG8: SI | BH8: NO | BI8: NO | BJ8: NO | BK8: SI | BL8: SI | BM8: SI | BN8: SI | BO8: SI | BP8: SI | BQ8: NO | BR8: NO | BS8: SI | BT8: SI | BU8: NO | BV8: NO | BW8: NO | BX8: NO | BY8: SI | BZ8: NO | CA8: NO | CB8: NO | CC8: NO | CD8: NO | CE8: SI | CF8: NO
B9: REGIMEN | C9: GENERAL | D9: GENERAL | E9: GENERAL | F9: GENERAL | G9: GENERAL | H9: GENERAL | I9: GENERAL | J9: GENERAL | K9: GENERAL | L9: GENERAL | M9: GENERAL | N9: GENERAL | O9: GENERAL | P9: GENERAL | Q9: GENERAL | R9: GENERAL | S9: GENERAL | T9: GENERAL | U9: GENERAL | V9: GENERAL | W9: GENERAL | X9: GENERAL | Y9: GENERAL | Z9: GENERAL | AA9: GENERAL | AB9: GENERAL | AC9: GENERAL | AD9: GENERAL | AE9: GENERAL | AF9: GENERAL | AG9: GENERAL | AH9: GENERAL | AI9: GENERAL | AJ9: GENERAL | AK9: GENERAL | AL9: GENERAL | AM9: GENERAL | AN9: GENERAL | AO9: GENERAL | AP9: GENERAL | AQ9: GENERAL | AR9: GENERAL | AS9: GENERAL | AT9: GENERAL | AU9: GENERAL | AV9: GENERAL | AW9: GENERAL | AX9: GENERAL | AY9: GENERAL | AZ9: GENERAL | BA9: GENERAL | BB9: GENERAL | BC9: GENERAL | BD9: GENERAL | BE9: GENERAL | BF9: GENERAL | BG9: GENERAL | BH9: GENERAL | BI9: GENERAL | BJ9: GENERAL | BK9: GENERAL | BL9: GENERAL | BM9: GENERAL | BN9: GENERAL | BO9: GENERAL | BP9: GENERAL | BQ9: GENERAL | BR9: GENERAL | BS9: GENERAL | BT9: GENERAL | BU9: GENERAL | BV9: GENERAL | BW9: GENERAL | BX9: GENERAL | BY9: GENERAL | BZ9: GENERAL | CA9: GENERAL | CB9: GENERAL | CC9: GENERAL | CD9: GENERAL | CE9: GENERAL | CF9: GENERAL
B10: PERIODO | C10: ALFARO VILLACORTA VICTOR HUGO GARY | D10: AYOS JUNGBLUTH MARIANA | E10: BARRANZUELA SANTOS MELISSA ANTONED | F10: BONATTI CARRASCO JORGE LUIS | G10: CARRERA RAMIREZ KATTYA HELEN | H10: CAVERO RODRIGUEZ JANNYE VERONICA | I10: CIEZA AGUILAR CESAR AUGUSTO | J10: GARRIDO LEON CARLA VERONICA | K10: GIURIA CONSTANTINO HUMBERTO ANDRES | L10: IZARRA CARRASCO IRINA KAREM | M10: LOPEZ MENDOZA GIULIANA JANNET | N10: MARTINEZ MURAYARI DE PEREZ INES ROXANA | O10: MEJIA CAVERO PAOLA CECILIA | P10: RAMIREZ ALBINAGORTA ENRIQUE ALEJANDRO | Q10: ROMAN PINTADO JULLISA IVETTE | R10: ROMERO ORDOÑEZ EDUARDO ARTURO | S10: RONCEROS GONZALES LUISA MARILIN | T10: ROTALDE DEL RIO XIMENA MARIA | U10: RUIZ SALCEDO MARIA DE LOURDES | V10: SALAZAR DE LA ROCHA JUAN CARLOS | W10: VALDEZ CRUZ JOSEPH JOSUE | X10: VILLANTOY GUTIERREZ ANDRES DANIEL | Y10: AVALOS MORANTE KATHERINE ALEXANDRA | Z10: ALEJOS EGUSQUIZA AYXA JELUZETH | AA10: ANTAYHUA GRABIEL ISAAC ISMAEL | AB10: GAME LOAIZA MANUEL XAVIER | AC10: HUAMAN COLLANTES WALTER JUNIOR | AD10: CAMPOS PALOMINO DIANA MARGARITA | AE10: CHERO ORTIZ MARTIN ALEJANDRO | AF10: GUTIERREZ DE LA CRUZ MIGUEL ANGEL | AG10: REBATTA ROJAS GONZALO | AH10: HUAMANI ALTAMIRANO GABRIELA SABRINA | AI10: GUEVARA SALINAS BRYAN GUSTAVO | AJ10: ALIAGA DEL ROSARIO JOSEPH CHRISTHOPHER | AK10: CHAVEZ QUILCATE JULIA DEL PILAR | AL10: REYNA CORTEZ PATRICK ADAMS | AM10: RUIZ TORRES CESAR AUGUSTO | AN10: SAKAY MORISAKI LUIS CARLOS | AO10: ROSALES ATOCHE ROXANA IVETTE | AP10: BALDOCEDA COLQUI YESENIA FLORA | AQ10: SANCHEZ AUCCAPURE JILLS KRAINEEM | AR10: GAME TRIVIÑO MARIA JOSE | AS10: GAME TRIVIÑO MANUEL XAVIER | AT10: GAME TRIVIÑO JUAN ANDRES | AU10: BENITES OTERO YRINNA | AV10: CASTAÑEDA CARRION VIVIEN | AW10: ESCALANTE ZUÑIGA DAVID | AX10: SANDOVAL GONZALES YASIRA JASMIN | AY10: MOSCAYZA NAZARIO STEPHANIE JULIANA | AZ10: ENCALADA PRADA GLORIA STEFANY | BA10: GALLEGOS BLAS LUIS MIGUEL | BB10: TORRES TORRES ANA PAULA | BC10: BELUPU GUTIERREZ CARLO DANIEL | BD10: SANCHEZ VALDEZ MACARENA | BE10: CRUZ QUISPE GEYDI ANTONELA | BF10: YUCRA MANCILLA AHRON | BG10: MALPARTIDA CASTILLO CLAUDIA | BH10: ALAMA BERECHE ROYAL ANTHONY | BI10: QUINTO CAMAHUALI LISETH CHARO | BJ10: CABEZAS RUBIO JORGE ARTURO | BK10: ROMAN RENTERIA ZAIDA YASMIN | BL10: BORDA LEON ROSARIO LIZBETH | BM10: VERA HUAMANCHUMO ANA PAULA | BN10: GUILLEN QUEZADA EMELY HARUMI | BO10: CCAPA SIGUEÑAS SILENE DORA | BP10: CARDENAS CARDENAS LESLIE ELIZABETH | BQ10: MARTINEZ HUAMAN GABRIELA NICOLE | BR10: CASTILLO SANDOVAL MARIA ISABEL | BS10: ROBINSON TORIBIO SARA JANET | BT10: ZETA CORONADO SHAHIRA CELIA | BU10: FERNANDEZ MALASQUEZ KATHERINE | BV10: LEON FUENTES ROCIO MATILDE | BW10: VILLANUEVA TORRES GERALDINE CYNTHIA | BX10: MURGA ESPINOZA YAJAIRA LISBEL | BY10: DEXTRE ZUBIETA ELA SIBELY | BZ10: ESPINOZA REYES LIZ KERALDIL | CA10: OLAYA RAMOS GLADYS MARLENY | CB10: AMODEO GORDILLO ANGIE ESTEFANI | CC10: BAZAN ANAMPA JOE RAUL | CD10: GARCIA SARMIENTO HANZ ENRIQUE | CE10: SAAVEDRA PAREDES MIGUEL ANGEL | CF10: CORREA CORREA STEFANY DEL SOCORRO
B11: SUELDO + ASIG. FAM. + VACACIONES+DME+ LIC CON GOCE
B12: CERTIFICADO DE 5TA
B13: ENERO | C13: 9920 | D13: 11933.5 | E13: 3200 | F13: 4600.87 | G13: 2597.32 | H13: 8591.75 | I13: 3386.03 | J13: 10113 | K13: 7208.7233 | L13: 5434.21 | M13: 4913 | N13: 4377.17 | O13: 5153 | P13: 3575.55 | Q13: 3242.6 | R13: 4113 | S13: 8113 | T13: 15131.83 | U13: 12090.87 | V13: 38870.55 | W13: 3000 | X13: 5022.7767 | Y13: 9999.9967 | Z13: 113 | AA13: 3489.06 | AB13: 150204.29 | AC13: 3669.46 | AD13: 2313 | AE13: 3672.97 | AF13: 2231.87 | AG13: 2977.12 | AH13: 2422.08 | AI13: 2958.75 | AJ13: 2264.87 | AK13: 2588.21 | AL13: 2551.03 | AM13: 2021.31 | AN13: 2195.42 | AO13: 2297.14 | AP13: 1913 | AQ13: 2000 | AR13: 19841.631 | AS13: 23852.223 | AT13: 19841.631 | AU13: 4700 | AV13: 6499.9967 | AW13: 21855.5 | AX13: 2313 | AY13: 2577.9 | AZ13: 2588.21 | BA13: 6113 | BB13: 2244.98 | BC13: 3102.7967 | BD13: 2995 | BE13: 1998.58 | BF13: 3185.6 | BG13: 3500 | BH13: 3194.67 | BI13: 1939.2 | BJ13: 4014 | BK13: 2800 | BL13: 11113 | BM13: 2500 | BN13: 3500 | BO13: 4599.9967 | BP13: 3100 | BQ13: 2177.27 | BR13: 2000 | BS13: 4100 | BT13: 1797 | BU13: 3778.31 | BV13: 1913 | BW13: 2281.65 | BX13: 5000 | BY13: 5113 | BZ13: 1350 | CA13: 6500 | CB13: 1500 | CC13: 4946.3333 | CD13: 2059.3 | CE13: 3700 | CF13: 1480
B14: FEBRERO | C14: 9920 | D14: 12000 | E14: 3200 | F14: 4593.97 | G14: 2569.35 | H14: 8635.6 | I14: 3620.54 | J14: 10135.6 | K14: 7154.4333 | L14: 5113 | M14: 5073.79 | N14: 4276.86 | O14: 5196.58 | P14: 3498 | Q14: 3332.3133 | R14: 4107.67 | S14: 8180.8 | T14: 15116.77 | U14: 12113 | V14: 39103.07 | W14: 2997.25 | X14: 5050.3733 | Y14: 10000 | Z14: 2393.7033 | AA14: 3500 | AB14: 153110.97 | AC14: 3309.74 | AD14: 2343.1333 | AE14: 3653.47 | AF14: 2236.55 | AG14: 2989.42 | AH14: 2425.31 | AI14: 2937.5 | AJ14: 2232.29 | AK14: 2600.9267 | AL14: 2528.5 | AM14: 1913 | AN14: 2185.42 | AO14: 2321.27 | AP14: 1913 | AQ14: 2000 | AR14: 19956.211 | AS14: 24005.073 | AT14: 19956.211 | AU14: 4700 | AV14: 6500.0033 | AW14: 21972.5 | AX14: 2361.9667 | AY14: 2582.8233 | AZ14: 2684.4567 | BA14: 6124.3 | BB14: 2358.3133 | BC14: 3100 | BD14: 2964.87 | BE14: 2006.59 | BF14: 0 | BG14: 3500.0033 | BH14: 3200 | BI14: 1913 | BJ14: 4035.6 | BK14: 2798.02 | BL14: 11113 | BM14: 2493.44 | BN14: 0 | BO14: 4600 | BP14: 3081.79 | BQ14: 2185.7 | BR14: 2000 | BS14: 4100 | BT14: 1797.15 | BU14: 3792.9667 | BV14: 1913 | BW14: 2268.91 | BX14: 5000 | BY14: 5113 | BZ14: 1350 | CA14: 6500 | CB14: 1500 | CC14: 5022.79 | CD14: 2356.3 | CE14: 3700 | CF14: 3700
B15: MARZO | C15: 9920 | D15: 12000 | E15: 3200 | F15: 4713 | G15: 2613 | H15: 8613 | I15: 3113 | J15: 10113 | K15: 7113 | L15: 5113 | M15: 4913 | N15: 4413 | O15: 5153 | P15: 3600 | Q15: 3313 | R15: 4113 | S15: 8113 | T15: 15113 | U15: 12113 | V15: 39076.7 | W15: 3000 | X15: 5000 | Y15: 10000 | Z15: 3613 | AA15: 3500 | AB15: 153110.97 | AC15: 3413 | AD15: 2313 | AE15: 3713 | AF15: 2313 | AG15: 3000 | AH15: 2500 | AI15: 3000 | AJ15: 2313 | AK15: 2613 | AL15: 2600 | AM15: 1913 | AN15: 2200 | AO15: 2313 | AP15: 1913 | AQ15: 2000 | AR15: 19956.211 | AS15: 24005.073 | AT15: 19956.211 | AU15: 4700 | AV15: 6500 | AW15: 21972.5 | AX15: 2313 | AY15: 2613 | AZ15: 2613 | BA15: 6113 | BB15: 2313 | BC15: 3100 | BD15: 3000 | BE15: 2000 | BF15: 0 | BG15: 3500 | BH15: 3200 | BI15: 1913 | BJ15: 4035.6 | BK15: 2800 | BL15: 11113 | BM15: 2500 | BN15: 0 | BO15: 4600 | BP15: 3100 | BQ15: 2200 | BR15: 2000 | BS15: 4100 | BT15: 1800 | BU15: 3813 | BV15: 1913 | BW15: 2313 | BX15: 5000 | BY15: 5113 | BZ15: 1350 | CA15: 6500 | CB15: 1500 | CC15: 5113 | CD15: 2400 | CE15: 3700 | CF15: 3700
B16: ABRIL | C16: 9920 | D16: 12000 | E16: 3200 | F16: 4713 | G16: 2613 | H16: 8613 | I16: 3113 | J16: 10113 | K16: 7113 | L16: 5113 | M16: 4913 | N16: 4413 | O16: 5153 | P16: 3600 | Q16: 3313 | R16: 4113 | S16: 8113 | T16: 15113 | U16: 12113 | V16: 39076.7 | W16: 3000 | X16: 5000 | Y16: 10000 | Z16: 3613 | AA16: 3500 | AB16: 153110.97 | AC16: 3413 | AD16: 2313 | AE16: 3713 | AF16: 2313 | AG16: 3000 | AH16: 2500 | AI16: 3000 | AJ16: 2313 | AK16: 2613 | AL16: 2600 | AM16: 1913 | AN16: 2200 | AO16: 2313 | AP16: 1913 | AQ16: 2000 | AR16: 19956.211 | AS16: 24005.073 | AT16: 19956.211 | AU16: 4700 | AV16: 6500 | AW16: 21972.5 | AX16: 2313 | AY16: 2613 | AZ16: 2613 | BA16: 6113 | BB16: 2313 | BC16: 3100 | BD16: 3000 | BE16: 2000 | BF16: 0 | BG16: 3500 | BH16: 3200 | BI16: 1913 | BJ16: 4035.6 | BK16: 2800 | BL16: 11113 | BM16: 2500 | BN16: 0 | BO16: 4600 | BP16: 3100 | BQ16: 2200 | BR16: 2000 | BS16: 4100 | BT16: 1800 | BU16: 3813 | BV16: 1913 | BW16: 2313 | BX16: 5000 | BY16: 5113 | BZ16: 1350 | CA16: 6500 | CB16: 1500 | CC16: 5113 | CD16: 2400 | CE16: 3700 | CF16: 3700
B17: MAYO | C17: 9920 | D17: 12000 | E17: 3200 | F17: 4713 | G17: 2613 | H17: 8613 | I17: 3113 | J17: 10113 | K17: 7113 | L17: 5113 | M17: 4913 | N17: 4413 | O17: 5153 | P17: 3600 | Q17: 3313 | R17: 4113 | S17: 8113 | T17: 15113 | U17: 12113 | V17: 39076.7 | W17: 3000 | X17: 5000 | Y17: 10000 | Z17: 3613 | AA17: 3500 | AB17: 153110.97 | AC17: 3413 | AD17: 2313 | AE17: 3713 | AF17: 2313 | AG17: 3000 | AH17: 2500 | AI17: 3000 | AJ17: 2313 | AK17: 2613 | AL17: 2600 | AM17: 1913 | AN17: 2200 | AO17: 2313 | AP17: 1913 | AQ17: 2000 | AR17: 19956.211 | AS17: 24005.073 | AT17: 19956.211 | AU17: 4700 | AV17: 6500 | AW17: 21972.5 | AX17: 2313 | AY17: 2613 | AZ17: 2613 | BA17: 6113 | BB17: 2313 | BC17: 3100 | BD17: 3000 | BE17: 2000 | BF17: 0 | BG17: 3500 | BH17: 3200 | BI17: 1913 | BJ17: 4035.6 | BK17: 2800 | BL17: 11113 | BM17: 2500 | BN17: 0 | BO17: 4600 | BP17: 3100 | BQ17: 2200 | BR17: 2000 | BS17: 4100 | BT17: 1800 | BU17: 3813 | BV17: 1913 | BW17: 2313 | BX17: 5000 | BY17: 5113 | BZ17: 1350 | CA17: 6500 | CB17: 1500 | CC17: 5113 | CD17: 2400 | CE17: 3700 | CF17: 3700
B18: JUNIO | C18: 9920 | D18: 12000 | E18: 3200 | F18: 4713 | G18: 2613 | H18: 8613 | I18: 3113 | J18: 10113 | K18: 7113 | L18: 5113 | M18: 4913 | N18: 4413 | O18: 5153 | P18: 3600 | Q18: 3313 | R18: 4113 | S18: 8113 | T18: 15113 | U18: 12113 | V18: 39076.7 | W18: 3000 | X18: 5000 | Y18: 10000 | Z18: 3613 | AA18: 3500 | AB18: 153110.97 | AC18: 3413 | AD18: 2313 | AE18: 3713 | AF18: 2313 | AG18: 3000 | AH18: 2500 | AI18: 3000 | AJ18: 2313 | AK18: 2613 | AL18: 2600 | AM18: 1913 | AN18: 2200 | AO18: 2313 | AP18: 1913 | AQ18: 2000 | AR18: 19956.211 | AS18: 24005.073 | AT18: 19956.211 | AU18: 4700 | AV18: 6500 | AW18: 21972.5 | AX18: 2313 | AY18: 2613 | AZ18: 2613 | BA18: 6113 | BB18: 2313 | BC18: 3100 | BD18: 3000 | BE18: 2000 | BF18: 0 | BG18: 3500 | BH18: 3200 | BI18: 1913 | BJ18: 4035.6 | BK18: 2800 | BL18: 11113 | BM18: 2500 | BN18: 0 | BO18: 4600 | BP18: 3100 | BQ18: 2200 | BR18: 2000 | BS18: 4100 | BT18: 1800 | BU18: 3813 | BV18: 1913 | BW18: 2313 | BX18: 5000 | BY18: 5113 | BZ18: 1350 | CA18: 6500 | CB18: 1500 | CC18: 5113 | CD18: 2400 | CE18: 3700 | CF18: 3700
B19: JULIO | C19: 9920 | D19: 12000 | E19: 3200 | F19: 4713 | G19: 2613 | H19: 8613 | I19: 3113 | J19: 10113 | K19: 7113 | L19: 5113 | M19: 4913 | N19: 4413 | O19: 5153 | P19: 3600 | Q19: 3313 | R19: 4113 | S19: 8113 | T19: 15113 | U19: 12113 | V19: 39076.7 | W19: 3000 | X19: 5000 | Y19: 10000 | Z19: 3613 | AA19: 3500 | AB19: 153110.97 | AC19: 3413 | AD19: 2313 | AE19: 3713 | AF19: 2313 | AG19: 3000 | AH19: 2500 | AI19: 3000 | AJ19: 2313 | AK19: 2613 | AL19: 2600 | AM19: 1913 | AN19: 2200 | AO19: 2313 | AP19: 1913 | AQ19: 2000 | AR19: 19956.211 | AS19: 24005.073 | AT19: 19956.211 | AU19: 4700 | AV19: 6500 | AW19: 21972.5 | AX19: 2313 | AY19: 2613 | AZ19: 2613 | BA19: 6113 | BB19: 2313 | BC19: 3100 | BD19: 3000 | BE19: 2000 | BF19: 0 | BG19: 3500 | BH19: 3200 | BI19: 1913 | BJ19: 4035.6 | BK19: 2800 | BL19: 11113 | BM19: 2500 | BN19: 0 | BO19: 4600 | BP19: 3100 | BQ19: 2200 | BR19: 2000 | BS19: 4100 | BT19: 1800 | BU19: 3813 | BV19: 1913 | BW19: 2313 | BX19: 5000 | BY19: 5113 | BZ19: 1350 | CA19: 6500 | CB19: 1500 | CC19: 5113 | CD19: 2400 | CE19: 3700 | CF19: 3700
B20: AGOSTO | C20: 9920 | D20: 12000 | E20: 3200 | F20: 4713 | G20: 2613 | H20: 8613 | I20: 3113 | J20: 10113 | K20: 7113 | L20: 5113 | M20: 4913 | N20: 4413 | O20: 5153 | P20: 3600 | Q20: 3313 | R20: 4113 | S20: 8113 | T20: 15113 | U20: 12113 | V20: 39076.7 | W20: 3000 | X20: 5000 | Y20: 10000 | Z20: 3613 | AA20: 3500 | AB20: 153110.97 | AC20: 3413 | AD20: 2313 | AE20: 3713 | AF20: 2313 | AG20: 3000 | AH20: 2500 | AI20: 3000 | AJ20: 2313 | AK20: 2613 | AL20: 2600 | AM20: 1913 | AN20: 2200 | AO20: 2313 | AP20: 1913 | AQ20: 2000 | AR20: 19956.211 | AS20: 24005.073 | AT20: 19956.211 | AU20: 4700 | AV20: 6500 | AW20: 21972.5 | AX20: 2313 | AY20: 2613 | AZ20: 2613 | BA20: 6113 | BB20: 2313 | BC20: 3100 | BD20: 3000 | BE20: 2000 | BF20: 0 | BG20: 3500 | BH20: 3200 | BI20: 1913 | BJ20: 4035.6 | BK20: 2800 | BL20: 11113 | BM20: 2500 | BN20: 0 | BO20: 4600 | BP20: 3100 | BQ20: 2200 | BR20: 2000 | BS20: 4100 | BT20: 1800 | BU20: 3813 | BV20: 1913 | BW20: 2313 | BX20: 5000 | BY20: 5113 | BZ20: 1350 | CA20: 6500 | CB20: 1500 | CC20: 5113 | CD20: 2400 | CE20: 3700 | CF20: 3700
B21: SEPTIEMBRE | C21: 9920 | D21: 12000 | E21: 3200 | F21: 4713 | G21: 2613 | H21: 8613 | I21: 3113 | J21: 10113 | K21: 7113 | L21: 5113 | M21: 4913 | N21: 4413 | O21: 5153 | P21: 3600 | Q21: 3313 | R21: 4113 | S21: 8113 | T21: 15113 | U21: 12113 | V21: 39076.7 | W21: 3000 | X21: 5000 | Y21: 10000 | Z21: 3613 | AA21: 3500 | AB21: 153110.97 | AC21: 3413 | AD21: 2313 | AE21: 3713 | AF21: 2313 | AG21: 3000 | AH21: 2500 | AI21: 3000 | AJ21: 2313 | AK21: 2613 | AL21: 2600 | AM21: 1913 | AN21: 2200 | AO21: 2313 | AP21: 1913 | AQ21: 2000 | AR21: 19956.211 | AS21: 24005.073 | AT21: 19956.211 | AU21: 4700 | AV21: 6500 | AW21: 21972.5 | AX21: 2313 | AY21: 2613 | AZ21: 2613 | BA21: 6113 | BB21: 2313 | BC21: 3100 | BD21: 3000 | BE21: 2000 | BF21: 0 | BG21: 3500 | BH21: 3200 | BI21: 1913 | BJ21: 4035.6 | BK21: 2800 | BL21: 11113 | BM21: 2500 | BN21: 0 | BO21: 4600 | BP21: 3100 | BQ21: 2200 | BR21: 2000 | BS21: 4100 | BT21: 1800 | BU21: 3813 | BV21: 1913 | BW21: 2313 | BX21: 5000 | BY21: 5113 | BZ21: 1350 | CA21: 6500 | CB21: 1500 | CC21: 5113 | CD21: 2400 | CE21: 3700 | CF21: 3700
B22: OCTUBRE | C22: 9920 | D22: 12000 | E22: 3200 | F22: 4713 | G22: 2613 | H22: 8613 | I22: 3113 | J22: 10113 | K22: 7113 | L22: 5113 | M22: 4913 | N22: 4413 | O22: 5153 | P22: 3600 | Q22: 3313 | R22: 4113 | S22: 8113 | T22: 15113 | U22: 12113 | V22: 39076.7 | W22: 3000 | X22: 5000 | Y22: 10000 | Z22: 3613 | AA22: 3500 | AB22: 153110.97 | AC22: 3413 | AD22: 2313 | AE22: 3713 | AF22: 2313 | AG22: 3000 | AH22: 2500 | AI22: 3000 | AJ22: 2313 | AK22: 2613 | AL22: 2600 | AM22: 1913 | AN22: 2200 | AO22: 2313 | AP22: 1913 | AQ22: 2000 | AR22: 19956.211 | AS22: 24005.073 | AT22: 19956.211 | AU22: 4700 | AV22: 6500 | AW22: 21972.5 | AX22: 2313 | AY22: 2613 | AZ22: 2613 | BA22: 6113 | BB22: 2313 | BC22: 3100 | BD22: 3000 | BE22: 2000 | BF22: 0 | BG22: 3500 | BH22: 3200 | BI22: 1913 | BJ22: 4035.6 | BK22: 2800 | BL22: 11113 | BM22: 2500 | BN22: 0 | BO22: 4600 | BP22: 3100 | BQ22: 2200 | BR22: 2000 | BS22: 4100 | BT22: 1800 | BU22: 3813 | BV22: 1913 | BW22: 2313 | BX22: 5000 | BY22: 5113 | BZ22: 1350 | CA22: 6500 | CB22: 1500 | CC22: 5113 | CD22: 2400 | CE22: 3700 | CF22: 3700
B23: NOVIEMBRE | C23: 9920 | D23: 12000 | E23: 3200 | F23: 4713 | G23: 2613 | H23: 8613 | I23: 3113 | J23: 10113 | K23: 7113 | L23: 5113 | M23: 4913 | N23: 4413 | O23: 5153 | P23: 3600 | Q23: 3313 | R23: 4113 | S23: 8113 | T23: 15113 | U23: 12113 | V23: 39076.7 | W23: 3000 | X23: 5000 | Y23: 10000 | Z23: 3613 | AA23: 3500 | AB23: 153110.97 | AC23: 3413 | AD23: 2313 | AE23: 3713 | AF23: 2313 | AG23: 3000 | AH23: 2500 | AI23: 3000 | AJ23: 2313 | AK23: 2613 | AL23: 2600 | AM23: 1913 | AN23: 2200 | AO23: 2313 | AP23: 1913 | AQ23: 2000 | AR23: 19956.211 | AS23: 24005.073 | AT23: 19956.211 | AU23: 4700 | AV23: 6500 | AW23: 21972.5 | AX23: 2313 | AY23: 2613 | AZ23: 2613 | BA23: 6113 | BB23: 2313 | BC23: 3100 | BD23: 3000 | BE23: 2000 | BF23: 0 | BG23: 3500 | BH23: 3200 | BI23: 1913 | BJ23: 4035.6 | BK23: 2800 | BL23: 11113 | BM23: 2500 | BN23: 0 | BO23: 4600 | BP23: 3100 | BQ23: 2200 | BR23: 2000 | BS23: 4100 | BT23: 1800 | BU23: 3813 | BV23: 1913 | BW23: 2313 | BX23: 5000 | BY23: 5113 | BZ23: 1350 | CA23: 6500 | CB23: 1500 | CC23: 5113 | CD23: 2400 | CE23: 3700 | CF23: 3700
B24: DICIEMBRE | C24: 9920 | D24: 12000 | E24: 3200 | F24: 4713 | G24: 2613 | H24: 8613 | I24: 3113 | J24: 10113 | K24: 7113 | L24: 5113 | M24: 4913 | N24: 4413 | O24: 5153 | P24: 3600 | Q24: 3313 | R24: 4113 | S24: 8113 | T24: 15113 | U24: 12113 | V24: 39076.7 | W24: 3000 | X24: 5000 | Y24: 10000 | Z24: 3613 | AA24: 3500 | AB24: 153110.97 | AC24: 3413 | AD24: 2313 | AE24: 3713 | AF24: 2313 | AG24: 3000 | AH24: 2500 | AI24: 3000 | AJ24: 2313 | AK24: 2613 | AL24: 2600 | AM24: 1913 | AN24: 2200 | AO24: 2313 | AP24: 1913 | AQ24: 2000 | AR24: 19956.211 | AS24: 24005.073 | AT24: 19956.211 | AU24: 4700 | AV24: 6500 | AW24: 21972.5 | AX24: 2313 | AY24: 2613 | AZ24: 2613 | BA24: 6113 | BB24: 2313 | BC24: 3100 | BD24: 3000 | BE24: 2000 | BF24: 0 | BG24: 3500 | BH24: 3200 | BI24: 1913 | BJ24: 4035.6 | BK24: 2800 | BL24: 11113 | BM24: 2500 | BN24: 0 | BO24: 4600 | BP24: 3100 | BQ24: 2200 | BR24: 2000 | BS24: 4100 | BT24: 1800 | BU24: 3813 | BV24: 1913 | BW24: 2313 | BX24: 5000 | BY24: 5113 | BZ24: 1350 | CA24: 6500 | CB24: 1500 | CC24: 5113 | CD24: 2400 | CE24: 3700 | CF24: 3700
... B28: BONIFICACION 9% | C28: 669.6 | D28: 810 | E28: 216 | F28: 323.6949 | G28: 176.3775 | H28: 581.3775 | I28: 310.63849 | J28: 682.6275 | K28: 480.1275 | L28: 460.17 | M28: 501.31481 | N28: 297.8775 | O28: 471.20985 | P28: 243 | Q28: 243.19508 | R28: 407.40139 | S28: 547.6275 | T28: 1020.1275 | U28: 817.6275 | V28: 0 | W28: 213.46875 | X28: 464.99985 | Y28: 675 | Z28: 243.8775 | AA28: 236.25 | AB28: 0 | AC28: 230.3775 | AD28: 156.1275 | AE28: 334.17 | AF28: 156.1275 | AG28: 202.5 | AH28: 168.75 | AI28: 202.5 | AJ28: 156.1275 | AK28: 250.848 | AL28: 175.5 | AM28: 172.575 | AN28: 148.5 | AO28: 210.98025 | AP28: 174.195 | AQ28: 193.5 | AR28: 0 | AS28: 0 | AT28: 0 | AU28: 317.25 | AV28: 438.75 | AW28: 1977.525 | AX28: 167.38178 | AY28: 176.3775 | AZ28: 185.19638 | BA28: 412.6275 | BB28: 156.1275 | BC28: 212.2875 | BD28: 205.03125 | BE28: 137.81239 | BF28: 0 | BG28: 236.25 | BH28: 288 | BI28: 172.17 | BJ28: 363.204 | BK28: 189 | BL28: 750.43125 | BM28: 168.75 | BN28: 0 | BO28: 310.5 | BP28: 209.25 | BQ28: 198.405 | BR28: 192.00015 | BS28: 276.75 | BT28: 121.5 | BU28: 343.17 | BV28: 172.17 | BW28: 208.17 | BX28: 452.835 | BY28: 346.3425 | BZ28: 130.815 | CA28: 585 | CB28: 135 | CC28: 460.17 | CD28: 216 | CE28: 250.05375 | CF28: 333
B29: COMISIONES Y BONOS REGULARES
B30: ENERO | C30: 0 | D30: 0 | E30: 0 | F30: 0 | G30: 0 | H30: 0 | I30: 0 | J30: 0 | K30: 0 | L30: 0 | M30: 0 | N30: 0 | O30: 0 | P30: 0 | Q30: 0 | R30: 0 | S30: 0 | T30: 0 | U30: 0 | V30: 0 | W30: 0 | X30: 0 | Y30: 0 | Z30: 0 | AA30: 0 | AB30: 0 | AC30: 0 | AD30: 0 | AE30: 0 | AF30: 0 | AG30: 0 | AH30: 0 | AI30: 0 | AJ30: 0 | AK30: 0 | AL30: 0 | AM30: 0 | AN30: 0 | AO30: 0 | AP30: 45 | AQ30: 0 | AR30: 0 | AS30: 0 | AT30: 0 | AU30: 0 | AV30: 0 | AW30: 0 | AX30: 0 | AY30: 0 | AZ30: 0 | BA30: 0 | BB30: 0 | BC30: 36 | BD30: 0 | BE30: 0 | BF30: 0 | BG30: 0 | BH30: 0 | BI30: 0 | BJ30: 0 | BK30: 0 | BL30: 0 | BM30: 0 | BN30: 0 | BO30: 0 | BP30: 0 | BQ30: 0 | BR30: 0 | BS30: 0 | BT30: 0 | BU30: 0 | BV30: 0 | BW30: 0 | BX30: 9 | BY30: 27 | BZ30: 36 | CA30: 0 | CB30: 0 | CC30: 0 | CD30: 0 | CE30: 9 | CF30: 0
B31: FEBRERO | C31: 0 | D31: 0 | E31: 0 | F31: 0 | G31: 0 | H31: 0 | I31: 0 | J31: 0 | K31: 0 | L31: 0 | M31: 0 | N31: 0 | O31: 0 | P31: 0 | Q31: 0 | R31: 0 | S31: 0 | T31: 0 | U31: 0 | V31: 0 | W31: 0 | X31: 0 | Y31: 0 | Z31: 0 | AA31: 0 | AB31: 0 | AC31: 0 | AD31: 0 | AE31: 0 | AF31: 0 | AG31: 0 | AH31: 0 | AI31: 0 | AJ31: 0 | AK31: 0 | AL31: 0 | AM31: 9 | AN31: 0 | AO31: 0 | AP31: 0 | AQ31: 0 | AR31: 0 | AS31: 0 | AT31: 0 | AU31: 0 | AV31: 0 | AW31: 0 | AX31: 0 | AY31: 0 | AZ31: 0 | BA31: 0 | BB31: 0 | BC31: 54 | BD31: 0 | BE31: 0 | BF31: 0 | BG31: 0 | BH31: 0 | BI31: 0 | BJ31: 0 | BK31: 0 | BL31: 9 | BM31: 0 | BN31: 0 | BO31: 0 | BP31: 0 | BQ31: 9 | BR31: 0 | BS31: 0 | BT31: 0 | BU31: 0 | BV31: 0 | BW31: 0 | BX31: 54 | BY31: 9 | BZ31: 171 | CA31: 0 | CB31: 0 | CC31: 0 | CD31: 0 | CE31: 0 | CF31: 0
B32: MARZO
B33: ABRIL
B34: MAYO
B35: JUNIO
B36: JULIO
B37: AGOSTO
B38: SEPTIEMBRE
B39: OCTUBRE
B40: NOVIEMBRE
B41: DICIEMBRE
B42: HORAS EXTRAS
B43: ENERO | C43: 0 | D43: 0 | E43: 0 | F43: 164.96 | G43: 0 | H43: 0 | I43: 1428.7373 | J43: 0 | K43: 0 | L43: 0 | M43: 1314.329 | N43: 0 | O43: 165.33 | P43: 0 | Q43: 579.78 | R43: 0 | S43: 0 | T43: 0 | U43: 0 | V43: 0 | W43: 325 | X43: 333.33 | Y43: 0 | Z43: 0 | AA43: 0 | AB43: 0 | AC43: 0 | AD43: 0 | AE43: 0 | AF43: 0 | AG43: 0 | AH43: 0 | AI43: 0 | AJ43: 0 | AK43: 348.4 | AL43: 0 | AM43: 0 | AN43: 0 | AO43: 62.45 | AP43: 0 | AQ43: 300 | AR43: 0 | AS43: 0 | AT43: 0 | AU43: 0 | AV43: 0 | AW43: 0 | AX43: 333.46 | AY43: 0 | AZ43: 261.3 | BA43: 0 | BB43: 0 | BC43: 0 | BD43: 75 | BE43: 83.33 | BF43: 0 | BG43: 0 | BH43: 0 | BI43: 0 | BJ43: 0 | BK43: 0 | BL43: 0 | BM43: 0 | BN43: 0 | BO43: 0 | BP43: 0 | BQ43: 0 | BR43: 266.67 | BS43: 0 | BT43: 0 | BU43: 0 | BV43: 0 | BW43: 0 | BX43: 0 | BY43: 0 | BZ43: 0 | CA43: 0 | CB43: 0 | CC43: 0 | CD43: 0 | CE43: 0 | CF43: 0
B44: FEBRERO | C44: 0 | D44: 0 | E44: 0 | F44: 0 | G44: 0 | H44: 0 | I44: 1549.366 | J44: 0 | K44: 0 | L44: 0 | M44: 0 | N44: 0 | O44: 0 | P44: 0 | Q44: 0 | R44: 827.36423 | S44: 0 | T44: 0 | U44: 0 | V44: 0 | W44: 0 | X44: 0 | Y44: 0 | Z44: 0 | AA44: 0 | AB44: 0 | AC44: 0 | AD44: 0 | AE44: 0 | AF44: 0 | AG44: 0 | AH44: 0 | AI44: 0 | AJ44: 0 | AK44: 0 | AL44: 0 | AM44: 0 | AN44: 0 | AO44: 0 | AP44: 0 | AQ44: 0 | AR44: 0 | AS44: 0 | AT44: 0 | AU44: 0 | AV44: 0 | AW44: 0 | AX44: 0 | AY44: 0 | AZ44: 0 | BA44: 0 | BB44: 0 | BC44: 0 | BD44: 0 | BE44: 0 | BF44: 0 | BG44: 0 | BH44: 0 | BI44: 0 | BJ44: 0 | BK44: 0 | BL44: 0 | BM44: 0 | BN44: 0 | BO44: 0 | BP44: 0 | BQ44: 0 | BR44: 0 | BS44: 0 | BT44: 0 | BU44: 0 | BV44: 0 | BW44: 0 | BX44: 0 | BY44: 0 | BZ44: 0 | CA44: 0 | CB44: 0 | CC44: 0 | CD44: 0 | CE44: 0 | CF44: 0
B45: MARZO
B46: ABRIL
B47: MAYO
B48: JUNIO
B49: JULIO
B50: AGOSTO
B51: SEPTIEMBRE
B52: OCTUBRE
B53: NOVIEMBRE
B54: DICIEMBRE
B55: MOVILIDAD + REFRIGERIO+ SODEXO +ASIG COMERCIAL
B56: ENERO | C56: 0 | D56: 0 | E56: 0 | F56: 0 | G56: 0 | H56: 0 | I56: 0 | J56: 0 | K56: 0 | L56: 0 | M56: 0 | N56: 0 | O56: 0 | P56: 0 | Q56: 0 | R56: 0 | S56: 0 | T56: 0 | U56: 0 | V56: 0 | W56: 0 | X56: 0 | Y56: 0 | Z56: 0 | AA56: 0 | AB56: 0 | AC56: 0 | AD56: 0 | AE56: 0 | AF56: 0 | AG56: 0 | AH56: 0 | AI56: 0 | AJ56: 0 | AK56: 0 | AL56: 0 | AM56: 0 | AN56: 0 | AO56: 0 | AP56: 0 | AQ56: 0 | AR56: 0 | AS56: 0 | AT56: 0 | AU56: 0 | AV56: 0 | AW56: 0 | AX56: 0 | AY56: 200 | AZ56: 0 | BA56: 0 | BB56: 0 | BC56: 0 | BD56: 0 | BE56: 0 | BF56: 0 | BG56: 0 | BH56: 0 | BI56: 0 | BJ56: 0 | BK56: 0 | BL56: 0 | BM56: 0 | BN56: 0 | BO56: 0 | BP56: 0 | BQ56: 0 | BR56: 0 | BS56: 0 | BT56: 0 | BU56: 0 | BV56: 0 | BW56: 0 | BX56: 0 | BY56: 0 | BZ56: 0 | CA56: 0 | CB56: 0 | CC56: 0 | CD56: 0 | CE56: 0 | CF56: 0
B57: FEBRERO | C57: 0 | D57: 0 | E57: 0 | F57: 0 | G57: 0 | H57: 0 | I57: 0 | J57: 0 | K57: 0 | L57: 0 | M57: 0 | N57: 0 | O57: 0 | P57: 0 | Q57: 0 | R57: 0 | S57: 0 | T57: 0 | U57: 0 | V57: 0 | W57: 0 | X57: 0 | Y57: 0 | Z57: 0 | AA57: 0 | AB57: 0 | AC57: 0 | AD57: 0 | AE57: 0 | AF57: 0 | AG57: 0 | AH57: 0 | AI57: 0 | AJ57: 0 | AK57: 0 | AL57: 0 | AM57: 0 | AN57: 0 | AO57: 0 | AP57: 0 | AQ57: 0 | AR57: 0 | AS57: 0 | AT57: 0 | AU57: 0 | AV57: 0 | AW57: 0 | AX57: 0 | AY57: 140 | AZ57: 0 | BA57: 0 | BB57: 0 | BC57: 0 | BD57: 0 | BE57: 0 | BF57: 0 | BG57: 0 | BH57: 0 | BI57: 0 | BJ57: 0 | BK57: 0 | BL57: 0 | BM57: 0 | BN57: 0 | BO57: 0 | BP57: 0 | BQ57: 0 | BR57: 0 | BS57: 0 | BT57: 0 | BU57: 0 | BV57: 0 | BW57: 0 | BX57: 0 | BY57: 0 | BZ57: 0 | CA57: 0 | CB57: 0 | CC57: 0 | CD57: 0 | CE57: 0 | CF57: 0
B58: MARZO | C58: 0 | D58: 0 | E58: 0 | F58: 0 | G58: 0 | H58: 0 | I58: 0 | J58: 0 | K58: 0 | L58: 0 | M58: 0 | N58: 0 | O58: 0 | P58: 0 | Q58: 0 | R58: 0 | S58: 0 | T58: 0 | U58: 0 | V58: 0 | W58: 0 | X58: 0 | Y58: 0 | Z58: 0 | AA58: 0 | AB58: 0 | AC58: 0 | AD58: 0 | AE58: 0 | AF58: 0 | AG58: 0 | AH58: 0 | AI58: 0 | AJ58: 0 | AK58: 0 | AL58: 0 | AM58: 0 | AN58: 0 | AO58: 0 | AP58: 0 | AQ58: 0 | AR58: 0 | AS58: 0 | AT58: 0 | AU58: 0 | AV58: 0 | AW58: 0 | AX58: 0 | AY58: 200 | AZ58: 0 | BA58: 0 | BB58: 0 | BC58: 0 | BD58: 0 | BE58: 0 | BF58: 0 | BG58: 0 | BH58: 0 | BI58: 0 | BJ58: 0 | BK58: 0 | BL58: 0 | BM58: 0 | BN58: 0 | BO58: 0 | BP58: 0 | BQ58: 0 | BR58: 0 | BS58: 0 | BT58: 0 | BU58: 0 | BV58: 0 | BW58: 0 | BX58: 0 | BY58: 0 | BZ58: 0 | CA58: 0 | CB58: 0 | CC58: 0 | CD58: 0 | CE58: 0 | CF58: 0
B59: ABRIL | C59: 0 | D59: 0 | E59: 0 | F59: 0 | G59: 0 | H59: 0 | I59: 0 | J59: 0 | K59: 0 | L59: 0 | M59: 0 | N59: 0 | O59: 0 | P59: 0 | Q59: 0 | R59: 0 | S59: 0 | T59: 0 | U59: 0 | V59: 0 | W59: 0 | X59: 0 | Y59: 0 | Z59: 0 | AA59: 0 | AB59: 0 | AC59: 0 | AD59: 0 | AE59: 0 | AF59: 0 | AG59: 0 | AH59: 0 | AI59: 0 | AJ59: 0 | AK59: 0 | AL59: 0 | AM59: 0 | AN59: 0 | AO59: 0 | AP59: 0 | AQ59: 0 | AR59: 0 | AS59: 0 | AT59: 0 | AU59: 0 | AV59: 0 | AW59: 0 | AX59: 0 | AY59: 200 | AZ59: 0 | BA59: 0 | BB59: 0 | BC59: 0 | BD59: 0 | BE59: 0 | BF59: 0 | BG59: 0 | BH59: 0 | BI59: 0 | BJ59: 0 | BK59: 0 | BL59: 0 | BM59: 0 | BN59: 0 | BO59: 0 | BP59: 0 | BQ59: 0 | BR59: 0 | BS59: 0 | BT59: 0 | BU59: 0 | BV59: 0 | BW59: 0 | BX59: 0 | BY59: 0 | BZ59: 0 | CA59: 0 | CB59: 0 | CC59: 0 | CD59: 0 | CE59: 0 | CF59: 0
B60: MAYO | C60: 0 | D60: 0 | E60: 0 | F60: 0 | G60: 0 | H60: 0 | I60: 0 | J60: 0 | K60: 0 | L60: 0 | M60: 0 | N60: 0 | O60: 0 | P60: 0 | Q60: 0 | R60: 0 | S60: 0 | T60: 0 | U60: 0 | V60: 0 | W60: 0 | X60: 0 | Y60: 0 | Z60: 0 | AA60: 0 | AB60: 0 | AC60: 0 | AD60: 0 | AE60: 0 | AF60: 0 | AG60: 0 | AH60: 0 | AI60: 0 | AJ60: 0 | AK60: 0 | AL60: 0 | AM60: 0 | AN60: 0 | AO60: 0 | AP60: 0 | AQ60: 0 | AR60: 0 | AS60: 0 | AT60: 0 | AU60: 0 | AV60: 0 | AW60: 0 | AX60: 0 | AY60: 200 | AZ60: 0 | BA60: 0 | BB60: 0 | BC60: 0 | BD60: 0 | BE60: 0 | BF60: 0 | BG60: 0 | BH60: 0 | BI60: 0 | BJ60: 0 | BK60: 0 | BL60: 0 | BM60: 0 | BN60: 0 | BO60: 0 | BP60: 0 | BQ60: 0 | BR60: 0 | BS60: 0 | BT60: 0 | BU60: 0 | BV60: 0 | BW60: 0 | BX60: 0 | BY60: 0 | BZ60: 0 | CA60: 0 | CB60: 0 | CC60: 0 | CD60: 0 | CE60: 0 | CF60: 0
B61: JUNIO | C61: 0 | D61: 0 | E61: 0 | F61: 0 | G61: 0 | H61: 0 | I61: 0 | J61: 0 | K61: 0 | L61: 0 | M61: 0 | N61: 0 | O61: 0 | P61: 0 | Q61: 0 | R61: 0 | S61: 0 | T61: 0 | U61: 0 | V61: 0 | W61: 0 | X61: 0 | Y61: 0 | Z61: 0 | AA61: 0 | AB61: 0 | AC61: 0 | AD61: 0 | AE61: 0 | AF61: 0 | AG61: 0 | AH61: 0 | AI61: 0 | AJ61: 0 | AK61: 0 | AL61: 0 | AM61: 0 | AN61: 0 | AO61: 0 | AP61: 0 | AQ61: 0 | AR61: 0 | AS61: 0 | AT61: 0 | AU61: 0 | AV61: 0 | AW61: 0 | AX61: 0 | AY61: 200 | AZ61: 0 | BA61: 0 | BB61: 0 | BC61: 0 | BD61: 0 | BE61: 0 | BF61: 0 | BG61: 0 | BH61: 0 | BI61: 0 | BJ61: 0 | BK61: 0 | BL61: 0 | BM61: 0 | BN61: 0 | BO61: 0 | BP61: 0 | BQ61: 0 | BR61: 0 | BS61: 0 | BT61: 0 | BU61: 0 | BV61: 0 | BW61: 0 | BX61: 0 | BY61: 0 | BZ61: 0 | CA61: 0 | CB61: 0 | CC61: 0 | CD61: 0 | CE61: 0 | CF61: 0
B62: JULIO | C62: 0 | D62: 0 | E62: 0 | F62: 0 | G62: 0 | H62: 0 | I62: 0 | J62: 0 | K62: 0 | L62: 0 | M62: 0 | N62: 0 | O62: 0 | P62: 0 | Q62: 0 | R62: 0 | S62: 0 | T62: 0 | U62: 0 | V62: 0 | W62: 0 | X62: 0 | Y62: 0 | Z62: 0 | AA62: 0 | AB62: 0 | AC62: 0 | AD62: 0 | AE62: 0 | AF62: 0 | AG62: 0 | AH62: 0 | AI62: 0 | AJ62: 0 | AK62: 0 | AL62: 0 | AM62: 0 | AN62: 0 | AO62: 0 | AP62: 0 | AQ62: 0 | AR62: 0 | AS62: 0 | AT62: 0 | AU62: 0 | AV62: 0 | AW62: 0 | AX62: 0 | AY62: 200 | AZ62: 0 | BA62: 0 | BB62: 0 | BC62: 0 | BD62: 0 | BE62: 0 | BF62: 0 | BG62: 0 | BH62: 0 | BI62: 0 | BJ62: 0 | BK62: 0 | BL62: 0 | BM62: 0 | BN62: 0 | BO62: 0 | BP62: 0 | BQ62: 0 | BR62: 0 | BS62: 0 | BT62: 0 | BU62: 0 | BV62: 0 | BW62: 0 | BX62: 0 | BY62: 0 | BZ62: 0 | CA62: 0 | CB62: 0 | CC62: 0 | CD62: 0 | CE62: 0 | CF62: 0
B63: AGOSTO | C63: 0 | D63: 0 | E63: 0 | F63: 0 | G63: 0 | H63: 0 | I63: 0 | J63: 0 | K63: 0 | L63: 0 | M63: 0 | N63: 0 | O63: 0 | P63: 0 | Q63: 0 | R63: 0 | S63: 0 | T63: 0 | U63: 0 | V63: 0 | W63: 0 | X63: 0 | Y63: 0 | Z63: 0 | AA63: 0 | AB63: 0 | AC63: 0 | AD63: 0 | AE63: 0 | AF63: 0 | AG63: 0 | AH63: 0 | AI63: 0 | AJ63: 0 | AK63: 0 | AL63: 0 | AM63: 0 | AN63: 0 | AO63: 0 | AP63: 0 | AQ63: 0 | AR63: 0 | AS63: 0 | AT63: 0 | AU63: 0 | AV63: 0 | AW63: 0 | AX63: 0 | AY63: 200 | AZ63: 0 | BA63: 0 | BB63: 0 | BC63: 0 | BD63: 0 | BE63: 0 | BF63: 0 | BG63: 0 | BH63: 0 | BI63: 0 | BJ63: 0 | BK63: 0 | BL63: 0 | BM63: 0 | BN63: 0 | BO63: 0 | BP63: 0 | BQ63: 0 | BR63: 0 | BS63: 0 | BT63: 0 | BU63: 0 | BV63: 0 | BW63: 0 | BX63: 0 | BY63: 0 | BZ63: 0 | CA63: 0 | CB63: 0 | CC63: 0 | CD63: 0 | CE63: 0 | CF63: 0
B64: SEPTIEMBRE | C64: 0 | D64: 0 | E64: 0 | F64: 0 | G64: 0 | H64: 0 | I64: 0 | J64: 0 | K64: 0 | L64: 0 | M64: 0 | N64: 0 | O64: 0 | P64: 0 | Q64: 0 | R64: 0 | S64: 0 | T64: 0 | U64: 0 | V64: 0 | W64: 0 | X64: 0 | Y64: 0 | Z64: 0 | AA64: 0 | AB64: 0 | AC64: 0 | AD64: 0 | AE64: 0 | AF64: 0 | AG64: 0 | AH64: 0 | AI64: 0 | AJ64: 0 | AK64: 0 | AL64: 0 | AM64: 0 | AN64: 0 | AO64: 0 | AP64: 0 | AQ64: 0 | AR64: 0 | AS64: 0 | AT64: 0 | AU64: 0 | AV64: 0 | AW64: 0 | AX64: 0 | AY64: 200 | AZ64: 0 | BA64: 0 | BB64: 0 | BC64: 0 | BD64: 0 | BE64: 0 | BF64: 0 | BG64: 0 | BH64: 0 | BI64: 0 | BJ64: 0 | BK64: 0 | BL64: 0 | BM64: 0 | BN64: 0 | BO64: 0 | BP64: 0 | BQ64: 0 | BR64: 0 | BS64: 0 | BT64: 0 | BU64: 0 | BV64: 0 | BW64: 0 | BX64: 0 | BY64: 0 | BZ64: 0 | CA64: 0 | CB64: 0 | CC64: 0 | CD64: 0 | CE64: 0 | CF64: 0
B65: OCTUBRE | C65: 0 | D65: 0 | E65: 0 | F65: 0 | G65: 0 | H65: 0 | I65: 0 | J65: 0 | K65: 0 | L65: 0 | M65: 0 | N65: 0 | O65: 0 | P65: 0 | Q65: 0 | R65: 0 | S65: 0 | T65: 0 | U65: 0 | V65: 0 | W65: 0 | X65: 0 | Y65: 0 | Z65: 0 | AA65: 0 | AB65: 0 | AC65: 0 | AD65: 0 | AE65: 0 | AF65: 0 | AG65: 0 | AH65: 0 | AI65: 0 | AJ65: 0 | AK65: 0 | AL65: 0 | AM65: 0 | AN65: 0 | AO65: 0 | AP65: 0 | AQ65: 0 | AR65: 0 | AS65: 0 | AT65: 0 | AU65: 0 | AV65: 0 | AW65: 0 | AX65: 0 | AY65: 200 | AZ65: 0 | BA65: 0 | BB65: 0 | BC65: 0 | BD65: 0 | BE65: 0 | BF65: 0 | BG65: 0 | BH65: 0 | BI65: 0 | BJ65: 0 | BK65: 0 | BL65: 0 | BM65: 0 | BN65: 0 | BO65: 0 | BP65: 0 | BQ65: 0 | BR65: 0 | BS65: 0 | BT65: 0 | BU65: 0 | BV65: 0 | BW65: 0 | BX65: 0 | BY65: 0 | BZ65: 0 | CA65: 0 | CB65: 0 | CC65: 0 | CD65: 0 | CE65: 0 | CF65: 0
B66: NOVIEMBRE | C66: 0 | D66: 0 | E66: 0 | F66: 0 | G66: 0 | H66: 0 | I66: 0 | J66: 0 | K66: 0 | L66: 0 | M66: 0 | N66: 0 | O66: 0 | P66: 0 | Q66: 0 | R66: 0 | S66: 0 | T66: 0 | U66: 0 | V66: 0 | W66: 0 | X66: 0 | Y66: 0 | Z66: 0 | AA66: 0 | AB66: 0 | AC66: 0 | AD66: 0 | AE66: 0 | AF66: 0 | AG66: 0 | AH66: 0 | AI66: 0 | AJ66: 0 | AK66: 0 | AL66: 0 | AM66: 0 | AN66: 0 | AO66: 0 | AP66: 0 | AQ66: 0 | AR66: 0 | AS66: 0 | AT66: 0 | AU66: 0 | AV66: 0 | AW66: 0 | AX66: 0 | AY66: 200 | AZ66: 0 | BA66: 0 | BB66: 0 | BC66: 0 | BD66: 0 | BE66: 0 | BF66: 0 | BG66: 0 | BH66: 0 | BI66: 0 | BJ66: 0 | BK66: 0 | BL66: 0 | BM66: 0 | BN66: 0 | BO66: 0 | BP66: 0 | BQ66: 0 | BR66: 0 | BS66: 0 | BT66: 0 | BU66: 0 | BV66: 0 | BW66: 0 | BX66: 0 | BY66: 0 | BZ66: 0 | CA66: 0 | CB66: 0 | CC66: 0 | CD66: 0 | CE66: 0 | CF66: 0
B67: DICIEMBRE | C67: 0 | D67: 0 | E67: 0 | F67: 0 | G67: 0 | H67: 0 | I67: 0 | J67: 0 | K67: 0 | L67: 0 | M67: 0 | N67: 0 | O67: 0 | P67: 0 | Q67: 0 | R67: 0 | S67: 0 | T67: 0 | U67: 0 | V67: 0 | W67: 0 | X67: 0 | Y67: 0 | Z67: 0 | AA67: 0 | AB67: 0 | AC67: 0 | AD67: 0 | AE67: 0 | AF67: 0 | AG67: 0 | AH67: 0 | AI67: 0 | AJ67: 0 | AK67: 0 | AL67: 0 | AM67: 0 | AN67: 0 | AO67: 0 | AP67: 0 | AQ67: 0 | AR67: 0 | AS67: 0 | AT67: 0 | AU67: 0 | AV67: 0 | AW67: 0 | AX67: 0 | AY67: 200 | AZ67: 0 | BA67: 0 | BB67: 0 | BC67: 0 | BD67: 0 | BE67: 0 | BF67: 0 | BG67: 0 | BH67: 0 | BI67: 0 | BJ67: 0 | BK67: 0 | BL67: 0 | BM67: 0 | BN67: 0 | BO67: 0 | BP67: 0 | BQ67: 0 | BR67: 0 | BS67: 0 | BT67: 0 | BU67: 0 | BV67: 0 | BW67: 0 | BX67: 0 | BY67: 0 | BZ67: 0 | CA67: 0 | CB67: 0 | CC67: 0 | CD67: 0 | CE67: 0 | CF67: 0
B68: COMPRA DE VACACIONES + BONOS EXTRAORDINARIAS + GRATIF EXTRAOR
B69: ENERO | C69: 0 | D69: 0 | E69: 0 | F69: 0 | G69: 0 | H69: 0 | I69: 0 | J69: 0 | K69: 0 | L69: 0 | M69: 0 | N69: 0 | O69: 0 | P69: 0 | Q69: 0 | R69: 0 | S69: 0 | T69: 0 | U69: 0 | V69: 6915.7187 | W69: 0 | X69: 0 | Y69: 0 | Z69: 0 | AA69: 0 | AB69: 26723.847 | AC69: 0 | AD69: 0 | AE69: 0 | AF69: 0 | AG69: 0 | AH69: 0 | AI69: 0 | AJ69: 0 | AK69: 0 | AL69: 0 | AM69: 0 | AN69: 0 | AO69: 0 | AP69: 0 | AQ69: 0 | AR69: 3604.563 | AS69: 4333.1539 | AT69: 3604.563 | AU69: 0 | AV69: 0 | AW69: 0 | AX69: 0 | AY69: 0 | AZ69: 0 | BA69: 0 | BB69: 0 | BC69: 0 | BD69: 0 | BE69: 0 | BF69: 0 | BG69: 0 | BH69: 0 | BI69: 0 | BJ69: 0 | BK69: 0 | BL69: 0 | BM69: 0 | BN69: 0 | BO69: 0 | BP69: 0 | BQ69: 0 | BR69: 0 | BS69: 0 | BT69: 0 | BU69: 0 | BV69: 0 | BW69: 0 | BX69: 0 | BY69: 0 | BZ69: 0 | CA69: 0 | CB69: 0 | CC69: 0 | CD69: 0 | CE69: 0 | CF69: 0
B70: FEBRERO | C70: 0 | D70: 0 | E70: 0 | F70: 0 | G70: 0 | H70: 0 | I70: 0 | J70: 0 | K70: 0 | L70: 0 | M70: 0 | N70: 0 | O70: 0 | P70: 0 | Q70: 0 | R70: 0 | S70: 0 | T70: 0 | U70: 0 | V70: 6952.3962 | W70: 0 | X70: 0 | Y70: 0 | Z70: 0 | AA70: 0 | AB70: 27240.993 | AC70: 0 | AD70: 0 | AE70: 0 | AF70: 0 | AG70: 0 | AH70: 0 | AI70: 0 | AJ70: 0 | AK70: 0 | AL70: 0 | AM70: 0 | AN70: 0 | AO70: 0 | AP70: 0 | AQ70: 0 | AR70: 3625.3784 | AS70: 4360.9215 | AT70: 3625.3784 | AU70: 0 | AV70: 0 | AW70: 0 | AX70: 0 | AY70: 0 | AZ70: 0 | BA70: 0 | BB70: 0 | BC70: 0 | BD70: 0 | BE70: 0 | BF70: 0 | BG70: 0 | BH70: 0 | BI70: 0 | BJ70: 0 | BK70: 0 | BL70: 0 | BM70: 0 | BN70: 0 | BO70: 0 | BP70: 0 | BQ70: 0 | BR70: 0 | BS70: 0 | BT70: 0 | BU70: 0 | BV70: 0 | BW70: 0 | BX70: 0 | BY70: 0 | BZ70: 0 | CA70: 0 | CB70: 0 | CC70: 0 | CD70: 0 | CE70: 0 | CF70: 0
B71: MARZO | V71: 6952.3962 | AB71: 27240.993 | AR71: 3625.3784 | AS71: 4360.9215 | AT71: 3625.3784
B72: ABRIL | V72: 6952.3962 | AB72: 27240.993 | AR72: 3625.3784 | AS72: 4360.9215 | AT72: 3625.3784
B73: MAYO | V73: 6952.3962 | AB73: 27240.993 | AR73: 3625.3784 | AS73: 4360.9215 | AT73: 3625.3784
B74: JUNIO | V74: 6952.3962 | AB74: 27240.993 | AR74: 3625.3784 | AS74: 4360.9215 | AT74: 3625.3784
B75: JULIO | V75: 6952.3962 | AB75: 27240.993 | AR75: 3625.3784 | AS75: 4360.9215 | AT75: 3625.3784
B76: AGOSTO | V76: 6952.3962 | AB76: 27240.993 | AR76: 3625.3784 | AS76: 4360.9215 | AT76: 3625.3784
B77: SEPTIEMBRE | V77: 6952.3962 | AB77: 27240.993 | AR77: 3625.3784 | AS77: 4360.9215 | AT77: 3625.3784
B78: OCTUBRE | V78: 6952.3962 | AB78: 27240.993 | AR78: 3625.3784 | AS78: 4360.9215 | AT78: 3625.3784
B79: NOVIEMBRE | V79: 6952.3962 | AB79: 27240.993 | AR79: 3625.3784 | AS79: 4360.9215 | AT79: 3625.3784
B80: DICIEMBRE | V80: 6952.3962 | AB80: 27240.993 | AR80: 3625.3784 | AS80: 4360.9215 | AT80: 3625.3784
B81: OTROS
B82: ENERO | C82: 0 | D82: 0 | E82: 0 | F82: 0 | G82: 0 | H82: 0 | I82: 0 | J82: 0 | K82: 1960.4651 | L82: 0 | M82: 0 | N82: 200 | O82: 0 | P82: 0 | Q82: 0 | R82: 0 | S82: 10098 | T82: 0 | U82: 0 | V82: 0 | W82: 0 | X82: 0 | Y82: 0 | Z82: 0 | AA82: 0 | AB82: 0 | AC82: 0 | AD82: 0 | AE82: 0 | AF82: 0 | AG82: 0 | AH82: 0 | AI82: 0 | AJ82: 0 | AK82: 0 | AL82: 0 | AM82: 0 | AN82: 0 | AO82: 0 | AP82: 0 | AQ82: 0 | AR82: 0 | AS82: 0 | AT82: 0 | AU82: 0 | AV82: 0 | AW82: 0 | AX82: 0 | AY82: 0 | AZ82: 0 | BA82: 0 | BB82: 0 | BC82: 0 | BD82: 0 | BE82: 0 | BF82: 0 | BG82: 0 | BH82: 0 | BI82: 0 | BJ82: 0 | BK82: 0 | BL82: 0 | BM82: 0 | BN82: 0 | BO82: 0 | BP82: 0 | BQ82: 0 | BR82: 0 | BS82: 0 | BT82: 0 | BU82: 0 | BV82: 113 | BW82: 0 | BX82: 0 | BY82: 0 | BZ82: 0 | CA82: 0 | CB82: 0 | CC82: 0 | CD82: 0 | CE82: 0 | CF82: 0
B83: FEBRERO | C83: 0 | D83: 0 | E83: 0 | F83: 0 | G83: 0 | H83: 0 | I83: 0 | J83: 0 | K83: 0 | L83: 0 | M83: 0 | N83: 6932 | O83: 0 | P83: 0 | Q83: 0 | R83: 0 | S83: 0 | T83: 0 | U83: 0 | V83: 0 | W83: 0 | X83: 0 | Y83: 0 | Z83: 0 | AA83: 0 | AB83: 0 | AC83: 0 | AD83: 0 | AE83: 0 | AF83: 0 | AG83: 0 | AH83: 0 | AI83: 0 | AJ83: 0 | AK83: 0 | AL83: 0 | AM83: 0 | AN83: 0 | AO83: 0 | AP83: 0 | AQ83: 0 | AR83: 0 | AS83: 0 | AT83: 0 | AU83: 0 | AV83: 0 | AW83: 0 | AX83: 0 | AY83: 0 | AZ83: 0 | BA83: 0 | BB83: 0 | BC83: 0 | BD83: 0 | BE83: 0 | BF83: 0 | BG83: 0 | BH83: 0 | BI83: 0 | BJ83: 0 | BK83: 0 | BL83: 0 | BM83: 0 | BN83: 0 | BO83: 0 | BP83: 0 | BQ83: 0 | BR83: 0 | BS83: 0 | BT83: 0 | BU83: 0 | BV83: 0 | BW83: 0 | BX83: 0 | BY83: 0 | BZ83: 0 | CA83: 0 | CB83: 0 | CC83: 0 | CD83: 0 | CE83: 0 | CF83: 0
B84: MARZO
B85: ABRIL
B86: MAYO
B87: JUNIO
B88: JULIO
B89: AGOSTO
B90: SEPTIEMBRE
B91: OCTUBRE
B92: NOVIEMBRE
B93: DICIEMBRE
B94: LIQUIDACIÓN
B95: PARTICIPACION DE UTILIDADES 2025 | C95: =VLOOKUP(C7,'UTILIDADES 2025'!$D$5:$R$98,15,0) -> 26466.25 | D95: =VLOOKUP(D7,'UTILIDADES 2025'!$D$5:$R$98,15,0) -> 29004.79 | E95: =VLOOKUP(E7,'UTILIDADES 2025'!$D$5:$R$98,15,0) -> 15701.93 | F95: =VLOOKUP(F7,'UTILIDADES 2025'!$D$5:$R$98,15,0) -> 18326.35 | G95: =VLOOKUP(G7,'UTILIDADES 2025'!$D$5:$R$98,15,0) -> 15978.88 | H95: =VLOOKUP(H7,'UTILIDADES 2025'!$D$5:$R$98,15,0) -> 24767.64 | I95: =VLOOKUP(I7,'UTILIDADES 2025'!$D$5:$R$98,15,0) -> 17103.93 | J95: =VLOOKUP(J7,'UTILIDADES 2025'!$D$5:$R$98,15,0) -> 26733.64 | ... CB95: =VLOOKUP(CB7,'UTILIDADES 2025'!$D$5:$R$98,15,0) -> 788.58
B96: RENTA POR OTRAS EMPRESAS | AB96: 468840.09
B99: INGRESOS BRUTOS ANUALES | C99: =+SUM(C12:C97) -> 166685.45 | D99: =+SUM(D12:D97) -> 198558.29 | E99: =+SUM(E12:E97) -> 60933.93 | F99: =+SUM(F12:F97) -> 85054.5 | G99: =+SUM(G12:G97) -> 52854.305 | H99: =+SUM(H12:H97) -> 146513.74 | I99: =+SUM(I12:I97) -> 68043.984 | J99: =+SUM(J12:J97) -> 169703.49 | ... CF99: =+SUM(CF12:CF97) -> 49573.833
B100: DEDUCCIÓN DE 7 UIT'S | C100: =7*5500 -> 38500 | D100: =7*5500 -> 38500 | E100: =7*5500 -> 38500 | F100: =7*5500 -> 38500 | G100: =7*5500 -> 38500 | H100: =7*5500 -> 38500 | I100: =7*5500 -> 38500 | J100: =7*5500 -> 38500 | ... CF100: =7*5500 -> 38500
B101: BASE IMPONIBLE | C101: =IF(C99>C100,C99-C100,0) -> 128185.45 | D101: =IF(D99>D100,D99-D100,0) -> 160058.29 | E101: =IF(E99>E100,E99-E100,0) -> 22433.93 | F101: =IF(F99>F100,F99-F100,0) -> 46554.5 | G101: =IF(G99>G100,G99-G100,0) -> 14354.305 | H101: =IF(H99>H100,H99-H100,0) -> 108013.74 | I101: =IF(I99>I100,I99-I100,0) -> 29543.984 | J101: =IF(J99>J100,J99-J100,0) -> 131203.49 | ... CF101: =IF(CF99>CF100,CF99-CF100,0) -> 11073.833
B103: DE 0 A 5 UIT'S (8%) | C103: =IF(C101>27500,(27500*8%),C101*8%) -> 2200 | D103: =IF(D101>27500,(27500*8%),D101*8%) -> 2200 | E103: =IF(E101>27500,(27500*8%),E101*8%) -> 1794.7144 | F103: =IF(F101>27500,(27500*8%),F101*8%) -> 2200 | G103: =IF(G101>27500,(27500*8%),G101*8%) -> 1148.3444 | H103: =IF(H101>27500,(27500*8%),H101*8%) -> 2200 | I103: =IF(I101>27500,(27500*8%),I101*8%) -> 2200 | J103: =IF(J101>27500,(27500*8%),J101*8%) -> 2200 | ... CF103: =IF(CF101>27500,(27500*8%),CF101*8%) -> 885.90667
B104: BLANCO 1 | C104: =IF(C101>27500,C101-27500,0) -> 100685.45 | D104: =IF(D101>27500,D101-27500,0) -> 132558.29 | E104: =IF(E101>27500,E101-27500,0) -> 0 | F104: =IF(F101>27500,F101-27500,0) -> 19054.5 | G104: =IF(G101>27500,G101-27500,0) -> 0 | H104: =IF(H101>27500,H101-27500,0) -> 80513.745 | I104: =IF(I101>27500,I101-27500,0) -> 2043.9836 | J104: =IF(J101>27500,J101-27500,0) -> 103703.49 | ... CF104: =IF(CF101>27500,CF101-27500,0) -> 0
B105: DE 5 A 20 UIT'S (14%) | C105: =IF(C104>82500,(82500*14%),C104*14%) -> 11550 | D105: =IF(D104>82500,(82500*14%),D104*14%) -> 11550 | E105: =IF(E104>82500,(82500*14%),E104*14%) -> 0 | F105: =IF(F104>82500,(82500*14%),F104*14%) -> 2667.63 | G105: =IF(G104>82500,(82500*14%),G104*14%) -> 0 | H105: =IF(H104>82500,(82500*14%),H104*14%) -> 11271.924 | I105: =IF(I104>82500,(82500*14%),I104*14%) -> 286.15771 | J105: =IF(J104>82500,(82500*14%),J104*14%) -> 11550 | ... CF105: =IF(CF104>82500,(82500*14%),CF104*14%) -> 0
B106: BLANCO 2 | C106: =IF(C104>82500,C104-82500,0) -> 18185.45 | D106: =IF(D104>82500,D104-82500,0) -> 50058.29 | E106: =IF(E104>82500,E104-82500,0) -> 0 | F106: =IF(F104>82500,F104-82500,0) -> 0 | G106: =IF(G104>82500,G104-82500,0) -> 0 | H106: =IF(H104>82500,H104-82500,0) -> 0 | I106: =IF(I104>82500,I104-82500,0) -> 0 | J106: =IF(J104>82500,J104-82500,0) -> 21203.495 | ... CF106: =IF(CF104>82500,CF104-82500,0) -> 0
B107: DE 20 A 35 UIT'S (17%) | C107: =IF(C106>82500,(82500*17%),C106*17%) -> 3091.5265 | D107: =IF(D106>82500,(82500*17%),D106*17%) -> 8509.9093 | E107: =IF(E106>82500,(82500*17%),E106*17%) -> 0 | F107: =IF(F106>82500,(82500*17%),F106*17%) -> 0 | G107: =IF(G106>82500,(82500*17%),G106*17%) -> 0 | H107: =IF(H106>82500,(82500*17%),H106*17%) -> 0 | I107: =IF(I106>82500,(82500*17%),I106*17%) -> 0 | J107: =IF(J106>82500,(82500*17%),J106*17%) -> 3604.5941 | ... CF107: =IF(CF106>82500,(82500*17%),CF106*17%) -> 0
...

Sheet DÍAS EFECTIVOS LABORADOS 2025
A2: DÍAS EFECTIVOS TRABAJADORES 2025
D3: ok | F3: ok | G3: ok | H3: ok | I3: ok | J3: ok | O3: ok
A5: Datos del Trabajador
A6: Documento de Identidad | C6: NOMBRE | D6: FECHA DE INICIO | E6: FECHA UTILIDADES 2025 | F6: FECHA DE CESE | G6: DIAS EFECTIVOS | H6: FECHA UTILIDADES 2025 | I6: FECHA DE CESE | J6: DIAS EFECTIVOS | K6: DIAS DE LICENCIA MATERNIDAD | L6: DIAS FULL 2025 | M6: - DEDUCCIONES DIAS | O6: DÍAS 2025 | P6: JORNADA | R6: FECHA FERIADOS
A7: Tipo | B7: Número
B8: 07262343 | C8: CIEZA AGUILAR CESAR AUGUSTO | D8: 43357 | E8: =IF(YEAR(D8)=2025,D8,"01/01/2025") -> 01/01/2025 | F8: =IF(VLOOKUP(B8,'INGRESOS 2025'!$B$7:$E$98,4,0)=0,"31/12/2025",VLOOKUP(B8,'INGRESOS 2025'!$B$7:$E$98,4,0)) -> 31/12/2025 | G8: =NETWORKDAYS.INTL(E8,F8,1,$R$8:$R$23) -> 249 | L8: =+G8+J8+K8 -> 249 | M8: =SUMIF('DIAS NO LABORADOS'!$C$6:$C$286,B8,'DIAS NO LABORADOS'!$N$6:$N$286) -> 18 | O8: =L8-M8+N8 -> 231 | P8: L-V | R8: 45658
B9: 07537953 | C9: SALAZAR DE LA ROCHA JUAN CARLOS GERMAN | D9: 43003 | E9: =IF(YEAR(D9)=2025,D9,"01/01/2025") -> 01/01/2025 | F9: =IF(VLOOKUP(B9,'INGRESOS 2025'!$B$7:$E$98,4,0)=0,"31/12/2025",VLOOKUP(B9,'INGRESOS 2025'!$B$7:$E$98,4,0)) -> 31/12/2025 | G9: =NETWORKDAYS.INTL(E9,F9,1,$R$8:$R$23) -> 249 | L9: =+G9+J9+K9 -> 249 | M9: =SUMIF('DIAS NO LABORADOS'!$C$6:$C$286,B9,'DIAS NO LABORADOS'!$N$6:$N$286) -> 27 | O9: =L9-M9+N9 -> 222 | P9: L-V | R9: 45764
B10: 08693248 | C10: IZARRA CARRASCO IRINA KAREM | D10: 43160 | E10: =IF(YEAR(D10)=2025,D10,"01/01/2025") -> 01/01/2025 | F10: =IF(VLOOKUP(B10,'INGRESOS 2025'!$B$7:$E$98,4,0)=0,"31/12/2025",VLOOKUP(B10,'INGRESOS 2025'!$B$7:$E$98,4,0)) -> 31/12/2025 | G10: =NETWORKDAYS.INTL(E10,F10,1,$R$8:$R$23) -> 249 | L10: =+G10+J10+K10 -> 249 | M10: =SUMIF('DIAS NO LABORADOS'!$C$6:$C$286,B10,'DIAS NO LABORADOS'!$N$6:$N$286) -> 14 | O10: =L10-M10+N10 -> 235 | P10: L-V | R10: 45765
B11: 08887801 | C11: RUIZ SALCEDO MARIA DE LOURDES | D11: 43003 | E11: =IF(YEAR(D11)=2025,D11,"01/01/2025") -> 01/01/2025 | F11: =IF(VLOOKUP(B11,'INGRESOS 2025'!$B$7:$E$98,4,0)=0,"31/12/2025",VLOOKUP(B11,'INGRESOS 2025'!$B$7:$E$98,4,0)) -> 31/12/2025 | G11: =NETWORKDAYS.INTL(E11,F11,1,$R$8:$R$23) -> 249 | L11: =+G11+J11+K11 -> 249 | M11: =SUMIF('DIAS NO LABORADOS'!$C$6:$C$286,B11,'DIAS NO LABORADOS'!$N$6:$N$286) -> 27 | O11: =L11-M11+N11 -> 222 | P11: L-V | R11: 45778
B12: 09335023 | C12: AYOS JUNGBLUTH MARIANA | D12: 43003 | E12: =IF(YEAR(D12)=2025,D12,"01/01/2025") -> 01/01/2025 | F12: =IF(VLOOKUP(B12,'INGRESOS 2025'!$B$7:$E$98,4,0)=0,"31/12/2025",VLOOKUP(B12,'INGRESOS 2025'!$B$7:$E$98,4,0)) -> 31/12/2025 | G12: =NETWORKDAYS.INTL(E12,F12,1,$R$8:$R$23) -> 249 | L12: =+G12+J12+K12 -> 249 | M12: =SUMIF('DIAS NO LABORADOS'!$C$6:$C$286,B12,'DIAS NO LABORADOS'!$N$6:$N$286) -> 22 | O12: =L12-M12+N12 -> 227 | P12: L-V | R12: 45815
B13: 09410158 | C13: BONATTI CARRASCO JORGE LUIS | D13: 42985 | E13: =IF(YEAR(D13)=2025,D13,"01/01/2025") -> 01/01/2025 | F13: =IF(VLOOKUP(B13,'INGRESOS 2025'!$B$7:$E$98,4,0)=0,"31/12/2025",VLOOKUP(B13,'INGRESOS 2025'!$B$7:$E$98,4,0)) -> 31/12/2025 | G13: =NETWORKDAYS.INTL(E13,F13,1,$R$8:$R$23) -> 249 | L13: =+G13+J13+K13 -> 249 | M13: =SUMIF('DIAS NO LABORADOS'!$C$6:$C$286,B13,'DIAS NO LABORADOS'!$N$6:$N$286) -> 22 | O13: =L13-M13+N13 -> 227 | P13: L-V | R13: 45837
B14: 09542822 | C14: CAVERO RODRIGUEZ JANNYE VERONICA | D14: 42985 | E14: =IF(YEAR(D14)=2025,D14,"01/01/2025") -> 01/01/2025 | F14: =IF(VLOOKUP(B14,'INGRESOS 2025'!$B$7:$E$98,4,0)=0,"31/12/2025",VLOOKUP(B14,'INGRESOS 2025'!$B$7:$E$98,4,0)) -> 31/12/2025 | G14: =NETWORKDAYS.INTL(E14,F14,1,$R$8:$R$23) -> 249 | L14: =+G14+J14+K14 -> 249 | M14: =SUMIF('DIAS NO LABORADOS'!$C$6:$C$286,B14,'DIAS NO LABORADOS'!$N$6:$N$286) -> 14 | O14: =L14-M14+N14 -> 235 | P14: L-V | R14: 45861
B15: 09867320 | C15: ROTALDE DEL RIO XIMENA MARIA | D15: 42985 | E15: =IF(YEAR(D15)=2025,D15,"01/01/2025") -> 01/01/2025 | F15: =IF(VLOOKUP(B15,'INGRESOS 2025'!$B$7:$E$98,4,0)=0,"31/12/2025",VLOOKUP(B15,'INGRESOS 2025'!$B$7:$E$98,4,0)) -> 31/12/2025 | G15: =NETWORKDAYS.INTL(E15,F15,1,$R$8:$R$23) -> 249 | L15: =+G15+J15+K15 -> 249 | M15: =SUMIF('DIAS NO LABORADOS'!$C$6:$C$286,B15,'DIAS NO LABORADOS'!$N$6:$N$286) -> 20 | O15: =L15-M15+N15 -> 229 | P15: L-V | R15: 45866
B16: 10080476 | C16: CASTILLEJOS HINOSTROZA NAYLLI MARLENE | D16: 44911 | E16: =IF(YEAR(D16)=2025,D16,"01/01/2025") -> 01/01/2025 | F16: =IF(VLOOKUP(B16,'INGRESOS 2025'!$B$7:$E$98,4,0)=0,"31/12/2025",VLOOKUP(B16,'INGRESOS 2025'!$B$7:$E$98,4,0)) -> 45961 | G16: =NETWORKDAYS.INTL(E16,F16,1,$R$8:$R$23) -> 209 | L16: =+G16+J16+K16 -> 209 | M16: =SUMIF('DIAS NO LABORADOS'!$C$6:$C$286,B16,'DIAS NO LABORADOS'!$N$6:$N$286) -> 30 | O16: =L16-M16+N16 -> 179 | P16: L-V | R16: 45867
B17: 10346719 | C17: ROMERO ORDOÑEZ EDUARDO ARTURO | D17: 43070 | E17: =IF(YEAR(D17)=2025,D17,"01/01/2025") -> 01/01/2025 | F17: =IF(VLOOKUP(B17,'INGRESOS 2025'!$B$7:$E$98,4,0)=0,"31/12/2025",VLOOKUP(B17,'INGRESOS 2025'!$B$7:$E$98,4,0)) -> 31/12/2025 | G17: =NETWORKDAYS.INTL(E17,F17,1,$R$8:$R$23) -> 249 | L17: =+G17+J17+K17 -> 249 | M17: =SUMIF('DIAS NO LABORADOS'!$C$6:$C$286,B17,'DIAS NO LABORADOS'!$N$6:$N$286) -> 9 | O17: =L17-M17+N17 -> 240 | P17: L-V | R17: 45875
B18: 10725704 | C18: RONCEROS GONZALES LUISA MARILIN | D18: 43382 | E18: =IF(YEAR(D18)=2025,D18,"01/01/2025") -> 01/01/2025 | F18: =IF(VLOOKUP(B18,'INGRESOS 2025'!$B$7:$E$98,4,0)=0,"31/12/2025",VLOOKUP(B18,'INGRESOS 2025'!$B$7:$E$98,4,0)) -> 31/12/2025 | G18: =NETWORKDAYS.INTL(E18,F18,1,$R$8:$R$23) -> 249 | L18: =+G18+J18+K18 -> 249 | M18: =SUMIF('DIAS NO LABORADOS'!$C$6:$C$286,B18,'DIAS NO LABORADOS'!$N$6:$N$286) -> 10 | O18: =L18-M18+N18 -> 239 | P18: L-V | R18: 45899
B19: 25710966 | C19: GIURIA CONSTANTINO HUMBERTO ANDRES | D19: 42985 | E19: =IF(YEAR(D19)=2025,D19,"01/01/2025") -> 01/01/2025 | F19: =IF(VLOOKUP(B19,'INGRESOS 2025'!$B$7:$E$98,4,0)=0,"31/12/2025",VLOOKUP(B19,'INGRESOS 2025'!$B$7:$E$98,4,0)) -> 31/12/2025 | G19: =NETWORKDAYS.INTL(E19,F19,1,$R$8:$R$23) -> 249 | L19: =+G19+J19+K19 -> 249 | M19: =SUMIF('DIAS NO LABORADOS'!$C$6:$C$286,B19,'DIAS NO LABORADOS'!$N$6:$N$286) -> 11 | O19: =L19-M19+N19 -> 238 | P19: L-V | R19: 45938
... B23: 40537272 | C23: GARRIDO LEON CARLA VERONICA | D23: 42985 | E23: =IF(YEAR(D23)=2025,D23,"01/01/2025") -> 01/01/2025 | F23: =IF(VLOOKUP(B23,'INGRESOS 2025'!$B$7:$E$98,4,0)=0,"31/12/2025",VLOOKUP(B23,'INGRESOS 2025'!$B$7:$E$98,4,0)) -> 31/12/2025 | G23: =NETWORKDAYS.INTL(E23,F23,1,$R$8:$R$23) -> 249 | L23: =+G23+J23+K23 -> 249 | M23: =SUMIF('DIAS NO LABORADOS'!$C$6:$C$286,B23,'DIAS NO LABORADOS'!$N$6:$N$286) -> 17 | O23: =L23-M23+N23 -> 232 | P23: L-V | R23: 46016
B24: 41047057 | C24: GALLEGOS BLAS LUIS MIGUEL | D24: 45481 | E24: =IF(YEAR(D24)=2025,D24,"01/01/2025") -> 01/01/2025 | F24: =IF(VLOOKUP(B24,'INGRESOS 2025'!$B$7:$E$98,4,0)=0,"31/12/2025",VLOOKUP(B24,'INGRESOS 2025'!$B$7:$E$98,4,0)) -> 31/12/2025 | G24: =NETWORKDAYS.INTL(E24,F24,1,$R$8:$R$23) -> 249 | L24: =+G24+J24+K24 -> 249 | M24: =SUMIF('DIAS NO LABORADOS'!$C$6:$C$286,B24,'DIAS NO LABORADOS'!$N$6:$N$286) -> 12 | O24: =L24-M24+N24 -> 237 | P24: L-V
B25: 41832234 | C25: HUERTA PALOMINO NELLY VANESSA | D25: 44986 | E25: =IF(YEAR(D25)=2025,D25,"01/01/2025") -> 01/01/2025 | F25: =IF(VLOOKUP(B25,'INGRESOS 2025'!$B$7:$E$98,4,0)=0,"31/12/2025",VLOOKUP(B25,'INGRESOS 2025'!$B$7:$E$98,4,0)) -> 45748 | G25: =NETWORKDAYS.INTL(E25,F25,1,$R$8:$R$23) -> 64 | L25: =+G25+J25+K25 -> 64 | M25: =SUMIF('DIAS NO LABORADOS'!$C$6:$C$286,B25,'DIAS NO LABORADOS'!$N$6:$N$286) -> 15 | O25: =L25-M25+N25 -> 49 | P25: L-V
B26: 42035890 | C26: CASTAÑEDA CARRION VIVIEN KARLA | D26: 45181 | E26: =IF(YEAR(D26)=2025,D26,"01/01/2025") -> 01/01/2025 | F26: =IF(VLOOKUP(B26,'INGRESOS 2025'!$B$7:$E$98,4,0)=0,"31/12/2025",VLOOKUP(B26,'INGRESOS 2025'!$B$7:$E$98,4,0)) -> 31/12/2025 | G26: =NETWORKDAYS.INTL(E26,F26,1,$R$8:$R$23) -> 249 | L26: =+G26+J26+K26 -> 249 | M26: =SUMIF('DIAS NO LABORADOS'!$C$6:$C$286,B26,'DIAS NO LABORADOS'!$N$6:$N$286) -> 22 | O26: =L26-M26+N26 -> 227 | P26: L-V
B27: 42168737 | C27: MARTINEZ MURAYARI INES ROXANA | D27: 43252 | E27: =IF(YEAR(D27)=2025,D27,"01/01/2025") -> 01/01/2025 | F27: =IF(VLOOKUP(B27,'INGRESOS 2025'!$B$7:$E$98,4,0)=0,"31/12/2025",VLOOKUP(B27,'INGRESOS 2025'!$B$7:$E$98,4,0)) -> 31/12/2025 | G27: =NETWORKDAYS.INTL(E27,F27,1,$R$8:$R$23) -> 249 | L27: =+G27+J27+K27 -> 249 | M27: =SUMIF('DIAS NO LABORADOS'!$C$6:$C$286,B27,'DIAS NO LABORADOS'!$N$6:$N$286) -> 11 | O27: =L27-M27+N27 -> 238 | P27: L-V
B28: 42326063 | C28: MARTI ROJAS DE ZÁRATE ANGELA TERESA | D28: 43900 | E28: =IF(YEAR(D28)=2025,D28,"01/01/2025") -> 01/01/2025 | F28: =IF(VLOOKUP(B28,'INGRESOS 2025'!$B$7:$E$98,4,0)=0,"31/12/2025",VLOOKUP(B28,'INGRESOS 2025'!$B$7:$E$98,4,0)) -> 45747 | G28: =NETWORKDAYS.INTL(E28,F28,1,$R$8:$R$23) -> 63 | L28: =+G28+J28+K28 -> 63 | M28: =SUMIF('DIAS NO LABORADOS'!$C$6:$C$286,B28,'DIAS NO LABORADOS'!$N$6:$N$286) -> 0 | O28: =L28-M28+N28 -> 63 | P28: L-V
B29: 42560153 | C29: VALDEZ CRUZ JOSEPH JOSUE | D29: 43222 | E29: =IF(YEAR(D29)=2025,D29,"01/01/2025") -> 01/01/2025 | F29: =IF(VLOOKUP(B29,'INGRESOS 2025'!$B$7:$E$98,4,0)=0,"31/12/2025",VLOOKUP(B29,'INGRESOS 2025'!$B$7:$E$98,4,0)) -> 31/12/2025 | G29: =NETWORKDAYS.INTL(E29,F29,1,$R$8:$R$23) -> 249 | L29: =+G29+J29+K29 -> 249 | M29: =SUMIF('DIAS NO LABORADOS'!$C$6:$C$286,B29,'DIAS NO LABORADOS'!$N$6:$N$286) -> 20 | O29: =L29-M29+N29 -> 229 | P29: L-V
B30: 42646402 | C30: BALDOCEDA COLQUI YESENIA FLORA | D30: 44935 | E30: =IF(YEAR(D30)=2025,D30,"01/01/2025") -> 01/01/2025 | F30: =IF(VLOOKUP(B30,'INGRESOS 2025'!$B$7:$E$98,4,0)=0,"31/12/2025",VLOOKUP(B30,'INGRESOS 2025'!$B$7:$E$98,4,0)) -> 31/12/2025 | G30: =NETWORKDAYS.INTL(E30,F30,1,$R$8:$R$23) -> 249 | L30: =+G30+J30+K30 -> 249 | M30: =SUMIF('DIAS NO LABORADOS'!$C$6:$C$286,B30,'DIAS NO LABORADOS'!$N$6:$N$286) -> 14 | O30: =L30-M30+N30 -> 235 | P30: L-V
B31: 43393889 | C31: ZAPATA QUEVEDO KARINA JANET | D31: 45631 | E31: =IF(YEAR(D31)=2025,D31,"01/01/2025") -> 01/01/2025 | F31: =IF(VLOOKUP(B31,'INGRESOS 2025'!$B$7:$E$98,4,0)=0,"31/12/2025",VLOOKUP(B31,'INGRESOS 2025'!$B$7:$E$98,4,0)) -> 45882 | G31: =NETWORKDAYS.INTL(E31,F31,1,$R$8:$R$23) -> 153 | L31: =+G31+J31+K31 -> 153 | M31: =SUMIF('DIAS NO LABORADOS'!$C$6:$C$286,B31,'DIAS NO LABORADOS'!$N$6:$N$286) -> 1 | O31: =L31-M31+N31 -> 152 | P31: L-V
B32: 43426313 | C32: LOPEZ MENDOZA GIULIANA JANNET | D32: 43206 | E32: =IF(YEAR(D32)=2025,D32,"01/01/2025") -> 01/01/2025 | F32: =IF(VLOOKUP(B32,'INGRESOS 2025'!$B$7:$E$98,4,0)=0,"31/12/2025",VLOOKUP(B32,'INGRESOS 2025'!$B$7:$E$98,4,0)) -> 31/12/2025 | G32: =NETWORKDAYS.INTL(E32,F32,1,$R$8:$R$23) -> 249 | L32: =+G32+J32+K32 -> 249 | M32: =SUMIF('DIAS NO LABORADOS'!$C$6:$C$286,B32,'DIAS NO LABORADOS'!$N$6:$N$286) -> 30 | O32: =L32-M32+N32 -> 219 | P32: L-V
B33: 43643490 | C33: ESPINOZA RUA KARINNA ESPERANZA | D33: 44348 | E33: =IF(YEAR(D33)=2025,D33,"01/01/2025") -> 01/01/2025 | F33: =IF(VLOOKUP(B33,'INGRESOS 2025'!$B$7:$E$98,4,0)=0,"31/12/2025",VLOOKUP(B33,'INGRESOS 2025'!$B$7:$E$98,4,0)) -> 45844 | G33: =NETWORKDAYS.INTL(E33,F33,1,$R$8:$R$23) -> 129 | L33: =+G33+J33+K33 -> 129 | M33: =SUMIF('DIAS NO LABORADOS'!$C$6:$C$286,B33,'DIAS NO LABORADOS'!$N$6:$N$286) -> 14 | O33: =L33-M33+N33 -> 115 | P33: L-V
B34: 45282900 | C34: BELUPU GUTIERREZ CARLO DANIEL | D34: 45541 | E34: =IF(YEAR(D34)=2025,D34,"01/01/2025") -> 01/01/2025 | F34: =IF(VLOOKUP(B34,'INGRESOS 2025'!$B$7:$E$98,4,0)=0,"31/12/2025",VLOOKUP(B34,'INGRESOS 2025'!$B$7:$E$98,4,0)) -> 31/12/2025 | G34: =NETWORKDAYS.INTL(E34,F34,1,$R$8:$R$23) -> 249 | L34: =+G34+J34+K34 -> 249 | M34: =SUMIF('DIAS NO LABORADOS'!$C$6:$C$286,B34,'DIAS NO LABORADOS'!$N$6:$N$286) -> 9 | O34: =L34-M34+N34 -> 240 | P34: L-V
B35: 45813056 | C35: ALFARO VILLACORTA VICTOR HUGO GARY | D35: 42948 | E35: =IF(YEAR(D35)=2025,D35,"01/01/2025") -> 01/01/2025 | F35: =IF(VLOOKUP(B35,'INGRESOS 2025'!$B$7:$E$98,4,0)=0,"31/12/2025",VLOOKUP(B35,'INGRESOS 2025'!$B$7:$E$98,4,0)) -> 31/12/2025 | G35: =NETWORKDAYS.INTL(E35,F35,1,$R$8:$R$23) -> 249 | L35: =+G35+J35+K35 -> 249 | M35: =SUMIF('DIAS NO LABORADOS'!$C$6:$C$286,B35,'DIAS NO LABORADOS'!$N$6:$N$286) -> 28 | O35: =L35-M35+N35 -> 221 | P35: L-V
... B44: 48035238 | C44: YUCRA MANCILLA AHRON | D44: 45627 | E44: =IF(YEAR(D44)=2025,D44,"01/01/2025") -> 01/01/2025 | F44: =IF(VLOOKUP(B44,'INGRESOS 2025'!$B$7:$E$98,4,0)=0,"31/12/2025",VLOOKUP(B44,'INGRESOS 2025'!$B$7:$E$98,4,0)) -> 31/12/2025 | G44: =NETWORKDAYS.INTL(E44,F44,1,$R$8:$R$23) -> 249 | L44: =+G44+J44+K44 -> 249 | M44: =SUMIF('DIAS NO LABORADOS'!$C$6:$C$286,B44,'DIAS NO LABORADOS'!$N$6:$N$286) -> 11 | O44: =L44-M44+N44 -> 238 | P44: L-V
B45: 48109666 | C45: CCAPA SIGUEÑAS SILENE DORA | D45: 45628 | E45: =IF(YEAR(D45)=2025,D45,"01/01/2025") -> 01/01/2025 | F45: 45716 | G45: =NETWORKDAYS.INTL(E45,F45,1,$R$8:$R$23) -> 42 | H45: 45887 | I45: 46022 | J45: =NETWORKDAYS.INTL(H45,I45,1,$R$8:$R$23) -> 94 | L45: =+G45+J45+K45 -> 136 | M45: =SUMIF('DIAS NO LABORADOS'!$C$6:$C$286,B45,'DIAS NO LABORADOS'!$N$6:$N$286) -> 3 | O45: =L45-M45+N45 -> 133 | P45: L-V
B46: 48588627 | C46: CARRERA RAMIREZ KATTYA HELEN | D46: 43243 | E46: =IF(YEAR(D46)=2025,D46,"01/01/2025") -> 01/01/2025 | F46: =IF(VLOOKUP(B46,'INGRESOS 2025'!$B$7:$E$98,4,0)=0,"31/12/2025",VLOOKUP(B46,'INGRESOS 2025'!$B$7:$E$98,4,0)) -> 31/12/2025 | G46: =NETWORKDAYS.INTL(E46,F46,1,$R$8:$R$23) -> 249 | K46: 98 | L46: =+G46+J46+K46 -> 347 | M46: =SUMIF('DIAS NO LABORADOS'!$C$6:$C$286,B46,'DIAS NO LABORADOS'!$N$6:$N$286) -> 83 | O46: =L46-M46+N46 -> 264 | P46: L-V
B47: 70857319 | C47: SAKAY MORISAKI LUIS CARLOS | D47: 44799 | E47: =IF(YEAR(D47)=2025,D47,"01/01/2025") -> 01/01/2025 | F47: =IF(VLOOKUP(B47,'INGRESOS 2025'!$B$7:$E$98,4,0)=0,"31/12/2025",VLOOKUP(B47,'INGRESOS 2025'!$B$7:$E$98,4,0)) -> 31/12/2025 | G47: =NETWORKDAYS.INTL(E47,F47,1,$R$8:$R$23) -> 249 | L47: =+G47+J47+K47 -> 249 | M47: =SUMIF('DIAS NO LABORADOS'!$C$6:$C$286,B47,'DIAS NO LABORADOS'!$N$6:$N$286) -> 24 | O47: =L47-M47+N47 -> 225 | P47: L-V
B48: 71467210 | C48: ANTAYHUA GRABIEL ISAAC ISMAEL | D48: 43525 | E48: =IF(YEAR(D48)=2025,D48,"01/01/2025") -> 01/01/2025 | F48: =IF(VLOOKUP(B48,'INGRESOS 2025'!$B$7:$E$98,4,0)=0,"31/12/2025",VLOOKUP(B48,'INGRESOS 2025'!$B$7:$E$98,4,0)) -> 31/12/2025 | G48: =NETWORKDAYS.INTL(E48,F48,1,$R$8:$R$23) -> 249 | L48: =+G48+J48+K48 -> 249 | M48: =SUMIF('DIAS NO LABORADOS'!$C$6:$C$286,B48,'DIAS NO LABORADOS'!$N$6:$N$286) -> 19 | O48: =L48-M48+N48 -> 230 | P48: L-V
B49: 71569497 | C49: CAMPOS PALOMINO DIANA MARGARITA | D49: 43973 | E49: =IF(YEAR(D49)=2025,D49,"01/01/2025") -> 01/01/2025 | F49: =IF(VLOOKUP(B49,'INGRESOS 2025'!$B$7:$E$98,4,0)=0,"31/12/2025",VLOOKUP(B49,'INGRESOS 2025'!$B$7:$E$98,4,0)) -> 31/12/2025 | G49: =NETWORKDAYS.INTL(E49,F49,1,$R$8:$R$23) -> 249 | K49: 98 | L49: =+G49+J49+K49 -> 347 | M49: =SUMIF('DIAS NO LABORADOS'!$C$6:$C$286,B49,'DIAS NO LABORADOS'!$N$6:$N$286) -> 95 | O49: =L49-M49+N49 -> 252 | P49: L-V
B50: 71726981 | C50: CRUZ QUISPE GEYDI ANTONELA | D50: 45600 | E50: =IF(YEAR(D50)=2025,D50,"01/01/2025") -> 01/01/2025 | F50: =IF(VLOOKUP(B50,'INGRESOS 2025'!$B$7:$E$98,4,0)=0,"31/12/2025",VLOOKUP(B50,'INGRESOS 2025'!$B$7:$E$98,4,0)) -> 31/12/2025 | G50: =NETWORKDAYS.INTL(E50,F50,1,$R$8:$R$23) -> 249 | L50: =+G50+J50+K50 -> 249 | M50: =SUMIF('DIAS NO LABORADOS'!$C$6:$C$286,B50,'DIAS NO LABORADOS'!$N$6:$N$286) -> 1 | O50: =L50-M50+N50 -> 248 | P50: L-V
B51: 72001771 | C51: GUEVARA SALINAS BRYAN GUSTAVO | D51: 44483 | E51: =IF(YEAR(D51)=2025,D51,"01/01/2025") -> 01/01/2025 | F51: =IF(VLOOKUP(B51,'INGRESOS 2025'!$B$7:$E$98,4,0)=0,"31/12/2025",VLOOKUP(B51,'INGRESOS 2025'!$B$7:$E$98,4,0)) -> 31/12/2025 | G51: =NETWORKDAYS.INTL(E51,F51,1,$R$8:$R$23) -> 249 | L51: =+G51+J51+K51 -> 249 | M51: =SUMIF('DIAS NO LABORADOS'!$C$6:$C$286,B51,'DIAS NO LABORADOS'!$N$6:$N$286) -> 17 | O51: =L51-M51+N51 -> 232 | P51: L-V
B52: 72016504 | C52: GUTIERREZ DE LA CRUZ MIGUEL ANGEL | D52: 44432 | E52: =IF(YEAR(D52)=2025,D52,"01/01/2025") -> 01/01/2025 | F52: =IF(VLOOKUP(B52,'INGRESOS 2025'!$B$7:$E$98,4,0)=0,"31/12/2025",VLOOKUP(B52,'INGRESOS 2025'!$B$7:$E$98,4,0)) -> 31/12/2025 | G52: =NETWORKDAYS.INTL(E52,F52,1,$R$8:$R$23) -> 249 | L52: =+G52+J52+K52 -> 249 | M52: =SUMIF('DIAS NO LABORADOS'!$C$6:$C$286,B52,'DIAS NO LABORADOS'!$N$6:$N$286) -> 21 | O52: =L52-M52+N52 -> 228 | P52: L-V
B53: 72152204 | C53: HUAMAN COLLANTES WALTER JUNIOR | D53: 43724 | E53: =IF(YEAR(D53)=2025,D53,"01/01/2025") -> 01/01/2025 | F53: =IF(VLOOKUP(B53,'INGRESOS 2025'!$B$7:$E$98,4,0)=0,"31/12/2025",VLOOKUP(B53,'INGRESOS 2025'!$B$7:$E$98,4,0)) -> 31/12/2025 | G53: =NETWORKDAYS.INTL(E53,F53,1,$R$8:$R$23) -> 249 | L53: =+G53+J53+K53 -> 249 | M53: =SUMIF('DIAS NO LABORADOS'!$C$6:$C$286,B53,'DIAS NO LABORADOS'!$N$6:$N$286) -> 10 | O53: =L53-M53+N53 -> 239 | P53: L-V
B54: 72152557 | C54: ENCALADA PRADA GLORIA STEFANY | D54: 45313 | E54: =IF(YEAR(D54)=2025,D54,"01/01/2025") -> 01/01/2025 | F54: =IF(VLOOKUP(B54,'INGRESOS 2025'!$B$7:$E$98,4,0)=0,"31/12/2025",VLOOKUP(B54,'INGRESOS 2025'!$B$7:$E$98,4,0)) -> 31/12/2025 | G54: =NETWORKDAYS.INTL(E54,F54,1,$R$8:$R$23) -> 249 | L54: =+G54+J54+K54 -> 249 | M54: =SUMIF('DIAS NO LABORADOS'!$C$6:$C$286,B54,'DIAS NO LABORADOS'!$N$6:$N$286) -> 6 | O54: =L54-M54+N54 -> 243 | P54: L-V
B55: 72410117 | C55: LOPEZ GAVELAN JESUS ALFREDO | D55: 45414 | E55: =IF(YEAR(D55)=2025,D55,"01/01/2025") -> 01/01/2025 | F55: =IF(VLOOKUP(B55,'INGRESOS 2025'!$B$7:$E$98,4,0)=0,"31/12/2025",VLOOKUP(B55,'INGRESOS 2025'!$B$7:$E$98,4,0)) -> 45900 | G55: =NETWORKDAYS.INTL(E55,F55,1,$R$8:$R$23) -> 165 | L55: =+G55+J55+K55 -> 165 | M55: =SUMIF('DIAS NO LABORADOS'!$C$6:$C$286,B55,'DIAS NO LABORADOS'!$N$6:$N$286) -> 10 | O55: =L55-M55+N55 -> 155 | P55: L-V
B56: 72686896 | C56: REBATTA ROJAS GONZALO | D56: 44453 | E56: =IF(YEAR(D56)=2025,D56,"01/01/2025") -> 01/01/2025 | F56: =IF(VLOOKUP(B56,'INGRESOS 2025'!$B$7:$E$98,4,0)=0,"31/12/2025",VLOOKUP(B56,'INGRESOS 2025'!$B$7:$E$98,4,0)) -> 31/12/2025 | G56: =NETWORKDAYS.INTL(E56,F56,1,$R$8:$R$23) -> 249 | L56: =+G56+J56+K56 -> 249 | M56: =SUMIF('DIAS NO LABORADOS'!$C$6:$C$286,B56,'DIAS NO LABORADOS'!$N$6:$N$286) -> 15 | O56: =L56-M56+N56 -> 234 | P56: L-V
B57: 72857524 | C57: SANCHEZ VALDEZ MACARENA | D57: 45574 | E57: =IF(YEAR(D57)=2025,D57,"01/01/2025") -> 01/01/2025 | F57: =IF(VLOOKUP(B57,'INGRESOS 2025'!$B$7:$E$98,4,0)=0,"31/12/2025",VLOOKUP(B57,'INGRESOS 2025'!$B$7:$E$98,4,0)) -> 31/12/2025 | G57: =NETWORKDAYS.INTL(E57,F57,1,$R$8:$R$23) -> 249 | L57: =+G57+J57+K57 -> 249 | M57: =SUMIF('DIAS NO LABORADOS'!$C$6:$C$286,B57,'DIAS NO LABORADOS'!$N$6:$N$286) -> 5 | O57: =L57-M57+N57 -> 244 | P57: L-V
B58: 72900856 | C58: TORRES ALEGRIA JUAN LUIS | D58: 43845 | E58: =IF(YEAR(D58)=2025,D58,"01/01/2025") -> 01/01/2025 | F58: =IF(VLOOKUP(B58,'INGRESOS 2025'!$B$7:$E$98,4,0)=0,"31/12/2025",VLOOKUP(B58,'INGRESOS 2025'!$B$7:$E$98,4,0)) -> 45835 | G58: =NETWORKDAYS.INTL(E58,F58,1,$R$8:$R$23) -> 124 | L58: =+G58+J58+K58 -> 124 | M58: =SUMIF('DIAS NO LABORADOS'!$C$6:$C$286,B58,'DIAS NO LABORADOS'!$N$6:$N$286) -> 6 | O58: =L58-M58+N58 -> 118 | P58: L-V
B59: 73115211 | C59: TORRES TORRES ANA PAULA | D59: 45481 | E59: =IF(YEAR(D59)=2025,D59,"01/01/2025") -> 01/01/2025 | F59: =IF(VLOOKUP(B59,'INGRESOS 2025'!$B$7:$E$98,4,0)=0,"31/12/2025",VLOOKUP(B59,'INGRESOS 2025'!$B$7:$E$98,4,0)) -> 31/12/2025 | G59: =NETWORKDAYS.INTL(E59,F59,1,$R$8:$R$23) -> 249 | L59: =+G59+J59+K59 -> 249 | M59: =SUMIF('DIAS NO LABORADOS'!$C$6:$C$286,B59,'DIAS NO LABORADOS'!$N$6:$N$286) -> 5 | O59: =L59-M59+N59 -> 244 | P59: L-V
B60: 73958636 | C60: ALEJOS EGUSQUIZA AYXA JELUZETH | D60: 43530 | E60: =IF(YEAR(D60)=2025,D60,"01/01/2025") -> 01/01/2025 | F60: =IF(VLOOKUP(B60,'INGRESOS 2025'!$B$7:$E$98,4,0)=0,"31/12/2025",VLOOKUP(B60,'INGRESOS 2025'!$B$7:$E$98,4,0)) -> 31/12/2025 | G60: =NETWORKDAYS.INTL(E60,F60,1,$R$8:$R$23) -> 249 | K60: 56 | L60: =+G60+J60+K60 -> 305 | M60: =SUMIF('DIAS NO LABORADOS'!$C$6:$C$286,B60,'DIAS NO LABORADOS'!$N$6:$N$286) -> 49 | O60: =L60-M60+N60 -> 256 | P60: L-V
B61: 74069271 | C61: HUAMANI ALTAMIRANO GABRIELA SABRINA | D61: 44483 | E61: =IF(YEAR(D61)=2025,D61,"01/01/2025") -> 01/01/2025 | F61: =IF(VLOOKUP(B61,'INGRESOS 2025'!$B$7:$E$98,4,0)=0,"31/12/2025",VLOOKUP(B61,'INGRESOS 2025'!$B$7:$E$98,4,0)) -> 31/12/2025 | G61: =NETWORKDAYS.INTL(E61,F61,1,$R$8:$R$23) -> 249 | L61: =+G61+J61+K61 -> 249 | M61: =SUMIF('DIAS NO LABORADOS'!$C$6:$C$286,B61,'DIAS NO LABORADOS'!$N$6:$N$286) -> 19 | O61: =L61-M61+N61 -> 230 | P61: L-V
B62: 74080395 | C62: AVALOS MORANTE KATHERINE ALEXANDRA | D62: 43497 | E62: =IF(YEAR(D62)=2025,D62,"01/01/2025") -> 01/01/2025 | F62: =IF(VLOOKUP(B62,'INGRESOS 2025'!$B$7:$E$98,4,0)=0,"31/12/2025",VLOOKUP(B62,'INGRESOS 2025'!$B$7:$E$98,4,0)) -> 31/12/2025 | G62: =NETWORKDAYS.INTL(E62,F62,1,$R$8:$R$23) -> 249 | L62: =+G62+J62+K62 -> 249 | M62: =SUMIF('DIAS NO LABORADOS'!$C$6:$C$286,B62,'DIAS NO LABORADOS'!$N$6:$N$286) -> 4 | O62: =L62-M62+N62 -> 245 | P62: L-V
B63: 74499365 | C63: GRANDA SANTIAGO YONATHAN SMIETH | D63: 45181 | E63: =IF(YEAR(D63)=2025,D63,"01/01/2025") -> 01/01/2025 | F63: =IF(VLOOKUP(B63,'INGRESOS 2025'!$B$7:$E$98,4,0)=0,"31/12/2025",VLOOKUP(B63,'INGRESOS 2025'!$B$7:$E$98,4,0)) -> 46003 | G63: =NETWORKDAYS.INTL(E63,F63,1,$R$8:$R$23) -> 237 | L63: =+G63+J63+K63 -> 237 | M63: =SUMIF('DIAS NO LABORADOS'!$C$6:$C$286,B63,'DIAS NO LABORADOS'!$N$6:$N$286) -> 13 | O63: =L63-M63+N63 -> 224 | P63: L-V
B64: 75597433 | C64: AZAÑERO SALAZAR LUIS ARTURO | D64: 45663 | E64: =IF(YEAR(D64)=2025,D64,"01/01/2025") -> 45663 | F64: =IF(VLOOKUP(B64,'INGRESOS 2025'!$B$7:$E$98,4,0)=0,"31/12/2025",VLOOKUP(B64,'INGRESOS 2025'!$B$7:$E$98,4,0)) -> 45807 | G64: =NETWORKDAYS.INTL(E64,F64,1,$R$8:$R$23) -> 102 | L64: =+G64+J64+K64 -> 102 | M64: =SUMIF('DIAS NO LABORADOS'!$C$6:$C$286,B64,'DIAS NO LABORADOS'!$N$6:$N$286) -> 0 | O64: =L64-M64+N64 -> 102 | P64: L-V
B65: 75743277 | C65: MALPARTIDA CASTILLO CLAUDIA | D65: 45628 | E65: =IF(YEAR(D65)=2025,D65,"01/01/2025") -> 01/01/2025 | F65: =IF(VLOOKUP(B65,'INGRESOS 2025'!$B$7:$E$98,4,0)=0,"31/12/2025",VLOOKUP(B65,'INGRESOS 2025'!$B$7:$E$98,4,0)) -> 31/12/2025 | G65: =NETWORKDAYS.INTL(E65,F65,1,$R$8:$R$23) -> 249 | L65: =+G65+J65+K65 -> 249 | M65: =SUMIF('DIAS NO LABORADOS'!$C$6:$C$286,B65,'DIAS NO LABORADOS'!$N$6:$N$286) -> 25 | O65: =L65-M65+N65 -> 224 | P65: L-V
B66: 76055775 | C66: ALAMA BERECHE ROYAL ANTHONY | D66: 45658 | E66: =IF(YEAR(D66)=2025,D66,"01/01/2025") -> 45658 | F66: =IF(VLOOKUP(B66,'INGRESOS 2025'!$B$7:$E$98,4,0)=0,"31/12/2025",VLOOKUP(B66,'INGRESOS 2025'!$B$7:$E$98,4,0)) -> 31/12/2025 | G66: =NETWORKDAYS.INTL(E66,F66,1,$R$8:$R$23) -> 249 | L66: =+G66+J66+K66 -> 249 | M66: =SUMIF('DIAS NO LABORADOS'!$C$6:$C$286,B66,'DIAS NO LABORADOS'!$N$6:$N$286) -> 7 | O66: =L66-M66+N66 -> 242 | P66: L-V
B67: 76084478 | C67: SANCHEZ AUCCAPURE JILLS KRAINEEM | D67: 45125 | E67: =IF(YEAR(D67)=2025,D67,"01/01/2025") -> 01/01/2025 | F67: =IF(VLOOKUP(B67,'INGRESOS 2025'!$B$7:$E$98,4,0)=0,"31/12/2025",VLOOKUP(B67,'INGRESOS 2025'!$B$7:$E$98,4,0)) -> 31/12/2025 | G67: =NETWORKDAYS.INTL(E67,F67,1,$R$8:$R$23) -> 249 | L67: =+G67+J67+K67 -> 249 | M67: =SUMIF('DIAS NO LABORADOS'!$C$6:$C$286,B67,'DIAS NO LABORADOS'!$N$6:$N$286) -> 0 | O67: =L67-M67+N67 -> 249 | P67: L-V
B68: 76163280 | C68: BENITES OTERO YRINNA GISELLA | D68: 45181 | E68: =IF(YEAR(D68)=2025,D68,"01/01/2025") -> 01/01/2025 | F68: =IF(VLOOKUP(B68,'INGRESOS 2025'!$B$7:$E$98,4,0)=0,"31/12/2025",VLOOKUP(B68,'INGRESOS 2025'!$B$7:$E$98,4,0)) -> 31/12/2025 | G68: =NETWORKDAYS.INTL(E68,F68,1,$R$8:$R$23) -> 249 | L68: =+G68+J68+K68 -> 249 | M68: =SUMIF('DIAS NO LABORADOS'!$C$6:$C$286,B68,'DIAS NO LABORADOS'!$N$6:$N$286) -> 19 | O68: =L68-M68+N68 -> 230 | P68: L-V
B69: 76723256 | C69: REYNA CORTEZ PATRICK ADAMS | D69: 44636 | E69: =IF(YEAR(D69)=2025,D69,"01/01/2025") -> 01/01/2025 | F69: =IF(VLOOKUP(B69,'INGRESOS 2025'!$B$7:$E$98,4,0)=0,"31/12/2025",VLOOKUP(B69,'INGRESOS 2025'!$B$7:$E$98,4,0)) -> 31/12/2025 | G69: =NETWORKDAYS.INTL(E69,F69,1,$R$8:$R$23) -> 249 | L69: =+G69+J69+K69 -> 249 | M69: =SUMIF('DIAS NO LABORADOS'!$C$6:$C$286,B69,'DIAS NO LABORADOS'!$N$6:$N$286) -> 18 | O69: =L69-M69+N69 -> 231 | P69: L-V
B70: 77473806 | C70: SANDOVAL GONZALES YASIRA JASMIN | D70: 45261 | E70: =IF(YEAR(D70)=2025,D70,"01/01/2025") -> 01/01/2025 | F70: =IF(VLOOKUP(B70,'INGRESOS 2025'!$B$7:$E$98,4,0)=0,"31/12/2025",VLOOKUP(B70,'INGRESOS 2025'!$B$7:$E$98,4,0)) -> 31/12/2025 | G70: =NETWORKDAYS.INTL(E70,F70,1,$R$8:$R$23) -> 249 | K70: 98 | L70: =+G70+J70+K70 -> 347 | M70: =SUMIF('DIAS NO LABORADOS'!$C$6:$C$286,B70,'DIAS NO LABORADOS'!$N$6:$N$286) -> 72 | O70: =L70-M70+N70 -> 275 | P70: L-V
B71: 002120932 | C71: GAME LOAIZA MANUELXAVIER | D71: 43678 | E71: =IF(YEAR(D71)=2025,D71,"01/01/2025") -> 01/01/2025 | F71: =IF(VLOOKUP(B71,'INGRESOS 2025'!$B$7:$E$98,4,0)=0,"31/12/2025",VLOOKUP(B71,'INGRESOS 2025'!$B$7:$E$98,4,0)) -> 31/12/2025 | G71: =NETWORKDAYS.INTL(E71,F71,1,$R$8:$R$23) -> 249 | L71: =+G71+J71+K71 -> 249 | M71: =SUMIF('DIAS NO LABORADOS'!$C$6:$C$286,B71,'DIAS NO LABORADOS'!$N$6:$N$286) -> 0 | O71: =L71-M71+N71 -> 249 | P71: L-V
B72: 002420607 | C72: ESCALANTE ZUÑIGA DAVID | D72: 45261 | E72: =IF(YEAR(D72)=2025,D72,"01/01/2025") -> 01/01/2025 | F72: =IF(VLOOKUP(B72,'INGRESOS 2025'!$B$7:$E$98,4,0)=0,"31/12/2025",VLOOKUP(B72,'INGRESOS 2025'!$B$7:$E$98,4,0)) -> 31/12/2025 | G72: =NETWORKDAYS.INTL(E72,F72,1,$R$8:$R$23) -> 249 | L72: =+G72+J72+K72 -> 249 | M72: =SUMIF('DIAS NO LABORADOS'!$C$6:$C$286,B72,'DIAS NO LABORADOS'!$N$6:$N$286) -> 0 | O72: =L72-M72+N72 -> 249 | P72: L-V
B73: 005608621 | C73: GAME TRIVIÑO MARIA JOSE | D73: 45170 | E73: =IF(YEAR(D73)=2025,D73,"01/01/2025") -> 01/01/2025 | F73: =IF(VLOOKUP(B73,'INGRESOS 2025'!$B$7:$E$98,4,0)=0,"31/12/2025",VLOOKUP(B73,'INGRESOS 2025'!$B$7:$E$98,4,0)) -> 31/12/2025 | G73: =NETWORKDAYS.INTL(E73,F73,1,$R$8:$R$23) -> 249 | L73: =+G73+J73+K73 -> 249 | M73: =SUMIF('DIAS NO LABORADOS'!$C$6:$C$286,B73,'DIAS NO LABORADOS'!$N$6:$N$286) -> 0 | O73: =L73-M73+N73 -> 249 | P73: L-V
B74: 005698394 | C74: GAME TRIVIÑO JUAN ANDRES | D74: 45170 | E74: =IF(YEAR(D74)=2025,D74,"01/01/2025") -> 01/01/2025 | F74: =IF(VLOOKUP(B74,'INGRESOS 2025'!$B$7:$E$98,4,0)=0,"31/12/2025",VLOOKUP(B74,'INGRESOS 2025'!$B$7:$E$98,4,0)) -> 31/12/2025 | G74: =NETWORKDAYS.INTL(E74,F74,1,$R$8:$R$23) -> 249 | L74: =+G74+J74+K74 -> 249 | M74: =SUMIF('DIAS NO LABORADOS'!$C$6:$C$286,B74,'DIAS NO LABORADOS'!$N$6:$N$286) -> 0 | O74: =L74-M74+N74 -> 249 | P74: L-V
B75: 006123587 | C75: GAME TRIVIÑO MANUEL XAVIER | D75: 45170 | E75: =IF(YEAR(D75)=2025,D75,"01/01/2025") -> 01/01/2025 | F75: =IF(VLOOKUP(B75,'INGRESOS 2025'!$B$7:$E$98,4,0)=0,"31/12/2025",VLOOKUP(B75,'INGRESOS 2025'!$B$7:$E$98,4,0)) -> 31/12/2025 | G75: =NETWORKDAYS.INTL(E75,F75,1,$R$8:$R$23) -> 249 | L75: =+G75+J75+K75 -> 249 | M75: =SUMIF('DIAS NO LABORADOS'!$C$6:$C$286,B75,'DIAS NO LABORADOS'!$N$6:$N$286) -> 0 | O75: =L75-M75+N75 -> 249 | P75: L-V
B76: 74723670 | C76: QUINTO CAMAHUALI LISETH CHARO | D76: 45689 | E76: =IF(YEAR(D76)=2025,D76,"01/01/2025") -> 45689 | F76: =IF(VLOOKUP(B76,'INGRESOS 2025'!$B$7:$E$98,4,0)=0,"31/12/2025",VLOOKUP(B76,'INGRESOS 2025'!$B$7:$E$98,4,0)) -> 31/12/2025 | G76: =NETWORKDAYS.INTL(E76,F76,1,$R$8:$R$23) -> 227 | L76: =+G76+J76+K76 -> 227 | M76: =SUMIF('DIAS NO LABORADOS'!$C$6:$C$286,B76,'DIAS NO LABORADOS'!$N$6:$N$286) -> 6 | O76: =L76-M76+N76 -> 221 | P76: L-V
B77: 70831120 | C77: TORRES OCHOA KAMILA OLENKA | D77: 45719 | E77: =IF(YEAR(D77)=2025,D77,"01/01/2025") -> 45719 | F77: =IF(VLOOKUP(B77,'INGRESOS 2025'!$B$7:$E$98,4,0)=0,"31/12/2025",VLOOKUP(B77,'INGRESOS 2025'!$B$7:$E$98,4,0)) -> 45900 | G77: =NETWORKDAYS.INTL(E77,F77,1,$R$8:$R$23) -> 123 | L77: =+G77+J77+K77 -> 123 | M77: =SUMIF('DIAS NO LABORADOS'!$C$6:$C$286,B77,'DIAS NO LABORADOS'!$N$6:$N$286) -> 3 | O77: =L77-M77+N77 -> 120 | P77: L-V
B78: 008938904 | C78: CABEZAS RUBIO JORGE ARTURO | D78: 45717 | E78: =IF(YEAR(D78)=2025,D78,"01/01/2025") -> 45717 | F78: =IF(VLOOKUP(B78,'INGRESOS 2025'!$B$7:$E$98,4,0)=0,"31/12/2025",VLOOKUP(B78,'INGRESOS 2025'!$B$7:$E$98,4,0)) -> 31/12/2025 | G78: =NETWORKDAYS.INTL(E78,F78,1,$R$8:$R$23) -> 207 | L78: =+G78+J78+K78 -> 207 | M78: =SUMIF('DIAS NO LABORADOS'!$C$6:$C$286,B78,'DIAS NO LABORADOS'!$N$6:$N$286) -> 0 | O78: =L78-M78+N78 -> 207 | P78: L-V
B79: 40365445 | C79: DE OLARTE FERNANDEZ MILAGROS | D79: 45783 | E79: =IF(YEAR(D79)=2025,D79,"01/01/2025") -> 45783 | F79: =IF(VLOOKUP(B79,'INGRESOS 2025'!$B$7:$E$98,4,0)=0,"31/12/2025",VLOOKUP(B79,'INGRESOS 2025'!$B$7:$E$98,4,0)) -> 45961 | G79: =NETWORKDAYS.INTL(E79,F79,1,$R$8:$R$23) -> 124 | L79: =+G79+J79+K79 -> 124 | M79: =SUMIF('DIAS NO LABORADOS'!$C$6:$C$286,B79,'DIAS NO LABORADOS'!$N$6:$N$286) -> 3 | O79: =L79-M79+N79 -> 121 | P79: L-V
B80: 78377581 | C80: ROMAN RENTERIA ZAIDA YASMIN | D80: 45784 | E80: =IF(YEAR(D80)=2025,D80,"01/01/2025") -> 45784 | F80: =IF(VLOOKUP(B80,'INGRESOS 2025'!$B$7:$E$98,4,0)=0,"31/12/2025",VLOOKUP(B80,'INGRESOS 2025'!$B$7:$E$98,4,0)) -> 31/12/2025 | G80: =NETWORKDAYS.INTL(E80,F80,1,$R$8:$R$23) -> 163 | L80: =+G80+J80+K80 -> 163 | M80: =SUMIF('DIAS NO LABORADOS'!$C$6:$C$286,B80,'DIAS NO LABORADOS'!$N$6:$N$286) -> 3 | O80: =L80-M80+N80 -> 160 | P80: L-V
B81: 42151178 | C81: BORDA LEON ROSARIO LIZBETH | D81: 45839 | E81: =IF(YEAR(D81)=2025,D81,"01/01/2025") -> 45839 | F81: =IF(VLOOKUP(B81,'INGRESOS 2025'!$B$7:$E$98,4,0)=0,"31/12/2025",VLOOKUP(B81,'INGRESOS 2025'!$B$7:$E$98,4,0)) -> 31/12/2025 | G81: =NETWORKDAYS.INTL(E81,F81,1,$R$8:$R$23) -> 124 | L81: =+G81+J81+K81 -> 124 | M81: =SUMIF('DIAS NO LABORADOS'!$C$6:$C$286,B81,'DIAS NO LABORADOS'!$N$6:$N$286) -> 0 | O81: =L81-M81+N81 -> 124 | P81: L-V
B82: 44521978 | C82: SORIA OCHOA MAGALY GIOVANNA | D82: 45868 | E82: =IF(YEAR(D82)=2025,D82,"01/01/2025") -> 45868 | F82: =IF(VLOOKUP(B82,'INGRESOS 2025'!$B$7:$E$98,4,0)=0,"31/12/2025",VLOOKUP(B82,'INGRESOS 2025'!$B$7:$E$98,4,0)) -> 45902 | G82: =NETWORKDAYS.INTL(E82,F82,1,$R$8:$R$23) -> 24 | L82: =+G82+J82+K82 -> 24 | M82: =SUMIF('DIAS NO LABORADOS'!$C$6:$C$286,B82,'DIAS NO LABORADOS'!$N$6:$N$286) -> 0 | O82: =L82-M82+N82 -> 24 | P82: L-V
... B95: 40865746 | C95: OLAYA RAMOS GLADYS MARLENY | D95: 45992 | E95: =IF(YEAR(D95)=2025,D95,"01/01/2025") -> 45992 | F95: =IF(VLOOKUP(B95,'INGRESOS 2025'!$B$7:$E$98,4,0)=0,"31/12/2025",VLOOKUP(B95,'INGRESOS 2025'!$B$7:$E$98,4,0)) -> 31/12/2025 | G95: =NETWORKDAYS.INTL(E95,F95,1,$R$8:$R$23) -> 20 | L95: =+G95+J95+K95 -> 20 | M95: =SUMIF('DIAS NO LABORADOS'!$C$6:$C$286,B95,'DIAS NO LABORADOS'!$N$6:$N$286) -> 0 | O95: =L95-M95+N95 -> 20 | P95: L-V
B96: 72859721 | C96: ESPINOZA REYES LIZ KERALDIL | D96: 45992 | E96: =IF(YEAR(D96)=2025,D96,"01/01/2025") -> 45992 | F96: =IF(VLOOKUP(B96,'INGRESOS 2025'!$B$7:$E$98,4,0)=0,"31/12/2025",VLOOKUP(B96,'INGRESOS 2025'!$B$7:$E$98,4,0)) -> 31/12/2025 | G96: =NETWORKDAYS.INTL(E96,F96,11,$R$8:$R$23) -> 24 | L96: =+G96+J96+K96 -> 24 | M96: =SUMIF('DIAS NO LABORADOS'!$C$6:$C$286,B96,'DIAS NO LABORADOS'!$N$6:$N$286) -> 0 | O96: =L96-M96+N96 -> 24 | P96: L-S
B97: 74376927 | C97: AMODEO GORDILLO ANGIE ESTEFANI | D97: 46002 | E97: =IF(YEAR(D97)=2025,D97,"01/01/2025") -> 46002 | F97: =IF(VLOOKUP(B97,'INGRESOS 2025'!$B$7:$E$98,4,0)=0,"31/12/2025",VLOOKUP(B97,'INGRESOS 2025'!$B$7:$E$98,4,0)) -> 31/12/2025 | G97: =NETWORKDAYS.INTL(E97,F97,1,$R$8:$R$23) -> 14 | L97: =+G97+J97+K97 -> 14 | M97: =SUMIF('DIAS NO LABORADOS'!$C$6:$C$286,B97,'DIAS NO LABORADOS'!$N$6:$N$286) -> 0 | O97: =L97-M97+N97 -> 14 | P97: L-V

Sheet CONSOLIDADO
B3: DATOS PERSONALES | P3: LABORAL | V3: DATOS DE CONTRATO | X3: SUELDO | Z3: CTS | AB3: FECHAS DE MOVIENTO | AE3: PENSIONES | AI3: TIPO DE REMUNERACIÓN | AK3: DATOS DE PLANILLA | AS3: DIAS | BG3: HORAS EXTRAS | BK3: REINTEGRO DE HORAS EXTRAS | BO3: TIEMPO DE TARDANZA | BP3: HORAS TRABAJADAS | BQ3: INGRESOS | EL3: BASE IMPONIBLE | EM3: TOTAL BRUTO | EN3: DESCUENTOS | FR3: NETO A PAGAR | FX3: ESSALUD 9% | GB3: BASE AFECTA | GC3: BASE AFECTA
B4: Nº | C4: CÓDIGO | D4: TIPO DOC. | E4: NUMERO DE DOCUMENTO | F4: APELLIDOS Y NOMBRES | G4: FECHA NAC. | H4: AREA | I4: CENTRO DE COSTOS (SEDE) | J4: Cod. Sede | K4: SEDE | L4: Cod. LN | M4: LINEA NEGOCIO | N4: % | O4: Cod. CC | P4: CENTRO COSTO | Q4: % | R4: Cod. Áreas | S4: AREAS | T4: TIPO DE TRABAJADOR | U4: CARGO | V4: MODALIDAD DE CONTRATACIÓN | W4: CARGO DE PUESTO | X4: BANCO | Y4: NUMERO DE CUENTA SUELDO | Z4: BANCO | AA4: NUMERO DE CUENTA CTS | AB4: FECHA DE INICIO | AC4: FECHA DE CESE | AD4: MOTIVO CESE | AE4: SISTEMA PENSIONARIO | AF4: C.U.S.P.P. | AG4: CRUCE | AH4: OBSERVACIÓN ADICIONAL | AI4: BRUTO O NETO | AJ4: IMPORTE DE SER NETO NETO | AK4: IMPORTE DE MOVILIDAD SUPEDITADA | AL4: IMPORTE DE MOVILIDAD LIBRE DISPOSICIÓN | AM4: REFRIGERIO SUPEDITADO | AN4: REFRIGERIO FIJO ( DECLARADO COMO SUPEDITADO) | AO4: EPS ( SI O NO) | AP4: SEXO | AQ4: ASIG. FAM. ( SI O NO) | AR4: REM. BÁSICA | AS4: DIAS LABORADOS | AT4: DESCANSO MÉDICO | AU4: VACACIONES | AV4: LICENCIA CON GOCE DE HABER | AW4: LICENCIA POR PATERNIDAD | AX4: LICENCIA POR FALLECIMIENTO | AY4: SUB POR MATERNIDAD | AZ4: SUBSIDIO POR ENFERMEDAD | BA4: FALTAS | BB4: SANCIÓN DISCIPLINARIA | BC4: LICENCIA SIN GOCE DE HABER | BD4: DÍAS DE COMPRA DE VACACIONES | BE4: DÍAS DE SOBRETASA NOCTURNA | BG4: 0.25 | BH4: 0.35 | BI4: 100% (DÍA DE DESCANSO) | BJ4: 100% (DÍA DE FERIADO) | BK4: 0.25 | BL4: 0.35 | BM4: 100% (DÍA DE DESCANSO) | BN4: 100% (DÍA DE FERIADO) | BQ4: IMPORTES AFECTOS A (AFP-ONP-ESSALUD- 5TA) | CV4: CONCEPTOS AFECTOS SÓLO A QUINTA | DP4: NO AFECTOS | EB4: LIQUIDACIÓN | EN4: APORTE PENSIONARIO | ET4: IMPUESTO | EU4: DESCUE NTOS AFECTOS | EY4: OTROS | FQ4: TOTAL DSCTO. | FT4: DOLARES | FU4: SOLES | FY4: VIDA LEY
A5: AA | J5: Cod. Sede | K5: SEDE | L5: Cod. LN | M5: LINEA NEGOCIO | N5: % | O5: Cod. CC | P5: CENTRO COSTO | Q5: % | BQ5: HABER MENSUAL | BR5: ASIGNACION FAMILIAR | BS5: DESCANSO MÉDICO | BT5: REMUNERACION VACACIONAL | BU5: LICENCIA CON GOCE DE HABER | BV5: LICENCIA POR PATERNIDAD | BW5: LICENCIA POR FALLECIMIENTO | BX5: MOVILIDAD LIBRE DISPOSICIÓN | BY5: ALIMNTACIÓN PRINCIPAL | BZ5: SUBSIDIO POR MATERNIDAD | CA5: SUBSIDIO POR ENFERMEDAD | CB5: COSTO DE HORAS AL 25% | CC5: COSTO DE HORAS AL 35% | CD5: COSTO DE HORAS AL 100% | CE5: COMPRA DE VACACIONES | CF5: REMUNERACIÓN POR TRABAJO EN DÍA FERIADO | CG5: COMISIONES | CH5: ALIMENTACION PRINCIPAL | CI5: REINTEGRO AFECTO | CK5: SOBRETASA NOCTURNA | CL5: 5TA ASUMIDA | CM5: BONIFICACIÓN | CN5: VACACIONES RIA | CO5: REINTEGRO DE HORAS EXTRAS | CP5: REINTEGRO AFECTO | CQ5: BONO AFECTO | CV5: MOVILIDAD SUPEDITADA | CW5: REFRIGERIO | CX5: GRATIFICACIÓN RIA | CY5: BONIFICACIÓN EXTRAORDINARIA RIA | CZ5: SODEXO | DA5: VENDING | DB5: ASIGNACIÓN POR ESCOLARIDAD | DC5: REGALO DIA DEL PADRE | DD5: TARJETA ALIMENTACIÓN | DE5: ASIGNACIÓN POR VIVIENDA | DF5: GRATIFICACIÓN | DG5: BONIFICACIÓN EXTRAORDINARIA | DH5: UTILIDAD CONVENCIONAL | DI5: BONIFICACIÓN | DJ5: AGUINALDO | DK5: OBSEQUIO POR HALLOWEEN | DL5: GRATIFICACIÓN EXTRAORDINARIA | DM5: VALE POR NACIMIENTO | DN5: ASIGNACIÓN POR FESTIVIDAD DÍA MADRE | DO5: UTILIDADES | DP5: ADELANTO DE SUELDO | DQ5: PRÉSTAMO | DR5: DEVOLUCIÓN DE 5TA | DS5: ADELANTO DE VACACIONES | DT5: IMDEMNIZACIÓN POR VACACIONES | DU5: CTS | DV5: INTERESES CTS | DW5: CTS RIA | DX5: PRESTAMO ESCOLAR | DY5: REINTEGRO INAFECTO | EB5: CTS TRUNCA | EC5: CTS PENDIENTE | ED5: INTERESES | EE5: VACACIONES TRUNCAS | EF5: VACACIONES PENDIENTES | EG5: INDEMNIZACIÓN POR VACACIONES | EH5: GRATIFICACION PROPORCIONAL | EI5: BONIFICACION EXTRAORDINARIA PROPORCIONAL | EJ5: SUMA GRACIOSA | EK5: INDEMNIZACIÓN POR DESPIDO | EN5: APORTE OBLIGATORIO - AFP | EO5: COMISIONES - AFP | EP5: PRIMA DE SEGUROS - AFP | EQ5: APORTE COMPLEMENTARIO AFP - JUB ANTICIP | ER5: FONDO COMPLEMENTARIO DE JUBILACION | ES5: ONP | ET5: RENTA 5TA CATEGORIA | EU5: TARDANZAS | EV5: FALTAS | EW5: DESCUENTO AFECTO | EY5: REGALO DIA DEL PADRE | EZ5: DESCUENTOS DE EPS | FA5: DESCUENTO ONCOLOGICO | FB5: DESCUENTO CELULAR | FC5: ADELANTO QUINCENAL | FD5: ESSALUD +VIDA | FE5: ADELANTO | FF5: ADELANTO DE VACACIONES | FG5: ADELANTO VACACIONES | FH5: PRESTAMO | FI5: ADELANTO DE GRATIFICACION | FJ5: DESC DE GRATIF | FK5: OTROS DESCUENTOS | FL5: ADELANTO UTILIDAD CONVENCIONAL | FM5: OBSEQUIO POR HALLOWEEN | FN5: ADELANTO DE ALIMENTACIÓN | FO5: DESCUENTO DE ALIMENTACIÓN TRABAJADOR | FP5: ADELANTO AGUINALDO | GE5: RM AFECTA UTILIDADES
A6: BCP | B6: 1 | C6: ENERO | D6: DNI | E6: 45813056 | F6: ALFARO VILLACORTA VICTOR HUGO GARY | G6: 32348 | H6: OPERACIONES PORTUARIAS | I6: MAGDALENA | J6: 01OFP | K6: OFICINA PRINCIPAL | L6: 100002 | M6: Agenciamiento Marítimo | N6: 1 | O6: 001OP | P6: OPERACIONES | Q6: 1 | R6: 004OPP | S6: OPERACIONES PORTUARIAS | T6: EMPLEADO | U6: JEFE DE OPERACIONES | V6: INDETERMINADO | W6: CONFIANZA | X6: BANCO DE CREDITO | Y6: 19307189164080 | AB6: 42948 | AE6: INTEGRA | AF6: 623461VAVAL7 | AL6: 380 | AO6: SI | AP6: M | AQ6: NO | AR6: 9540 | AS6: 12 | AT6: 0 | AU6: 18 | BI6: 0 | BK6: 0 | BL6: 0 | BM6: 0 | BN6: 0 | BO6: 0 | BP6: 96 | BQ6: 3816 | BR6: 0 | BS6: 0 | BT6: 6429 | BU6: 0 | BV6: 0 | BW6: 0 | BX6: 380 | CB6: 0 | CC6: 0 | CD6: 0 | CF6: 0 | CH6: 0 | CO6: 0 | CV6: 0 | EL6: 10625 | EM6: 10625 | EN6: 1062.5 | EO6: 164.69 | EP6: 145.56 | EQ6: 0 | ER6: 0 | ES6: 0 | ET6: 1073.45 | EU6: 0 | EV6: 0 | EZ6: 0 | FA6: 45.67 | FB6: 0 | FC6: 3968 | FH6: 1855 | FN6: 0 | FO6: 0 | FQ6: 8314.87 | FR6: 2310.13 | FS6: 2310.13 | FU6: 2310.13 | FV6: 2162.6 | FW6: 0 | FX6: 956.25 | FY6: 0 | GB6: =+EL6-BZ6-CA6-GC6 -> 0 | GC6: 10625 | GE6: =+GC6+DF6+CX6+EH6 -> 10625
A7: BCP | B7: 2 | C7: ENERO | D7: DNI | E7: 09335023 | F7: AYOS JUNGBLUTH MARIANA | G7: 25197 | H7: COMERCIAL | I7: OFICINA PRINCIPAL | J7: 01OFP | K7: OFICINA PRINCIPAL | L7: 100001 | M7: Agenciamiento General | N7: 1 | O7: 003VE | P7: VENTAS | Q7: 1 | R7: 006VEN | S7: COMERCIAL- VENTAS | T7: EMPLEADO | U7: ASESOR COMERCIAL EXPO | V7: INDETERMINADO | X7: BANCO DE CREDITO | Y7: 191-39024898-0-87 | AB7: 43003 | AE7: INTEGRA | AF7: 251950MAJSG6 | AO7: SI | AP7: F | AQ7: NO | AR7: 12000 | AS7: 30 | AT7: 0 | AU7: 0 | BI7: 0 | BK7: 0 | BL7: 0 | BM7: 0 | BN7: 0 | BO7: 0 | BP7: 240 | BQ7: 12000 | BR7: 0 | BS7: 0 | BT7: 0 | BU7: 0 | BV7: 0 | BW7: 0 | CB7: 0 | CC7: 0 | CD7: 0 | CF7: 0 | CH7: 0 | CO7: 0 | CV7: 0 | EL7: 12000 | EM7: 12000 | EN7: 1200 | EO7: 186 | EP7: 164.4 | EQ7: 0 | ER7: 0 | ES7: 0 | ET7: 1471.16 | EU7: 0 | EV7: 0 | EZ7: 99.59 | FA7: 141.03 | FB7: 62.8 | FC7: 4800 | FH7: 0 | FN7: 0 | FO7: 0 | FQ7: 8124.98 | FR7: 3875.02 | FS7: 3875.02 | FU7: 3875.02 | FV7: 3788.08 | FW7: 0 | FX7: 1080 | FY7: 0 | GB7: =+EL7-BZ7-CA7-GC7 -> 0 | GC7: 12000 | GE7: =+GC7+DF7+CX7+EH7 -> 12000
A8: BCP | B8: 3 | C8: ENERO | D8: DNI | E8: 47472407 | F8: BARRANZUELA SANTOS MELISSA ANTONED | G8: 33606 | H8: COBRANZAS Y FACTURACIÓN | I8: OFICINA PRINCIPAL | J8: 01OFP | K8: OFICINA PRINCIPAL | L8: 100001 | M8: Agenciamiento General | N8: 1 | O8: 002AD | P8: ADMINISTRACION | Q8: 1 | R8: 011COB | S8: COBRANZAS | T8: EMPLEADO | U8: Analista de Cobranza y Facturacion | V8: INDETERMINADO | X8: BCP | Y8: 191-71058934-0-99 | AB8: 43374 | AE8: PRIMA MIXTA | AF8: 636040MBSRT5 | AO8: SI | AP8: F | AQ8: NO | AR8: 3200 | AS8: 24 | AT8: 0 | AU8: 6 | BI8: 0 | BK8: 0 | BL8: 0 | BM8: 0 | BN8: 0 | BO8: 0 | BP8: 192 | BQ8: 2560 | BR8: 0 | BS8: 0 | BT8: 640 | BU8: 0 | BV8: 0 | BW8: 0 | CB8: 0 | CC8: 0 | CD8: 0 | CF8: 0 | CH8: 0 | CO8: 0 | CV8: 0 | EL8: 3200 | EM8: 3200 | EN8: 320 | EO8: 0 | EP8: 43.84 | EQ8: 0 | ER8: 0 | ES8: 0 | ET8: 51.88 | EU8: 0 | EV8: 0 | EZ8: 0 | FA8: 0 | FB8: 0 | FC8: 1280 | FH8: 0 | FN8: 0 | FO8: 0 | FQ8: 1695.72 | FR8: 1504.28 | FS8: 1504.28 | FU8: 1504.28 | FV8: 1328.88 | FW8: 0 | FX8: 288 | FY8: 0 | GB8: =+EL8-BZ8-CA8-GC8 -> 0 | GC8: 3200 | GE8: =+GC8+DF8+CX8+EH8 -> 3200
A9: BCP | B9: 4 | C9: ENERO | D9: DNI | E9: 09410158 | F9: BONATTI CARRASCO JORGE LUIS | G9: 24997 | H9: DOCUMENTACIÓN Y VISTO BUENO | I9: MAGDALENA | J9: 01OFP | K9: OFICINA PRINCIPAL | L9: 100002 | M9: Agenciamiento Marítimo | N9: 1 | O9: 001OP | P9: OPERACIONES | Q9: 0 | R9: 003DVB | S9: DOCUMENTACION-VISTO BUENO | T9: EMPLEADO | U9: ANALISTA SENIOR DE DOCUMENTACIÓN | V9: INDETERMINADO | X9: BANCO DE CREDITO | Y9: 191-38538700-0-78 | AB9: 42985 | AE9: INTEGRA | AF9: 249951JBCAR8 | AO9: SI | AP9: M | AQ9: SI | AR9: 4600 | AS9: 30 | AT9: 0 | AU9: 0 | BI9: 9 | BK9: 0 | BL9: 0 | BM9: 0 | BN9: 0 | BO9: 0 | BP9: 240 | BQ9: 4600 | BR9: 113 | BS9: 0 | BT9: 0 | BU9: 0 | BV9: 0 | BW9: 0 | CB9: 0 | CC9: 0 | CD9: 353.475 | CF9: 0 | CH9: 0 | CO9: 0 | CV9: 0 | EL9: 5066.475 | EM9: 5066.475 | EN9: 506.65 | EO9: 78.53 | EP9: 69.41 | EQ9: 0 | ER9: 0 | ES9: 0 | ET9: 257.4965 | EU9: 0 | EV9: 0 | EZ9: 294.09 | FA9: 325.29 | FB9: 0 | FC9: 1885.2 | FD9: 5 | FH9: 0 | FN9: 0 | FO9: 0 | FQ9: 3421.67 | FR9: 1644.81 | FS9: 1644.81 | FU9: 1644.81 | FV9: 1229.95 | FW9: 0 | FX9: 455.98 | FY9: 0 | GB9: =+EL9-BZ9-CA9-GC9 -> -0.005 | GC9: 5066.48 | GE9: =+GC9+DF9+CX9+EH9 -> 5066.48
A10: BCP | B10: 5 | C10: ENERO | D10: DNI | E10: 48588627 | F10: CARRERA RAMIREZ KATTYA HELEN | G10: 34886 | H10: CONTROL DE EQUIPOS | I10: OFICINA PRINCIPAL | J10: 01OFP | K10: OFICINA PRINCIPAL | L10: 100002 | M10: Agenciamiento Marítimo | N10: 0 | O10: 001OP | P10: OPERACIONES | Q10: 0 | R10: 005CEQ | S10: CONTROL DE EQUIPOS | T10: EMPLEADO | U10: ASISTENTE DE CONTROL DE EQUIPOS | V10: INDETERMINADO | X10: BANCO DE CREDITO | Y10: 191-39405207-0-38 | AB10: 43243 | AE10: PRIMA MIXTA | AF10: 648840KCRRI5 | AO10: SI | AP10: F | AQ10: SI | AR10: 2500 | AS10: 9 | AT10: 0 | AU10: 0 | AY10: 21 | BI10: 0 | BK10: 0 | BL10: 0 | BM10: 0 | BN10: 0 | BO10: 0 | BP10: 72 | BQ10: 750 | BR10: 113 | BS10: 0 | BT10: 0 | BU10: 0 | BV10: 0 | BW10: 0 | BZ10: 1823.8541 | CB10: 0 | CC10: 0 | CD10: 0 | CF10: 0 | CH10: 0 | CO10: 0 | CV10: 0 | EL10: 2686.8541 | EM10: 2686.8541 | EN10: 268.69 | EO10: 0 | EP10: 36.81 | EQ10: 0 | ER10: 0 | ES10: 0 | ET10: 0 | EU10: 0 | EV10: 0 | EZ10: 115.71 | FA10: 64.72 | FB10: 0 | FC10: 1045.2 | FH10: 0 | FN10: 0 | FO10: 0 | FQ10: 1531.13 | FR10: 1155.72 | FS10: 1155.72 | FU10: 1155.72 | FV10: 1082.27 | FW10: 0 | FX10: 77.67 | FY10: 0 | GB10: =+EL10-BZ10-CA10-GC10 -> 0 | GC10: 863 | GE10: =+GC10+DF10+CX10+EH10 -> 863
A11: BCP | B11: 6 | C11: ENERO | D11: DNI | E11: 09542822 | F11: CAVERO RODRIGUEZ JANNYE VERONICA | G11: 26663 | H11: COMERCIAL | I11: OFICINA PRINCIPAL | J11: 01OFP | K11: OFICINA PRINCIPAL | L11: 100001 | M11: Agenciamiento General | N11: 1 | O11: 003VE | P11: VENTAS | Q11: 1 | R11: 006VEN | S11: COMERCIAL- VENTAS | T11: EMPLEADO | U11: CUSTOMER SERVICE SENIOR EXPO | V11: INDETERMINADO | X11: BANCO DE CREDITO | Y11: 191-38538707-0-85 | AB11: 42985 | AE11: PROFUTURO | AF11: 566610JCRER0 | AO11: SI | AP11: F | AQ11: SI | AR11: 8500 | AS11: 30 | AT11: 0 | AU11: 0 | BI11: 0 | BK11: 0 | BL11: 0 | BM11: 0 | BN11: 0 | BO11: 0 | BP11: 240 | BQ11: 8500 | BR11: 113 | BS11: 0 | BT11: 0 | BU11: 0 | BV11: 0 | BW11: 0 | CB11: 0 | CC11: 0 | CD11: 0 | CF11: 0 | CH11: 0 | CO11: 0 | CV11: 0 | EL11: 8613 | EM11: 8613 | EN11: 861.3 | EO11: 145.56 | EP11: 118 | EQ11: 0 | ER11: 0 | ES11: 0 | ET11: 849.69 | EU11: 0 | EV11: 0 | EZ11: 160.81 | FA11: 162.77 | FB11: 0 | FC11: 3445.2 | FH11: 0 | FN11: 0 | FO11: 0 | FQ11: 5743.33 | FR11: 2869.67 | FS11: 2869.67 | FU11: 2869.67 | FV11: 2751.17 | FW11: 0 | FX11: 775.17 | FY11: 0 | GB11: =+EL11-BZ11-CA11-GC11 -> 0 | GC11: 8613 | GE11: =+GC11+DF11+CX11+EH11 -> 8613
A12: BCP | B12: 7 | C12: ENERO | D12: DNI | E12: 07262343 | F12: CIEZA AGUILAR CESAR AUGUSTO | G12: 25690 | H12: ADMINISTRACIÓN | I12: OFICINA PRINCIPAL | J12: 01OFP | K12: OFICINA PRINCIPAL | L12: 100001 | M12: Agenciamiento General | N12: 1 | O12: 002AD | P12: ADMINISTRACION | Q12: 1 | R12: 012ADM | S12: ADMINISTRACION | T12: EMPLEADO | U12: CHOFER | V12: INDETERMINADO | X12: BCP | Y12: 19307012280010 | AB12: 43357 | AE12: INTEGRA MIXTA | AF12: 556881CCAZI0 | AO12: SI | AP12: M | AQ12: SI | AR12: 2650 | AS12: 30 | AT12: 0 | AU12: 0 | BI12: 0 | BK12: 6 | BL12: 17 | BM12: 9 | BN12: 0 | BO12: 0 | BP12: 240 | BQ12: 2650 | BR12: 113 | BS12: 0 | BT12: 0 | BU12: 0 | BV12: 0 | BW12: 0 | CB12: 0 | CC12: 0 | CD12: 0 | CF12: 0 | CH12: 0 | CO12: 557.78062 | CV12: 0 | EL12: 3320.7806 | EM12: 3320.7806 | EN12: 332.08 | EO12: 0 | EP12: 45.49 | EQ12: 0 | ER12: 0 | ES12: 0 | ET12: 56.64245 | EU12: 0 | EV12: 0 | EZ12: 115.71 | FA12: 0 | FB12: 0 | FC12: 1105.2 | FH12: 500 | FN12: 0 | FO12: 0 | FQ12: 2155.12 | FR12: 1165.66 | FS12: 1165.66 | FU12: 1165.66 | FV12: 1776.32 | FW12: 0 | FX12: 298.87 | FY12: 0 | GB12: =+EL12-BZ12-CA12-GC12 -> 0.000625 | GC12: 3320.78 | GE12: =+GC12+DF12+CX12+EH12 -> 3320.78
A13: BCP | B13: 8 | C13: ENERO | D13: DNI | E13: 40537272 | F13: GARRIDO LEON CARLA VERONICA | G13: 29363 | H13: COMERCIAL | I13: OFICINA PRINCIPAL | J13: 01OFP | K13: OFICINA PRINCIPAL | L13: 100001 | M13: Agenciamiento General | N13: 1 | O13: 003VE | P13: VENTAS | Q13: 1 | R13: 006VEN | S13: COMERCIAL- VENTAS | T13: EMPLEADO | U13: ASESOR COMERCIAL EXPORTACIÓN | V13: INDETERMINADO | X13: BANCO DE CREDITO | Y13: 191-38538716-0-94 | AB13: 42985 | AE13: PROFUTURO | AF13: 593611CGLRN2 | AO13: SI | AP13: F | AQ13: SI | AR13: 10000 | AS13: 28 | AT13: 0 | AU13: 2 | BI13: 0 | BK13: 0 | BL13: 0 | BM13: 0 | BN13: 0 | BO13: 0 | BP13: 224 | BQ13: 9333.3333 | BR13: 113 | BS13: 0 | BT13: 674.2 | BU13: 0 | BV13: 0 | BW13: 0 | CB13: 0 | CC13: 0 | CD13: 0 | CF13: 0 | CH13: 0 | CO13: 0 | CV13: 0 | EL13: 10120.533 | EM13: 10120.533 | EN13: 1012.05 | EO13: 171.04 | EP13: 138.65 | EQ13: 0 | ER13: 0 | ES13: 0 | ET13: 1097.14 | EU13: 0 | EV13: 0 | EZ13: 185.17 | FA13: 0 | FB13: 0 | FC13: 4045.2 | FH13: 0 | FN13: 0 | FO13: 0 | FQ13: 6649.25 | FR13: 3471.28 | FS13: 3471.28 | FU13: 3471.28 | FV13: 3409.52 | FW13: 0 | FX13: 910.85 | FY13: 0 | GB13: =+EL13-BZ13-CA13-GC13 -> 0.0033333333 | GC13: 10120.53 | GE13: =+GC13+DF13+CX13+EH13 -> 10120.53
A14: BCP | B14: 9 | C14: ENERO | D14: DNI | E14: 25710966 | F14: GIURIA CONSTANTINO HUMBERTO ANDRES | G14: 26055 | H14: COORDINADOR DE DOCUMENTACIÓN | I14: MAGDALENA | J14: 01OFP | K14: OFICINA PRINCIPAL | L14: 100002 | M14: Agenciamiento Marítimo | N14: 1 | O14: 001OP | P14: OPERACIONES | Q14: 0 | R14: 003DVB | S14: DOCUMENTACION-VISTO BUENO | T14: EMPLEADO | U14: JEFE DE DOCUMENTACIÓN Y VISTO BUENO | V14: INDETERMINADO | W14: CONFIANZA | X14: BANCO DE CREDITO | Y14: 191-38538688-0-65 | AB14: 42985 | AE14: INTEGRA | AF14: 560531HGCRS0 | AO14: SI | AP14: M | AQ14: SI | AR14: 7000 | AS14: 30 | AT14: 0 | AU14: 0 | BI14: 5.5 | BK14: 0 | BL14: 0 | BM14: 10.5 | BN14: 0 | BO14: 0 | BP14: 240 | BQ14: 7000 | BR14: 113 | BS14: 0 | BT14: 0 | BU14: 0 | BV14: 0 | BW14: 0 | CB14: 0 | CC14: 0 | CD14: 326.0125 | CF14: 0 | CH14: 0 | CO14: 622.3875 | CV14: 0 | EL14: 8061.4 | EM14: 8061.4 | EN14: 806.14 | EO14: 124.95 | EP14: 110.44 | EQ14: 0 | ER14: 0 | ES14: 0 | ET14: 739.036 | EU14: 0 | EV14: 0 | EZ14: 204.9 | FA14: 0 | FB14: 0 | FC14: 2845.2 | FH14: 0 | FN14: 0 | FO14: 0 | FQ14: 4830.67 | FR14: 3230.73 | FS14: 3230.73 | FU14: 3230.73 | FV14: 3014.08 | FW14: 0 | FX14: 725.53 | FY14: 0 | GB14: =+EL14-BZ14-CA14-GC14 -> 0 | GC14: 8061.4 | GE14: =+GC14+DF14+CX14+EH14 -> 8061.4
A15: BCP | B15: 10 | C15: ENERO | D15: DNI | E15: 08693248 | F15: IZARRA CARRASCO IRINA KAREM | G15: 25577 | H15: DOCUMENTACIÓN Y VISTO BUENO | I15: MAGDALENA | J15: 01OFP | K15: OFICINA PRINCIPAL | L15: 100002 | M15: Agenciamiento Marítimo | N15: 1 | O15: 001OP | P15: OPERACIONES | Q15: 0 | R15: 003DVB | S15: DOCUMENTACION-VISTO BUENO | T15: EMPLEADO | U15: ANALISTA SENIOR DE DOCUMENTACIÓN | V15: INDETERMINADO | X15: BANCO DE CREDITO | Y15: 191-40176840-0-65 | AB15: 43160 | AE15: PRIMA | AF15: 255750IICRR1 | AP15: F | AQ15: SI | AR15: 5000 | AS15: 30 | AT15: 0 | AU15: 0 | BI15: 0 | BK15: 0 | BL15: 0 | BM15: 0 | BN15: 0 | BO15: 0 | BP15: 240 | BQ15: 5000 | BR15: 113 | BS15: 0 | BT15: 0 | BU15: 0 | BV15: 0 | BW15: 0 | CB15: 0 | CC15: 0 | CD15: 0 | CF15: 0 | CH15: 0 | CO15: 0 | CV15: 0 | EL15: 5113 | EM15: 5113 | EN15: 511.3 | EO15: 81.81 | EP15: 70.05 | EQ15: 0 | ER15: 0 | ES15: 0 | ET15: 275.19 | EU15: 0 | EV15: 0 | EZ15: 0 | FA15: 0 | FB15: 0 | FC15: 2045.2 | FH15: 0 | FN15: 0 | FO15: 0 | FQ15: 2983.55 | FR15: 2129.45 | FS15: 2129.45 | FU15: 2129.45 | FV15: 1915.02 | FW15: 0 | FX15: 460.17 | FY15: 0 | GB15: =+EL15-BZ15-CA15-GC15 -> 0 | GC15: 5113 | GE15: =+GC15+DF15+CX15+EH15 -> 5113
A16: BCP | B16: 11 | C16: ENERO | D16: DNI | E16: 43426313 | F16: LOPEZ MENDOZA GIULIANA JANNET | G16: 31251 | H16: DOCUMENTACIÓN Y VISTO BUENO | I16: OFICINA PAITA | J16: 05PAI | K16: PAITA | L16: 100002 | M16: Agenciamiento Marítimo | N16: 1 | O16: 001OP | P16: OPERACIONES | Q16: 0 | R16: 003DVB | S16: DOCUMENTACION-VISTO BUENO | T16: EMPLEADO | U16: ANALISTA DE DOCUMENTACIÓN Y VISTO BUENO | V16: INDETERMINADO | X16: BANCO DE CREDITO | Y16: 45594366852089 | AB16: 43206 | AE16: ONP | AP16: F | AQ16: SI | AR16: 4000 | AS16: 30 | AT16: 0 | AU16: 0 | BI16: 6 | BK16: 0 | BL16: 0 | BM16: 0 | BN16: 0 | BO16: 0 | BP16: 240 | BQ16: 4000 | BR16: 113 | BS16: 0 | BT16: 0 | BU16: 0 | BV16: 0 | BW16: 0 | CB16: 0 | CC16: 0 | CD16: 205.65 | CF16: 0 | CH16: 0 | CO16: 0 | CV16: 0 | EL16: 4318.65 | EM16: 4318.65 | EN16: 0 | EO16: 0 | EP16: 0 | EQ16: 0 | ER16: 0 | ES16: 561.42 | ET16: 156.102 | EU16: 0 | EV16: 0 | EZ16: 0 | FA16: 0 | FB16: 0 | FC16: 1645.2 | FH16: 0 | FN16: 0 | FO16: 0 | FQ16: 2362.72 | FR16: 1955.93 | FS16: 1955.93 | FU16: 1955.93 | FV16: 1900.99 | FW16: 0 | FX16: 388.68 | FY16: 0 | GB16: =+EL16-BZ16-CA16-GC16 -> 0 | GC16: 4318.65 | GE16: =+GC16+DF16+CX16+EH16 -> 4318.65
A17: BCP | B17: 12 | C17: ENERO | D17: DNI | E17: 42168737 | F17: MARTINEZ MURAYARI DE PEREZ INES ROXANA | G17: 30662 | H17: COMERCIAL | I17: OFICINA PRINCIPAL | J17: 01OFP | K17: OFICINA PRINCIPAL | L17: 100001 | M17: Agenciamiento General | N17: 1 | O17: 003VE | P17: VENTAS | Q17: 1 | R17: 006VEN | S17: COMERCIAL- VENTAS | T17: EMPLEADO | U17: CUSTOMER SERVICE IMPO | V17: INDETERMINADO | X17: INTERBANK | Y17: 003-201-013149741606-18 | AB17: 43252 | AE17: PROFUTURO MIXTA | AF17: 606600IMMTA5 | AO17: SI | AP17: F | AQ17: SI | AR17: 4300 | AS17: 30 | AT17: 0 | AU17: 0 | BI17: 0 | BK17: 0 | BL17: 0 | BM17: 0 | BN17: 0 | BO17: 0 | BP17: 240 | BQ17: 4300 | BR17: 113 | BS17: 0 | BT17: 0 | BU17: 0 | BV17: 0 | BW17: 0 | CB17: 0 | CC17: 0 | CD17: 0 | CF17: 0 | CH17: 0 | CO17: 0 | CV17: 0 | EL17: 4413 | EM17: 4413 | EN17: 441.3 | EO17: 0 | EP17: 60.46 | EQ17: 0 | ER17: 0 | ES17: 0 | ET17: 166.19 | EU17: 0 | EV17: 0 | EZ17: 347.13 | FA17: 91.95 | FB17: 0 | FC17: 1765.2 | FH17: 0 | FN17: 0 | FO17: 0 | FQ17: 2872.23 | FR17: 1540.77 | FS17: 1540.77 | FU17: 1540.77 | FV17: 1552.84 | FW17: 0 | FX17: 397.17 | FY17: 0 | GB17: =+EL17-BZ17-CA17-GC17 -> 0 | GC17: 4413 | GE17: =+GC17+DF17+CX17+EH17 -> 4413
A18: BCP | B18: 13 | C18: ENERO | D18: DNI | E18: 40508445 | F18: MEJIA CAVERO PAOLA CECILIA | G18: 29312 | H18: CONTROL DE EQUIPOS | I18: OFICINA PRINCIPAL | J18: 01OFP | K18: OFICINA PRINCIPAL | L18: 100002 | M18: Agenciamiento Marítimo | N18: 0 | O18: 001OP | P18: OPERACIONES | Q18: 0 | R18: 005CEQ | S18: CONTROL DE EQUIPOS | T18: EMPLEADO | U18: ANALISTA SENIOR DE CONTROL DE EQUIPOS | V18: INDETERMINADO | X18: BANCO DE CREDITO | Y18: 191-38538727-0-05 | AB18: 42985 | AE18: INTEGRA | AF18: 593100PMCIE0 | AP18: F | AQ18: SI | AR18: 5040 | AS18: 25 | AT18: 0 | AU18: 5 | BI18: 1.5 | BK18: 0 | BL18: 0 | BM18: 5 | BN18: 0 | BO18: 0 | BP18: 200 | BQ18: 4200 | BR18: 113 | BS18: 0 | BT18: 891.57 | BU18: 0 | BV18: 0 | BW18: 0 | CB18: 0 | CC18: 0 | CD18: 64.4125 | CF18: 0 | CH18: 0 | CO18: 214.70833 | CV18: 0 | EL18: 5483.6908 | EM18: 5483.6908 | EN18: 548.37 | EO18: 85 | EP18: 75.13 | EQ18: 0 | ER18: 0 | ES18: 0 | ET18: 322.67692 | EU18: 0 | EV18: 0 | EZ18: 0 | FA18: 105.48 | FB18: 0 | FC18: 2061.2 | FH18: 0 | FN18: 0 | FO18: 0 | FQ18: 3197.86 | FR18: 2285.83 | FS18: 2285.83 | FU18: 2285.83 | FV18: 1918.55 | FW18: 0 | FX18: 493.53 | FY18: 0 | GB18: =+EL18-BZ18-CA18-GC18 -> 0.00083333333 | GC18: 5483.69 | GE18: =+GC18+DF18+CX18+EH18 -> 5483.69
A19: BCP | B19: 14 | C19: ENERO | D19: DNI | E19: 47806538 | F19: RAMIREZ ALBINAGORTA ENRIQUE ALEJANDRO | G19: 34101 | H19: DOCUMENTACIÓN Y VISTO BUENO | I19: OFICINA PAITA | J19: 05PAI | K19: PAITA | L19: 100002 | M19: Agenciamiento Marítimo | N19: 1 | O19: 001OP | P19: OPERACIONES | Q19: 0 | R19: 003DVB | S19: DOCUMENTACION-VISTO BUENO | T19: EMPLEADO | U19: ASISTENTE DE DOCUMENTACIÓN | V19: INDETERMINADO | X19: BANCO DE CREDITO | Y19: 45537717056073 | AB19: 43402 | AE19: PRIMA MIXTA | AF19: 340991ERAII7 | AO19: SI | AP19: M | AQ19: NO | AR19: 2600 | AS19: 30 | AT19: 0 | AU19: 0 | BI19: 0 | BK19: 0 | BL19: 0 | BM19: 5.5 | BN19: 0 | BO19: 0 | BP19: 240 | BQ19: 2600 | BR19: 0 | BS19: 0 | BT19: 0 | BU19: 0 | BV19: 0 | BW19: 0 | CB19: 0 | CC19: 0 | CD19: 0 | CF19: 0 | CH19: 0 | CO19: 119.16667 | CV19: 0 | EL19: 2719.1667 | EM19: 2719.1667 | EN19: 271.92 | EO19: 0 | EP19: 37.25 | EQ19: 0 | ER19: 0 | ES19: 0 | ET19: 0 | EU19: 0 | EV19: 0 | EZ19: 0 | FA19: 0 | FB19: 0 | FC19: 1040 | FH19: 0 | FN19: 0 | FO19: 0 | FQ19: 1349.17 | FR19: 1370 | FS19: 1370 | FU19: 1370 | FV19: 1062.09 | FW19: 0 | FX19: 244.73 | FY19: 0 | GB19: =+EL19-BZ19-CA19-GC19 -> -0.0033333333 | GC19: 2719.17 | GE19: =+GC19+DF19+CX19+EH19 -> 2719.17
A20: BCP | B20: 15 | C20: ENERO | D20: DNI | E20: 47668422 | F20: ROMAN PINTADO JULLISA IVETTE | G20: 33735 | H20: DOCUMENTACIÓN Y VISTO BUENO | I20: OFICINA PAITA | J20: 05PAI | K20: PAITA | L20: 100002 | M20: Agenciamiento Marítimo | N20: 1 | O20: 001OP | P20: OPERACIONES | Q20: 0 | R20: 003DVB | S20: DOCUMENTACION-VISTO BUENO | T20: EMPLEADO | U20: ASISTENTE SENIOR DE DOCUMENTACIÓN | V20: INDETERMINADO | X20: BBVA | Y20: 01105700021558705472 | AB20: 43160 | AE20: ONP | AO20: SI | AP20: F | AQ20: SI | AR20: 3200 | AS20: 30 | AT20: 0 | AU20: 0 | BI20: 0 | BK20: 0 | BL20: 0 | BM20: 0 | BN20: 0 | BO20: 0 | BP20: 240 | BQ20: 3200 | BR20: 113 | BS20: 0 | BT20: 0 | BU20: 0 | BV20: 0 | BW20: 0 | CB20: 0 | CC20: 0 | CD20: 0 | CF20: 0 | CH20: 0 | CO20: 0 | CV20: 0 | EL20: 3313 | EM20: 3313 | EN20: 0 | EO20: 0 | EP20: 0 | EQ20: 0 | ER20: 0 | ES20: 430.69 | ET20: 62.53 | EU20: 0 | EV20: 0 | EZ20: 115.71 | FA20: 0 | FB20: 0 | FC20: 1325.2 | FH20: 0 | FN20: 0 | FO20: 0 | FQ20: 1934.13 | FR20: 1378.87 | FS20: 1378.87 | FU20: 1378.87 | FV20: 1603.58 | FW20: 0 | FX20: 298.17 | FY20: 0 | GB20: =+EL20-BZ20-CA20-GC20 -> 0 | GC20: 3313 | GE20: =+GC20+DF20+CX20+EH20 -> 3313
A21: BCP | B21: 16 | C21: ENERO | D21: DNI | E21: 10346719 | F21: ROMERO ORDOÑEZ EDUARDO ARTURO | G21: 28257 | H21: DOCUMENTACIÓN Y VISTO BUENO | I21: MAGDALENA | J21: 01OFP | K21: OFICINA PRINCIPAL | L21: 100002 | M21: Agenciamiento Marítimo | N21: 1 | O21: 001OP | P21: OPERACIONES | Q21: 0 | R21: 003DVB | S21: DOCUMENTACION-VISTO BUENO | T21: EMPLEADO | U21: ANALISTA DE DOCUMENTACIÓN | V21: INDETERMINADO | X21: BANCO DE CREDITO | Y21: 193-39429501-0-77 | AB21: 43070 | AE21: PROFUTURO | AF21: 582551EROEO4 | AP21: M | AQ21: SI | AR21: 4000 | AS21: 30 | AT21: 0 | AU21: 0 | BI21: 5 | BK21: 0 | BL21: 0 | BM21: 10 | BN21: 0 | BO21: 0 | BP21: 240 | BQ21: 4000 | BR21: 113 | BS21: 0 | BT21: 0 | BU21: 0 | BV21: 0 | BW21: 0 | CB21: 0 | CC21: 0 | CD21: 171.375 | CF21: 0 | CH21: 0 | CO21: 342.75 | CV21: 0 | EL21: 4627.125 | EM21: 4627.125 | EN21: 462.71 | EO21: 78.2 | EP21: 63.39 | EQ21: 0 | ER21: 0 | ES21: 0 | ET21: 181.52 | EU21: 0 | EV21: 0 | EZ21: 0 | FA21: 0 | FB21: 0 | FC21: 1645.2 | FH21: 0 | FN21: 0 | FO21: 0 | FQ21: 2431.02 | FR21: 2196.11 | FS21: 2196.11 | FU21: 2196.11 | FV21: 1668.93 | FW21: 0 | FX21: 416.44 | FY21: 0 | GB21: =+EL21-BZ21-CA21-GC21 -> -0.005 | GC21: 4627.13 | GE21: =+GC21+DF21+CX21+EH21 -> 4627.13
A22: BCP | B22: 17 | C22: ENERO | D22: DNI | E22: 10725704 | F22: RONCEROS GONZALES LUISA MARILIN | G22: 28453 | H22: ADMINISTRACIÓN | I22: OFICINA PRINCIPAL | J22: 01OFP | K22: OFICINA PRINCIPAL | L22: 100001 | M22: Agenciamiento General | N22: 1 | O22: 002AD | P22: ADMINISTRACION | Q22: 1 | R22: 012ADM | S22: ADMINISTRACION | T22: EMPLEADO | U22: JEFE DE ADMINISTRACIÓN Y CONTROL | V22: INDETERMINADO | W22: CONFIANZA | X22: BANCO DE CREDITO | Y22: 191-21585152-0-82 | AB22: 43382 | AE22: PRIMA | AF22: 584510LRGCZ4 | AO22: SI | AP22: F | AQ22: SI | AR22: 8000 | AS22: 30 | AT22: 0 | AU22: 0 | BI22: 0 | BK22: 0 | BL22: 0 | BM22: 0 | BN22: 0 | BO22: 0 | BP22: 240 | BQ22: 8000 | BR22: 113 | BS22: 0 | BT22: 0 | BU22: 0 | BV22: 0 | BW22: 0 | CB22: 0 | CC22: 0 | CD22: 0 | CF22: 0 | CH22: 9 | CO22: 0 | CV22: 0 | EL22: 8122 | EM22: 8122 | EN22: 812.2 | EO22: 129.95 | EP22: 111.27 | EQ22: 0 | ER22: 0 | ES22: 0 | ET22: 768.53 | EU22: 0 | EV22: 0 | EZ22: 115.71 | FA22: 116.01 | FB22: 22.7 | FC22: 3245.2 | FH22: 0 | FN22: 9 | FO22: 4 | FQ22: 5334.57 | FR22: 2787.43 | FS22: 2787.43 | FU22: 2787.43 | FV22: 2807.28 | FW22: 0 | FX22: 730.98 | FY22: 0 | GB22: =+EL22-BZ22-CA22-GC22 -> 0 | GC22: 8122 | GE22: =+GC22+DF22+CX22+EH22 -> 8122
A23: BCP | B23: 18 | C23: ENERO | D23: DNI | E23: 09867320 | F23: ROTALDE DEL RIO XIMENA MARIA | G23: 26321 | H23: CONTROL DE EQUIPOS | I23: OFICINA PRINCIPAL | J23: 01OFP | K23: OFICINA PRINCIPAL | L23: 100002 | M23: Agenciamiento Marítimo | N23: 0 | O23: 001OP | P23: OPERACIONES | Q23: 0 | R23: 005CEQ | S23: CONTROL DE EQUIPOS | T23: EMPLEADO | U23: JEFE DE CONTROL DE EQUIPOS | V23: INDETERMINADO | W23: CONFIANZA | X23: BANCO DE CREDITO | Y23: 191-38538673-0-50 | AB23: 42985 | AE23: INTEGRA | AF23: 563190XRRAO4 | AO23: SI | AP23: F | AQ23: SI | AR23: 11500 | AS23: 30 | AT23: 0 | AU23: 0 | BI23: 6 | BK23: 0 | BL23: 0 | BM23: 0 | BN23: 0 | BO23: 0 | BP23: 240 | BQ23: 11500 | BR23: 113 | BS23: 0 | BT23: 0 | BU23: 0 | BV23: 0 | BW23: 0 | CB23: 0 | CC23: 0 | CD23: 580.65 | CF23: 0 | CH23: 0 | CO23: 0 | CV23: 0 | EL23: 12193.65 | EM23: 12193.65 | EN23: 1219.37 | EO23: 189 | EP23: 164.78 | EQ23: 0 | ER23: 0 | ES23: 0 | ET23: 1495.3005 | EU23: 0 | EV23: 0 | EZ23: 0 | FA23: 0 | FB23: 0 | FC23: 4645.2 | FH23: 0 | FN23: 0 | FO23: 0 | FQ23: 7713.65 | FR23: 4480 | FS23: 4480 | FU23: 4480 | FV23: 3997.85 | FW23: 0 | FX23: 1097.43 | FY23: 0 | GB23: =+EL23-BZ23-CA23-GC23 -> 0 | GC23: 12193.65 | GE23: =+GC23+DF23+CX23+EH23 -> 12193.65
A24: BCP | B24: 19 | C24: ENERO | D24: DNI | E24: 08887801 | F24: RUIZ SALCEDO MARIA DE LOURDES | G24: 27152 | H24: COMERCIAL | I24: OFICINA PRINCIPAL | J24: 01OFP | K24: OFICINA PRINCIPAL | L24: 100001 | M24: Agenciamiento General | N24: 1 | O24: 003VE | P24: VENTAS | Q24: 1 | R24: 006VEN | S24: COMERCIAL- VENTAS | T24: EMPLEADO | U24: ASESOR COMERCIAL IMPO | V24: INDETERMINADO | X24: BANCO DE CREDITO | Y24: 191-39024915-0-05 | AB24: 43003 | AE24: HABITAT | AF24: 271500MRSZC2 | AO24: SI | AP24: F | AQ24: SI | AR24: 12000 | AS24: 26 | AT24: 0 | AU24: 4 | BI24: 0 | BK24: 0 | BL24: 0 | BM24: 0 | BN24: 0 | BO24: 0 | BP24: 208 | BQ24: 10400 | BR24: 113 | BS24: 0 | BT24: 1615.07 | BU24: 0 | BV24: 0 | BW24: 0 | CB24: 0 | CC24: 0 | CD24: 0 | CF24: 0 | CH24: 0 | CO24: 0 | CV24: 0 | EL24: 12128.07 | EM24: 12128.07 | EN24: 1212.81 | EO24: 178.28 | EP24: 164.78 | EQ24: 0 | ER24: 0 | ES24: 0 | ET24: 1494 | EU24: 0 | EV24: 0 | EZ24: 831.87 | FA24: 0 | FB24: 52.9 | FC24: 4845.2 | FH24: 0 | FN24: 0 | FO24: 0 | FQ24: 8779.84 | FR24: 3348.23 | FS24: 3348.23 | FU24: 3348.23 | FV24: 3252.83 | FW24: 0 | FX24: 1091.53 | FY24: 0 | GB24: =+EL24-BZ24-CA24-GC24 -> 0 | GC24: 12128.07 | GE24: =+GC24+DF24+CX24+EH24 -> 12128.07
A25: BCP | B25: 20 | C25: ENERO | D25: DNI | E25: 07537953 | F25: SALAZAR DE LA ROCHA JUAN CARLOS | G25: 25978 | H25: GERENCIA GENERAL | I25: OFICINA PRINCIPAL | J25: 01OFP | K25: OFICINA PRINCIPAL | L25: VARIOS | M25: VARIOS | N25: VARIOS | O25: VARIOS | P25: VARIOS | Q25: VARIOS | R25: 001GGE | S25: GERENCIA GENERAL | T25: EJECUTIVO | U25: GERENTE GENERAL | V25: INDETERMINADO | W25: DIRECCIÓN | X25: BCP | Y25: 19436180079033 | AB25: 43003 | AE25: HABITAT | AF25: 259761JSRAH0 | AI25: NETO | AJ25: $ 10500 | AO25: SI | AP25: M | AQ25: SI | AR25: 43869.777 | AS25: 30 | AT25: 0 | AU25: 0 | BI25: 0 | BK25: 0 | BL25: 0 | BM25: 0 | BN25: 0 | BO25: 0 | BP25: 240 | BQ25: 43869.777 | BR25: 113 | BS25: 0 | BT25: 0 | BU25: 0 | BV25: 0 | BW25: 0 | CB25: 0 | CC25: 0 | CD25: 0 | CF25: 0 | CH25: 0 | CO25: 0 | CV25: 0 | CX25: 7330.4629 | CY25: 494.80625 | DW25: 4276.1034 | EL25: 43982.777 | EM25: 56084.15 | EN25: 4398.28 | EO25: 646.55 | EP25: 164.78 | EQ25: 0 | ER25: 0 | ES25: 0 | ET25: 11730.54 | EU25: 0 | EV25: 0 | EZ25: 0 | FA25: 0 | FB25: 699.63 | FC25: 22585.973 | FH25: 0 | FN25: 0 | FO25: 0 | FQ25: 40225.75 | FR25: 15858.4 | FS25: 15858.4 | FT25: 4253.8627 | FU25: 15858.4 | FV25: 15606.52 | FW25: 0 | FX25: 3958.45 | FY25: 0 | GB25: =+EL25-BZ25-CA25-GC25 -> -0.0025360018 | GC25: 43982.78 | GE25: =+GC25+DF25+CX25+EH25 -> 51313.243
A26: BCP | B26: 21 | C26: ENERO | D26: DNI | E26: 42560153 | F26: VALDEZ CRUZ JOSEPH JOSUE | G26: 30917 | H26: OPERACIONES PORTUARIAS | I26: OFICINA PAITA | J26: 05PAI | K26: PAITA | L26: 100002 | M26: Agenciamiento Marítimo | N26: 1 | O26: 001OP | P26: OPERACIONES | Q26: 1 | R26: 004OPP | S26: OPERACIONES PORTUARIAS | T26: EMPLEADO | U26: PROCURADOR MARITIMO PAITA | V26: INDETERMINADO | X26: BANCO DE CREDITO | Y26: 455-90479804-0-78 | AB26: 43222 | AE26: INTEGRA | AF26: 609151JVCDZ8 | AO26: SI | AP26: M | AQ26: NO | AR26: 3000 | AS26: 30 | AT26: 0 | AU26: 0 | BI26: 8 | BK26: 0 | BL26: 0 | BM26: 8 | BN26: 0 | BO26: 0 | BP26: 240 | BQ26: 3000 | BR26: 0 | BS26: 0 | BT26: 0 | BU26: 0 | BV26: 0 | BW26: 0 | CB26: 0 | CC26: 0 | CD26: 200 | CF26: 0 | CH26: 0 | CO26: 200 | CV26: 0 | EL26: 3400 | EM26: 3400 | EN26: 340 | EO26: 52.7 | EP26: 46.58 | EQ26: 0 | ER26: 0 | ES26: 0 | ET26: 65.98 | EU26: 0 | EV26: 0 | EZ26: 0 | FA26: 0 | FB26: 0 | FC26: 1200 | FH26: 0 | FN26: 0 | FO26: 0 | FQ26: 1705.26 | FR26: 1694.74 | FS26: 1694.74 | FU26: 1694.74 | FV26: 1209.42 | FW26: 0 | FX26: 306 | FY26: 0 | GB26: =+EL26-BZ26-CA26-GC26 -> 0 | GC26: 3400 | GE26: =+GC26+DF26+CX26+EH26 -> 3400
A27: BCP | B27: 22 | C27: ENERO | D27: DNI | E27: 47470495 | F27: VILLANTOY GUTIERREZ ANDRES DANIEL | G27: 33862 | H27: OPERACIONES PORTUARIAS | I27: MAGDALENA | J27: 01OFP | K27: OFICINA PRINCIPAL | L27: 100002 | M27: Agenciamiento Marítimo | N27: 1 | O27: 001OP | P27: OPERACIONES | Q27: 1 | R27: 004OPP | S27: OPERACIONES PORTUARIAS | T27: EMPLEADO | U27: PROCURADOR MARITIMO CALLAO | V27: INDETERMINADO | X27: BANCO DE CREDITO | Y27: 192-36160342-0-97 | AB27: 43206 | AE27: HABITAT MIXTA | AF27: 638601AVGLI0 | AO27: NO | AP27: M | AQ27: NO | AR27: 3500 | AS27: 30 | AT27: 0 | AU27: 0 | BI27: 8 | BK27: 0 | BL27: 0 | BM27: 8 | BN27: 0 | BO27: 0 | BP27: 240 | BQ27: 3500 | BR27: 0 | BS27: 0 | BT27: 0 | BU27: 0 | BV27: 0 | BW27: 0 | CB27: 0 | CC27: 0 | CD27: 233.33333 | CF27: 0 | CH27: 0 | CO27: 233.33333 | CV27: 0 | EL27: 3966.6667 | EM27: 3966.6667 | EN27: 396.67 | EO27: 0 | EP27: 54.34 | EQ27: 0 | ER27: 0 | ES27: 0 | ET27: 119.66333 | EU27: 0 | EV27: 0 | EZ27: 0 | FA27: 0 | FB27: 0 | FC27: 1400 | FH27: 0 | FN27: 0 | FO27: 0 | FQ27: 1970.67 | FR27: 1996 | FS27: 1996 | FU27: 1996 | FV27: 1631.42 | FW27: 0 | FX27: 357 | FY27: 0 | GB27: =+EL27-BZ27-CA27-GC27 -> 0.0066666667 | GC27: 3966.66 | GE27: =+GC27+DF27+CX27+EH27 -> 3966.66
A28: BCP | B28: 23 | C28: ENERO | D28: DNI | E28: 74080395 | F28: AVALOS MORANTE KATHERINE ALEXANDRA | G28: 34503 | H28: COMERCIAL | I28: OFICINA PRINCIPAL | J28: 01OFP | K28: OFICINA PRINCIPAL | L28: 100001 | M28: Agenciamiento General | N28: 1 | O28: 003VE | P28: VENTAS | Q28: 1 | R28: 006VEN | S28: COMERCIAL- VENTAS | T28: EMPLEADO | U28: CUSTOMER SERVICE EXPO | V28: INDETERMINADO | X28: BANCO DE CREDITO | Y28: 19338719164064 | AB28: 43497 | AE28: PRIMA MIXTA | AF28: 345010KAMLA9 | AO28: SI | AP28: F | AQ28: NO | AR28: 5000 | AS28: 30 | AT28: 0 | AU28: 0 | BI28: 3 | BK28: 0 | BL28: 0 | BM28: 5 | BN28: 0 | BO28: 0 | BP28: 240 | BQ28: 5000 | BR28: 0 | BS28: 0 | BT28: 0 | BU28: 0 | BV28: 0 | BW28: 0 | CB28: 0 | CC28: 0 | CD28: 125 | CF28: 0 | CH28: 0 | CO28: 208.33333 | CV28: 0 | EL28: 5333.3333 | EM28: 5333.3333 | EN28: 533.33 | EO28: 0 | EP28: 73.07 | EQ28: 0 | ER28: 0 | ES28: 0 | ET28: 301.92667 | EU28: 0 | EV28: 0 | EZ28: 0 | FA28: 0 | FB28: 0 | FC28: 2000 | FH28: 0 | FN28: 0 | FO28: 0 | FQ28: 2908.33 | FR28: 2425 | FS28: 2425 | FU28: 2425 | FV28: 2139.79 | FW28: 0 | FX28: 480 | FY28: 0 | GB28: =+EL28-BZ28-CA28-GC28 -> 0.0033333333 | GC28: 5333.33 | GE28: =+GC28+DF28+CX28+EH28 -> 5333.33
A29: BCP | B29: 24 | C29: ENERO | D29: DNI | E29: 73958636 | F29: ALEJOS EGUSQUIZA AYXA JELUZETH | G29: 36216 | H29: ADMINISTRACIÓN | I29: OFICINA PRINCIPAL | J29: 01OFP | K29: OFICINA PRINCIPAL | L29: 100001 | M29: Agenciamiento General | N29: 1 | O29: 002AD | P29: ADMINISTRACION | Q29: 1 | R29: 012ADM | S29: ADMINISTRACION | T29: EMPLEADO | U29: CUSTOMER SERVICE EXPORTACIÓN | V29: INDETERMINADO | X29: BANCO DE CREDITO | Y29: 191-73188399-0-73 | AB29: 43530 | AE29: PRIMA MIXTA | AF29: 662140AAEJS9 | AO29: SI | AP29: F | AQ29: NO | AR29: 3500 | AS29: 30 | AT29: 0 | AU29: 0 | BI29: 0 | BK29: 0 | BL29: 0 | BM29: 0 | BN29: 0 | BO29: 0 | BP29: 240 | BQ29: 3500 | BR29: 0 | BS29: 0 | BT29: 0 | BU29: 0 | BV29: 0 | BW29: 0 | CB29: 0 | CC29: 0 | CD29: 0 | CF29: 0 | CH29: 0 | CO29: 0 | CV29: 0 | EL29: 3500 | EM29: 3500 | EN29: 350 | EO29: 0 | EP29: 47.95 | EQ29: 0 | ER29: 0 | ES29: 0 | ET29: 80.15 | EU29: 0 | EV29: 0 | EZ29: 0 | FA29: 0 | FB29: 0 | FC29: 1400 | FH29: 0 | FN29: 0 | FO29: 0 | FQ29: 1878.1 | FR29: 1621.9 | FS29: 1621.9 | FU29: 1621.9 | FV29: 1586.81 | FW29: 0 | FX29: 315 | FY29: 0 | GB29: =+EL29-BZ29-CA29-GC29 -> 0 | GC29: 3500 | GE29: =+GC29+DF29+CX29+EH29 -> 3500
A30: BCP | B30: 25 | C30: ENERO | D30: DNI | E30: 71467210 | F30: ANTAYHUA GRABIEL ISAAC ISMAEL | G30: 33313 | H30: CONTABILIDAD | I30: OFICINA PRINCIPAL | J30: 01OFP | K30: OFICINA PRINCIPAL | L30: 100001 | M30: Agenciamiento General | N30: 1 | O30: 002AD | P30: ADMINISTRACION | Q30: 1 | R30: 007CON | S30: CONTABILIDAD | T30: EMPLEADO | U30: ANALISTA CONTABILIDAD | V30: INDETERMINADO | X30: BANCO DE CREDITO | Y30: 191-29235778-0-87 | AB30: 43525 | AE30: HABITAT MIXTA | AF30: 633111IAGAB3 | AO30: SI | AP30: M | AQ30: NO | AR30: 3500 | AS30: 30 | AT30: 0 | AU30: 0 | BI30: 0 | BK30: 0 | BL30: 0 | BM30: 0 | BN30: 0 | BO30: 0 | BP30: 240 | BQ30: 3500 | BR30: 0 | BS30: 0 | BT30: 0 | BU30: 0 | BV30: 0 | BW30: 0 | CB30: 0 | CC30: 0 | CD30: 0 | CF30: 0 | CH30: 0 | CO30: 0 | CV30: 0 | EL30: 3500 | EM30: 3500 | EN30: 350 | EO30: 0 | EP30: 47.95 | EQ30: 0 | ER30: 0 | ES30: 0 | ET30: 80.15 | EU30: 0 | EV30: 0 | EZ30: 0 | FA30: 0 | FB30: 0 | FC30: 1200 | FH30: 0 | FN30: 0 | FO30: 0 | FQ30: 1678.1 | FR30: 1821.9 | FS30: 1821.9 | FU30: 1821.9 | FV30: 1401.09 | FW30: 0 | FX30: 315 | FY30: 0 | GB30: =+EL30-BZ30-CA30-GC30 -> 0 | GC30: 3500 | GE30: =+GC30+DF30+CX30+EH30 -> 3500
A31: BCP DOL | B31: 26 | C31: ENERO | D31: CE | E31: 002120932 | F31: GAME LOAIZA MANUEL XAVIER | G31: 24827 | H31: GERENCIA GENERAL | I31: OFICINA PRINCIPAL | J31: 01OFP | K31: OFICINA PRINCIPAL | L31: 100001/100002 | M31: Agenciamiento General/Agenciamiento Marítimo | N31: 1 | O31: VARIOS | P31: VARIOS | Q31: 1 | R31: 001GGE | S31: GERENCIA GENERAL | T31: EJECUTIVO | U31: PRESIDENTE EJECUTIVO | V31: INDETERMINADO | X31: BCP | Y31: 19199679000156 | AB31: 43678 | AE31: INTEGRA MIXTA | AF31: 548251MGLEI7 | AI31: NETO | AJ31: $ 35000 | AO31: SI | AP31: M | AQ31: NO | AR31: 168044.39 | AS31: 30 | AT31: 0 | AU31: 0 | BI31: 0 | BK31: 0 | BL31: 0 | BM31: 0 | BN31: 0 | BO31: 0 | BP31: 240 | BQ31: 168044.39 | BR31: 0 | BS31: 0 | BT31: 0 | BU31: 0 | BV31: 0 | BW31: 0 | CB31: 0 | CC31: 0 | CD31: 0 | CF31: 0 | CH31: 0 | CO31: 0 | CV31: 0 | CX31: 28007.398 | CY31: 1890.4994 | DW31: 16337.649 | EL31: 168044.39 | EM31: 214279.93 | EN31: 16804.44 | EO31: 0 | EP31: 164.78 | EQ31: 0 | ER31: 0 | ES31: 0 | ET31: 66830.71 | EU31: 0 | EV31: 0 | EZ31: 0 | FA31: 0 | FB31: 0 | FC31: 79186.448 | FH31: 0 | FN31: 0 | FO31: 0 | FQ31: 162986.38 | FR31: 51293.55 | FS31: 51293.55 | FT31: 13758.999 | FU31: 130480 | FV31: 53818.01 | FW31: 0 | FX31: 15123.99 | FY31: 0 | GB31: =+EL31-BZ31-CA31-GC31 -> -0.0016990047 | GC31: 168044.39 | GE31: =+GC31+DF31+CX31+EH31 -> 196051.79
A32: BCP | B32: 27 | C32: ENERO | D32: DNI | E32: 72152204 | F32: HUAMAN COLLANTES WALTER JUNIOR | G32: 34469 | H32: DOCUMENTACIÓN Y VISTO BUENO | I32: MAGDALENA | J32: 01OFP | K32: OFICINA PRINCIPAL | L32: 100002 | M32: Agenciamiento Marítimo | N32: 1 | O32: 001OP | P32: OPERACIONES | Q32: 0 | R32: 003DVB | S32: DOCUMENTACION-VISTO BUENO | T32: EMPLEADO | U32: ANALISTA DE DOCUMENTACIÓN | V32: INDETERMINADO | X32: BCP | Y32: 19195948106076 | AB32: 43724 | AE32: HABITAT MIXTA | AF32: 344671WHCML2 | AO32: SI | AP32: M | AQ32: SI | AR32: 3300 | AS32: 30 | AT32: 0 | AU32: 0 | BI32: 0 | BK32: 0 | BL32: 0 | BM32: 11.5 | BN32: 0 | BO32: 0 | BP32: 240 | BQ32: 3300 | BR32: 113 | BS32: 0 | BT32: 0 | BU32: 0 | BV32: 0 | BW32: 0 | CB32: 0 | CC32: 0 | CD32: 0 | CF32: 0 | CH32: 0 | CO32: 327.07917 | CV32: 0 | EL32: 3740.0792 | EM32: 3740.0792 | EN32: 374.01 | EO32: 0 | EP32: 51.24 | EQ32: 0 | ER32: 0 | ES32: 0 | ET32: 98.896333 | EU32: 0 | EV32: 0 | EZ32: 240.32 | FA32: 0 | FB32: 0 | FC32: 1365.2 | FH32: 0 | FN32: 0 | FO32: 0 | FQ32: 2129.67 | FR32: 1610.41 | FS32: 1610.41 | FU32: 1610.41 | FV32: 1267.06 | FW32: 0 | FX32: 336.61 | FY32: 0 | GB32: =+EL32-BZ32-CA32-GC32 -> -0.00083333333 | GC32: 3740.08 | GE32: =+GC32+DF32+CX32+EH32 -> 3740.08
A33: BCP | B33: 28 | C33: ENERO | D33: DNI | E33: 72900856 | F33: TORRES ALEGRIA JUAN LUIS | G33: 34058 | H33: COMERCIAL | I33: OFICINA PRINCIPAL | J33: 01OFP | K33: OFICINA PRINCIPAL | L33: 100001 | M33: Agenciamiento General | N33: 1 | O33: 003VE | P33: VENTAS | Q33: 1 | R33: 006VEN | S33: COMERCIAL- VENTAS | T33: EMPLEADO | U33: CUSTOMER SERVICE EXPO | V33: INDETERMINADO | X33: BCP | Y33: 193-91572371-0-42 | AB33: 43845 | AE33: HABITAT MIXTA | AF33: 340561JTARG0 | AO33: SI | AP33: M | AQ33: NO | AR33: 3600 | AS33: 30 | AT33: 0 | AU33: 0 | BI33: 0 | BK33: 0 | BL33: 0 | BM33: 0 | BN33: 0 | BO33: 0 | BP33: 240 | BQ33: 3600 | BR33: 0 | BS33: 0 | BT33: 0 | BU33: 0 | BV33: 0 | BW33: 0 | CB33: 0 | CC33: 0 | CD33: 0 | CF33: 0 | CH33: 0 | CO33: 0 | CV33: 0 | EL33: 3600 | EM33: 3600 | EN33: 360 | EO33: 0 | EP33: 49.32 | EQ33: 0 | ER33: 0 | ES33: 0 | ET33: 89.57 | EU33: 0 | EV33: 0 | EZ33: 0 | FA33: 34.8 | FB33: 0 | FC33: 1440 | FH33: 0 | FN33: 0 | FO33: 0 | FQ33: 1973.69 | FR33: 1626.31 | FS33: 1626.31 | FU33: 1626.31 | FV33: 1441.11 | FW33: 0 | FX33: 324 | FY33: 0 | GB33: =+EL33-BZ33-CA33-GC33 -> 0 | GC33: 3600 | GE33: =+GC33+DF33+CX33+EH33 -> 3600
A34: BCP | B34: 29 | C34: ENERO | D34: DNI | E34: 42326063 | F34: MARTI ROJAS ANGELA TERESA | G34: 30780 | H34: COMERCIAL | I34: OFICINA PRINCIPAL | J34: 01OFP | K34: OFICINA PRINCIPAL | L34: 100001 | M34: Agenciamiento General | N34: 1 | O34: 003VE | P34: VENTAS | Q34: 1 | R34: 006VEN | S34: COMERCIAL- VENTAS | T34: EMPLEADO | U34: ASESOR COMERCIAL EXPO E IMPO | V34: INDETERMINADO | X34: BCP | Y34: 19390718162004 | AB34: 43900 | AE34: INTEGRA | AF34: 607780ADRGA6 | AO34: SI | AP34: F | AQ34: SI | AR34: 13500 | AS34: 30 | AT34: 0 | AU34: 0 | BI34: 0 | BK34: 0 | BL34: 0 | BM34: 0 | BN34: 0 | BO34: 0 | BP34: 240 | BQ34: 13500 | BR34: 113 | BS34: 0 | BT34: 0 | BU34: 0 | BV34: 0 | BW34: 0 | CB34: 0 | CC34: 0 | CD34: 0 | CF34: 0 | CH34: 0 | CO34: 0 | CV34: 0 | EL34: 13613 | EM34: 13613 | EN34: 1361.3 | EO34: 211 | EP34: 164.78 | EQ34: 0 | ER34: 0 | ES34: 0 | ET34: 1794.15 | EU34: 0 | EV34: 0 | EZ34: 222.81 | FA34: 0 | FB34: 149.44 | FC34: 5445.2 | FH34: 0 | FN34: 0 | FO34: 0 | FQ34: 9348.68 | FR34: 4264.32 | FS34: 4264.32 | FU34: 4264.32 | FV34: 4327.27 | FW34: 0 | FX34: 1225.17 | FY34: 0 | GB34: =+EL34-BZ34-CA34-GC34 -> 0 | GC34: 13613 | GE34: =+GC34+DF34+CX34+EH34 -> 13613
A35: BCP | B35: 30 | C35: ENERO | D35: DNI | E35: 71569497 | F35: CAMPOS PALOMINO DIANA MARGARITA | G35: 33826 | H35: DOCUMENTACIÓN Y VISTO BUENO | I35: MAGDALENA | J35: 01OFP | K35: OFICINA PRINCIPAL | L35: 100002 | M35: Agenciamiento Marítimo | N35: 1 | O35: 001OP | P35: OPERACIONES | Q35: 0 | R35: 003DVB | S35: DOCUMENTACION-VISTO BUENO | T35: EMPLEADO | U35: ASISTENTE DE VISTO BUENO Y FACTURACIÓN | V35: INDETERMINADO | X35: BCP | Y35: 19178785208016 | AB35: 43973 | AE35: PROFUTURO MIXTA | AF35: 338240DCPPO2 | AO35: SI | AP35: F | AQ35: NO | AR35: 2200 | AS35: 30 | AT35: 0 | AU35: 0 | BI35: 0 | BK35: 0 | BL35: 0 | BM35: 0 | BN35: 0 | BO35: 0 | BP35: 240 | BQ35: 2200 | BR35: 0 | BS35: 0 | BT35: 0 | BU35: 0 | BV35: 0 | BW35: 0 | CA35: 0 | CB35: 0 | CC35: 0 | CD35: 0 | CF35: 0 | CH35: 0 | CO35: 0 | CV35: 0 | EL35: 2200 | EM35: 2200 | EN35: 220 | EO35: 0 | EP35: 30.14 | EQ35: 0 | ER35: 0 | ES35: 0 | ET35: 0 | EU35: 0 | EV35: 0 | EZ35: 0 | FA35: 0 | FB35: 0 | FC35: 880 | FH35: 0 | FN35: 0 | FO35: 0 | FQ35: 1130.14 | FR35: 1069.86 | FS35: 1069.86 | FU35: 1069.86 | FV35: 873.36 | FW35: 0 | FX35: 198 | FY35: 0 | GB35: =+EL35-BZ35-CA35-GC35 -> 0 | GC35: 2200 | GE35: =+GC35+DF35+CX35+EH35 -> 2200
A36: BCP | B36: 31 | C36: ENERO | D36: DNI | E36: 25828090 | F36: CHERO ORTIZ MARTIN ALEJANDRO | G36: 27851 | H36: COST CONTROLLER | I36: MAGDALENA | J36: 01OFP | K36: OFICINA PRINCIPAL | L36: 100002 | M36: Agenciamiento Marítimo | N36: 0 | O36: 001OP | P36: OPERACIONES | Q36: 1 | R36: 002CCO | S36: COST CONTROLER | T36: EMPLEADO | U36: ANALISTA DE CONTROL DE COSTO | V36: POR INCREMENTO DE ACTIVIDADES | X36: BCP | Y36: 193-92060663-0-67 | AB36: 44111 | AE36: PRIMA | AF36: 578491MCORI0 | AO36: NO | AP36: M | AQ36: SI | AR36: 3600 | AS36: 29 | AT36: 0 | AU36: 1 | BI36: 0 | BK36: 0 | BL36: 0 | BM36: 0 | BN36: 0 | BO36: 0 | BP36: 232 | BQ36: 3480 | BR36: 113 | BS36: 0 | BT36: 123.77 | BU36: 0 | BV36: 0 | BW36: 0 | CB36: 0 | CC36: 0 | CD36: 0 | CF36: 0 | CH36: 0 | CO36: 0 | CV36: 0 | EL36: 3716.77 | EM36: 3716.77 | EN36: 371.68 | EO36: 59.47 | EP36: 50.92 | EQ36: 0 | ER36: 0 | ES36: 0 | ET36: 101.36 | EU36: 0 | EV36: 0 | EZ36: 0 | FA36: 0 | FB36: 0 | FC36: 1485.2 | FH36: 333.33 | FN36: 0 | FO36: 0 | FQ36: 2401.96 | FR36: 1314.81 | FS36: 1314.81 | FU36: 1314.81 | FV36: 1445.25 | FW36: 0 | FX36: 334.51 | FY36: 0 | GB36: =+EL36-BZ36-CA36-GC36 -> 0 | GC36: 3716.77 | GE36: =+GC36+DF36+CX36+EH36 -> 3716.77
A37: BCP | B37: 32 | C37: ENERO | D37: DNI | E37: 43643490 | F37: ESPINOZA RUA KARINNA ESPERANZA | G37: 31567 | H37: TALENTO HUMANO | I37: MAGDALENA | J37: 01OFP | K37: OFICINA PRINCIPAL | L37: 100001 | M37: Agenciamiento General | N37: 1 | O37: 002AD | P37: ADMINISTRACION | Q37: 1 | R37: 010TAH | S37: TALENTO HUMANO | T37: EMPLEADO | U37: JEFE DE TALENTO HUMANO | V37: INDETERMINADO | W37: CONFIANZA | X37: BCP | Y37: 193-14869847-0-45 | AB37: 44348 | AE37: PRIMA | AF37: 615650KERIA1 | AO37: SI | AP37: F | AQ37: SI | AR37: 6900 | AS37: 30 | AT37: 0 | AU37: 0 | BI37: 0 | BK37: 0 | BL37: 0 | BM37: 0 | BN37: 0 | BO37: 0 | BP37: 240 | BQ37: 6900 | BR37: 113 | BS37: 0 | BT37: 0 | BU37: 0 | BV37: 0 | BW37: 0 | CB37: 0 | CC37: 0 | CD37: 0 | CF37: 0 | CH37: 9 | CO37: 0 | CV37: 0 | EL37: 7022 | EM37: 7022 | EN37: 702.2 | EO37: 112.35 | EP37: 96.2 | EQ37: 0 | ER37: 0 | ES37: 0 | ET37: 587.13 | EU37: 0 | EV37: 0 | EZ37: 231.42 | FA37: 81.08 | FB37: 0 | FC37: 2805.2 | FH37: 0 | FN37: 9 | FO37: 4 | FQ37: 4628.58 | FR37: 2393.42 | FS37: 2393.42 | FU37: 2393.42 | FV37: 2339.18 | FW37: 0 | FX37: 631.98 | FY37: 0 | GB37: =+EL37-BZ37-CA37-GC37 -> 0 | GC37: 7022 | GE37: =+GC37+DF37+CX37+EH37 -> 7022
A38: BCP | B38: 33 | C38: ENERO | D38: DNI | E38: 72016504 | F38: GUTIERREZ DE LA CRUZ MIGUEL ANGEL | G38: 33721 | H38: DOCUMENTACIÓN Y VISTO BUENO | I38: MAGDALENA | J38: 01OFP | K38: OFICINA PRINCIPAL | L38: 100002 | M38: Agenciamiento Marítimo | N38: 1 | O38: 001OP | P38: OPERACIONES | Q38: 0 | R38: 003DVB | S38: DOCUMENTACION-VISTO BUENO | T38: EMPLEADO | U38: ASISTENTE DE DOCUMENTACIÓN | V38: POR INCREMENTO DE ACTIVIDADES | X38: INTERBANK | Y38: 00353001325448988532 | AB38: 44432 | AE38: HABITAT MIXTA | AF38: 637191MGCIZ6 | AO38: SI | AP38: M | AQ38: SI | AR38: 2200 | AS38: 30 | AT38: 0 | AU38: 0 | BI38: 0 | BK38: 0 | BL38: 0 | BM38: 5 | BN38: 0 | BO38: 0 | BP38: 240 | BQ38: 2200 | BR38: 113 | BS38: 0 | BT38: 0 | BU38: 0 | BV38: 0 | BW38: 0 | CB38: 0 | CC38: 0 | CD38: 0 | CF38: 0 | CH38: 0 | CO38: 96.375 | CV38: 0 | EL38: 2409.375 | EM38: 2409.375 | EN38: 240.94 | EO38: 0 | EP38: 33.01 | EQ38: 0 | ER38: 0 | ES38: 0 | ET38: 0 | EU38: 0 | EV38: 0 | EZ38: 115.71 | FA38: 0 | FB38: 0 | FC38: 925.2 | FH38: 0 | FN38: 0 | FO38: 0 | FQ38: 1314.86 | FR38: 1094.52 | FS38: 1094.52 | FU38: 1094.52 | FV38: 977.93 | FW38: 0 | FX38: 216.84 | FY38: 0 | GB38: =+EL38-BZ38-CA38-GC38 -> -0.005 | GC38: 2409.38 | GE38: =+GC38+DF38+CX38+EH38 -> 2409.38
